Workbook

Sheet OPENING STOCK
A1: Mahavishnu | C1: OPENING STOCK
C2: 750 ML | E2: 375 ML | G2: 180 ML | I2: 90 ML | K2: 60 ML
A3: SL. | B3: PRODUCT NAME | C3: CASES*12 | D3: BTLS | E3: CASES*24 | F3: BTLS | G3: CASES*48 | H3: BTLS | I3: CASES*96 | J3: BTLS | K3: BOX*25 | L3: BTLS
A4: 1 | B4: ='SALES & RATE'!B4 -> M H BRANDY | C4: 0 | D4: 10 | E4: 0 | F4: 11 | G4: 8 | H4: 41 | I4: 6 | J4: 70 | K4: 0 | L4: 0
A5: 2 | B5: ='SALES & RATE'!B5 -> MC BRANDY | C5: 0 | D5: 14 | E5: 1 | F5: 11 | G5: 10 | H5: 97 | I5: 6 | J5: 72 | K5: 0 | L5: 0
A6: 3 | B6: ='SALES & RATE'!B6 -> O.C.BRANDY | C6: 0 | D6: 0 | E6: 0 | F6: 0 | G6: 2 | H6: 89 | I6: 5 | J6: 42 | K6: 0 | L6: 0
A7: 4 | B7: ='SALES & RATE'!B7 -> AMRUT SILVER CUP | C7: 0 | D7: 0 | E7: 0 | F7: 0 | G7: 8 | H7: 46 | I7: 1 | J7: 2 | K7: 0 | L7: 0
A8: 5 | B8: ='SALES & RATE'!B8 -> HONEY BEE BRANDY | C8: 0 | D8: 0 | E8: 0 | F8: 0 | G8: 0 | H8: 26 | I8: 0 | J8: 54 | K8: 0 | L8: 0
A9: 6 | B9: ='SALES & RATE'!B9 -> O A BRANDY | C9: 0 | D9: 3 | E9: 0 | F9: 0 | G9: 1 | H9: 92 | I9: 3 | J9: 61 | K9: 0 | L9: 0
A10: 7 | B10: ='SALES & RATE'!B10 -> BEJOIS BRANDY | C10: 0 | D10: 6 | E10: 0 | F10: 0 | G10: 6 | H10: 59 | I10: 7 | J10: 19 | K10: 0 | L10: 0
A11: 8 | B11: ='SALES & RATE'!B11 -> MORPHIS BRANDY | C11: 0 | D11: 0 | E11: 0 | F11: 0 | G11: 0 | H11: 35 | I11: 0 | J11: 0 | K11: 0 | L11: 33
A12: 9 | B12: ='SALES & RATE'!B12 -> M C WHISKY | C12: 0 | D12: 10 | E12: 0 | F12: 15 | G12: 1 | H12: 52 | I12: 1 | J12: 95 | K12: 0 | L12: 0
A13: 10 | B13: ='SALES & RATE'!B13 -> BAGPIPER (W) | C13: 0 | D13: 11 | E13: 0 | F13: 9 | G13: 16 | H13: 51 | I13: 4 | J13: 49 | K13: 0 | L13: 0
A14: 11 | B14: ='SALES & RATE'!B14 -> SIGNATURE (W) | C14: 0 | D14: 0 | E14: 0 | F14: 0 | G14: 0 | H14: 31 | I14: 0 | J14: 0 | K14: 0 | L14: 0
A15: 12 | B15: ='SALES & RATE'!B15 -> O T WHISKY | C15: 0 | D15: 0 | E15: 0 | F15: 0 | G15: 2 | H15: 23 | I15: 0 | J15: 99 | K15: 0 | L15: 0
... A50: 47 | B50: ='SALES & RATE'!B50 -> 0 | C50: 0 | D50: 0 | E50: 0 | F50: 0 | G50: 0 | H50: 0 | I50: 0 | J50: 0 | K50: 0 | L50: 0
A51: Mahavishnu PAGE 2 | C51: OPENING STOCK PAGE 2
C52: 750 ML | E52: 375 ML | G52: 180 ML | I52: 90 ML | K52: 60 ML
A53: SL. | B53: PRODUCT NAME | C53: CASES*12 | D53: BTLS | E53: CASES*24 | F53: BTLS | G53: CASES*48 | H53: BTLS | I53: CASES*96 | J53: BTLS | K53: BOX*25 | L53: BTLS
A54: 1 | B54: ='SALES & RATE'!B54 -> CARNIVAL GIN | C54: 0 | D54: 0 | E54: 0 | F54: 0 | G54: 1 | H54: 16 | I54: 0 | J54: 82 | K54: 0 | L54: 0
A55: 2 | B55: ='SALES & RATE'!B55 -> SMIRNOFF VODKA | C55: 0 | D55: 4 | E55: 0 | F55: 0 | G55: 0 | H55: 59 | I55: 0 | J55: 0 | K55: 0 | L55: 20
A56: 3 | B56: ='SALES & RATE'!B56 -> MUSCOVY LEMON | C56: 0 | D56: 0 | E56: 0 | F56: 0 | G56: 0 | H56: 48 | I56: 0 | J56: 0 | K56: 0 | L56: 0
A57: 4 | B57: ='SALES & RATE'!B57 -> MUSCOVY VODKA | C57: 0 | D57: 0 | E57: 0 | F57: 0 | G57: 2 | H57: 89 | I57: 0 | J57: 95 | K57: 0 | L57: 0
A58: 5 | B58: ='SALES & RATE'!B58 -> ROMANOV VODKA | C58: 0 | D58: 0 | E58: 0 | F58: 0 | G58: 1 | H58: 56 | I58: 0 | J58: 96 | K58: 0 | L58: 0
A59: 6 | B59: ='SALES & RATE'!B59 -> GONAS WINE | C59: 0 | D59: 0 | E59: 0 | F59: 0 | G59: 0 | H59: 39 | I59: 0 | J59: 0 | K59: 0 | L59: 0
A60: 7 | B60: ='SALES & RATE'!B60 -> MAGIC PORT WINE | C60: 0 | D60: 20 | E60: 0 | F60: 24 | G60: 0 | H60: 12 | I60: 0 | J60: 0 | K60: 0 | L60: 0
A61: 8 | B61: ='SALES & RATE'!B61 -> SIDDUS WINE | C61: 0 | D61: 1 | E61: 0 | F61: 1 | G61: 0 | H61: 34 | I61: 0 | J61: 0 | K61: 0 | L61: 0
A62: 9 | B62: ='SALES & RATE'!B62 -> VEGA WINE | C62: 0 | D62: 0 | E62: 0 | F62: 13 | G62: 0 | H62: 0 | I62: 0 | J62: 0 | K62: 0 | L62: 0
A63: 10 | B63: ='SALES & RATE'!B63 -> 0 | C63: 0 | D63: 0 | E63: 0 | F63: 0 | G63: 0 | H63: 0 | I63: 0 | J63: 0 | K63: 0 | L63: 0
A64: 11 | B64: ='SALES & RATE'!B64 -> MAGIC MOMENTS | C64: 0 | D64: 2 | E64: 0 | F64: 0 | G64: 0 | H64: 0 | I64: 0 | J64: 0 | K64: 0 | L64: 6
A65: 12 | B65: ='SALES & RATE'!B65 -> BRO CODE | C65: 0 | D65: 0 | E65: 0 | F65: 26 | G65: 0 | H65: 0 | I65: 0 | J65: 0 | K65: 0 | L65: 0
... A71: 18 | B71: ='SALES & RATE'!B71 -> 0 | C71: 0 | D71: 0 | E71: 0 | F71: 0 | G71: 0 | H71: 0 | I71: 0 | J71: 0 | K71: 0 | L71: 0
A72: BEERS | C72: OPENING STOCK
C73: 650 ML | E73: 500 ML TIN(CAN) | G73: 330 ML (PINT) | I73: 330 ML TIN(CAN) | M73: PREVIOUS CLOSINGS
A74: SL. | B74: PRODUCT NAME | C74: CASES*12 | D74: BTLS | E74: CASES*24 | F74: BTLS | G74: CASES*24 | H74: BTLS | I74: CASES*24 | J74: BTLS | M74: PREV. CREDIT BILLS
A75: 1 | B75: ='SALES & RATE'!B75 -> K.F PREMIUM | C75: 1 | D75: 15 | E75: 0 | F75: 0 | G75: 0 | H75: 0 | I75: 0 | J75: 0 | M75: 93990
A76: 2 | B76: ='SALES & RATE'!B76 -> K.F STRONG | C76: 47 | D76: 32 | E76: 0 | F76: 1 | G76: 0 | H76: 0 | I76: 0 | J76: 0 | M76: PREV. GALLA CASH
A77: 3 | B77: ='SALES & RATE'!B77 -> U.B EXPORT | C77: 1 | D77: 28 | E77: 0 | F77: 0 | G77: 0 | H77: 0 | I77: 0 | J77: 0 | M77: 24950
A78: 4 | B78: ='SALES & RATE'!B78 -> KNOCK OUT | C78: 0 | D78: 0 | E78: 0 | F78: 0 | G78: 1 | H78: 10 | I78: 0 | J78: 0 | M78: PREV. CIGRETE
A79: 5 | B79: ='SALES & RATE'!B79 -> K.F STROM | C79: 0 | D79: 0 | E79: 0 | F79: 0 | G79: 0 | H79: 0 | I79: 0 | J79: 0 | M79: 35135
A80: 6 | B80: ='SALES & RATE'!B80 -> BUDWISER MAGNUM | C80: 8 | D80: 39 | E80: 0 | F80: 34 | G80: 0 | H80: 0 | I80: 0 | J80: 0
A81: 7 | B81: ='SALES & RATE'!B81 -> BUDWISER PREM | C81: 0 | D81: 2 | E81: 0 | F81: 24 | G81: 0 | H81: 0 | I81: 0 | J81: 0
A82: 8 | B82: ='SALES & RATE'!B82 -> K.F ULTRA/ WITT BEER | C82: 0 | D82: 22 | E82: 0 | F82: 0 | G82: 0 | H82: 0 | I82: 0 | J82: 0
A83: 9 | B83: ='SALES & RATE'!B83 -> TOBURG STRONG BEER | C83: 24 | D83: 21 | E83: 1 | F83: 14 | G83: 0 | H83: 0 | I83: 0 | J83: 0
A84: 10 | B84: ='SALES & RATE'!B84 -> POWERCOOL | C84: 3 | D84: 24 | E84: 0 | F84: 22 | G84: 0 | H84: 7 | I84: 0 | J84: 0
A85: 11 | B85: ='SALES & RATE'!B85 -> BACARDI + | C85: 0 | D85: 0 | E85: 0 | F85: 0 | G85: 3 | H85: 27 | I85: 0 | J85: 0
A86: 12 | B86: ='SALES & RATE'!B86 -> BACARDI BREEZER | C86: 0 | D86: 0 | E86: 0 | F86: 0 | G86: 0 | H86: 26 | I86: 0 | J86: 0
A87: 13 | B87: ='SALES & RATE'!B87 -> RC / BULLET BEER | C87: 2 | D87: 17 | E87: 0 | F87: 22 | G87: 0 | H87: 0 | I87: 0 | J87: 0
A88: 14 | B88: ='SALES & RATE'!B88 -> HUNTER | C88: 0 | D88: 0 | E88: 0 | F88: 0 | G88: 0 | H88: 0 | I88: 0 | J88: 0
A89: 15 | B89: ='SALES & RATE'!B89 -> CARLSBERG ELE STRONG | C89: 0 | D89: 4 | E89: 0 | F89: 0 | G89: 0 | H89: 0 | I89: 0 | J89: 0
A90: 16 | B90: ='SALES & RATE'!B90 -> SUNNY STRONG | C90: 0 | D90: 0 | E90: 0 | F90: 0 | G90: 0 | H90: 0 | I90: 0 | J90: 0
A91: 17 | B91: ='SALES & RATE'!B91 -> FOSTERS BEER | C91: 0 | D91: 0 | E91: 0 | F91: 0 | G91: 0 | H91: 0 | I91: 0 | J91: 0
... A94: 20 | B94: ='SALES & RATE'!B94 -> 0 | C94: 0 | D94: 0 | E94: 0 | F94: 0 | G94: 0 | H94: 0 | I94: 0 | J94: 0
A95: BEVERAGES | C95: OPENING STOCK
C96: 2 LTRS | E96: 1 LTRS | G96: 500 ML-600 ML | I96: 250 ML
A97: SL. | B97: PRODUCT NAME | C97: CASES*9 | D97: BTLS | E97: CASES*12 | F97: BTLS | G97: CASES*24 | H97: BTLS | I97: CASES*30 | J97: BTLS
A98: 1 | B98: ='SALES & RATE'!B98 -> COOL DRINKS | C98: 0 | D98: 0 | E98: 0 | F98: 0 | G98: 5 | H98: 116 | I98: 2 | J98: 82 | M98: PREV.CASH IN LOCKER
A99: 2 | B99: ='SALES & RATE'!B99 -> SODA*12/REDBULL*24 | C99: 0 | D99: 0 | E99: 0 | F99: 0 | G99: 2 | H99: 10 | I99: 0 | J99: 6 | M99: 65000
A100: 3 | B100: ='SALES & RATE'!B100 -> MIN WATER | C100: 10 | D100: 21 | E100: 10 | F100: 30 | G100: 2 | H100: 98 | I100: 0 | J100: 0

Sheet RECIEPTS
A1: Mahavishnu | C1: RECIEPTS INVOICE
C2: 750 ML | D2: 375 ML | E2: 180 ML | F2: 90 ML | G2: 60 ML
A3: SL. | B3: PRODUCT NAME | C3: CASES*12 | D3: CASES*24 | E3: CASES*48 | F3: CASES*96 | G3: BOX*25
A4: 1 | B4: ='SALES & RATE'!B4 -> M H BRANDY | C4: 0 | D4: 1 | E4: 2 | F4: 1 | G4: 0
A5: 2 | B5: ='SALES & RATE'!B5 -> MC BRANDY | C5: 0 | D5: 0 | E5: 2 | F5: 1 | G5: 0
A6: 3 | B6: ='SALES & RATE'!B6 -> O.C.BRANDY | C6: 0 | D6: 0 | E6: 4 | F6: 0 | G6: 0
A7: 4 | B7: ='SALES & RATE'!B7 -> AMRUT SILVER CUP | C7: 0 | D7: 0 | E7: 0 | F7: 5 | G7: 0
A8: 5 | B8: ='SALES & RATE'!B8 -> HONEY BEE BRANDY | C8: 0 | D8: 0 | E8: 0 | F8: 0 | G8: 0
A9: 6 | B9: ='SALES & RATE'!B9 -> O A BRANDY | C9: 0 | D9: 0 | E9: 2 | F9: 1 | G9: 0
A10: 7 | B10: ='SALES & RATE'!B10 -> BEJOIS BRANDY | C10: 0 | D10: 0 | E10: 2 | F10: 0 | G10: 0
A11: 8 | B11: ='SALES & RATE'!B11 -> MORPHIS BRANDY | C11: 0 | D11: 0 | E11: 0 | F11: 0 | G11: 0
A12: 9 | B12: ='SALES & RATE'!B12 -> M C WHISKY | C12: 0 | D12: 0 | E12: 1 | F12: 0 | G12: 0
A13: 10 | B13: ='SALES & RATE'!B13 -> BAGPIPER (W) | C13: 0 | D13: 0 | E13: 0 | F13: 2 | G13: 0
A14: 11 | B14: ='SALES & RATE'!B14 -> SIGNATURE (W) | C14: 0 | D14: 0 | E14: 0 | F14: 0 | G14: 0
A15: 12 | B15: ='SALES & RATE'!B15 -> O T WHISKY | C15: 0 | D15: 0 | E15: 0 | F15: 0 | G15: 0
... A50: 47 | B50: ='SALES & RATE'!B50 -> 0 | C50: 0 | D50: 0 | E50: 0 | F50: 0 | G50: 0
A51: Mahavishnu PAGE 2 | C51: RECIEPTS INVOICE
C52: 750 ML | D52: 375 ML | E52: 180 ML | F52: 90 ML | G52: 60 ML
A53: SL. | B53: PRODUCT NAME | C53: CASES*12 | D53: CASES*24 | E53: CASES*48 | F53: CASES*96 | G53: BOX*25
A54: 1 | B54: ='SALES & RATE'!B54 -> CARNIVAL GIN | C54: 0 | D54: 0 | E54: 0 | F54: 0 | G54: 0
A55: 2 | B55: ='SALES & RATE'!B55 -> SMIRNOFF VODKA | C55: 0 | D55: 0 | E55: 0 | F55: 0 | G55: 0
A56: 3 | B56: ='SALES & RATE'!B56 -> MUSCOVY LEMON | C56: 0 | D56: 0 | E56: 0 | F56: 0 | G56: 0
A57: 4 | B57: ='SALES & RATE'!B57 -> MUSCOVY VODKA | C57: 0 | D57: 0 | E57: 2 | F57: 1 | G57: 0
A58: 5 | B58: ='SALES & RATE'!B58 -> ROMANOV VODKA | C58: 0 | D58: 0 | E58: 0 | F58: 1 | G58: 0
A59: 6 | B59: ='SALES & RATE'!B59 -> GONAS WINE | C59: 0 | D59: 0 | E59: 0 | F59: 0 | G59: 0
A60: 7 | B60: ='SALES & RATE'!B60 -> MAGIC PORT WINE | C60: 0 | D60: 0 | E60: 0 | F60: 0 | G60: 0
A61: 8 | B61: ='SALES & RATE'!B61 -> SIDDUS WINE | C61: 0 | D61: 0 | E61: 0 | F61: 0 | G61: 0
A62: 9 | B62: ='SALES & RATE'!B62 -> VEGA WINE | C62: 0 | D62: 0 | E62: 0 | F62: 0 | G62: 0
A63: 10 | B63: ='SALES & RATE'!B63 -> 0 | C63: 0 | D63: 0 | E63: 0 | F63: 0 | G63: 0
A64: 11 | B64: ='SALES & RATE'!B64 -> MAGIC MOMENTS | C64: 0 | D64: 0 | E64: 1 | F64: 0 | G64: 1
A65: 12 | B65: ='SALES & RATE'!B65 -> BRO CODE | C65: 0 | D65: 0 | E65: 0 | F65: 0 | G65: 0
... A71: 18 | B71: ='SALES & RATE'!B71 -> 0 | C71: 0 | D71: 0 | E71: 0 | F71: 0 | G71: 0
A72: BEERS | C72: RECIEPTS INVOICE
C73: 650 ML | D73: 500 CAN | E73: 330 PINT | F73: 330 CAN
A74: SL. | B74: PRODUCT NAME | C74: CASES*12 | D74: CASES*24 | E74: CASES*24 | F74: CASES*24
A75: 1 | B75: ='SALES & RATE'!B75 -> K.F PREMIUM | C75: 0 | D75: 0 | E75: 0 | F75: 0
A76: 2 | B76: ='SALES & RATE'!B76 -> K.F STRONG | C76: 50 | D76: 2 | E76: 3 | F76: 1
A77: 3 | B77: ='SALES & RATE'!B77 -> U.B EXPORT | C77: 0 | D77: 0 | E77: 0 | F77: 0
A78: 4 | B78: ='SALES & RATE'!B78 -> KNOCK OUT | C78: 5 | D78: 0 | E78: 0 | F78: 0
A79: 5 | B79: ='SALES & RATE'!B79 -> K.F STROM | C79: 0 | D79: 0 | E79: 0 | F79: 0
A80: 6 | B80: ='SALES & RATE'!B80 -> BUDWISER MAGNUM | C80: 20 | D80: 0 | E80: 0 | F80: 0
A81: 7 | B81: ='SALES & RATE'!B81 -> BUDWISER PREM | C81: 3 | D81: 0 | E81: 0 | F81: 0
A82: 8 | B82: ='SALES & RATE'!B82 -> K.F ULTRA/ WITT BEER | C82: 0 | D82: 0 | E82: 0 | F82: 0
A83: 9 | B83: ='SALES & RATE'!B83 -> TOBURG STRONG BEER | C83: 0 | D83: 0 | E83: 3 | F83: 0
A84: 10 | B84: ='SALES & RATE'!B84 -> POWERCOOL | C84: 4 | D84: 0 | E84: 0 | F84: 0
A85: 11 | B85: ='SALES & RATE'!B85 -> BACARDI + | C85: 0 | D85: 0 | E85: 0 | F85: 0
A86: 12 | B86: ='SALES & RATE'!B86 -> BACARDI BREEZER | C86: 0 | D86: 0 | E86: 0 | F86: 0
... A94: 20 | B94: ='SALES & RATE'!B94 -> 0 | C94: 0 | D94: 0 | E94: 0 | F94: 0
A95: BEVERAGES | C95: RECIEPTS INVOICE
C96: 2 LTRS | D96: 1 LTRS | E96: 0.5-0.6L | F96: 0.3-.25L
A97: SL. | B97: PRODUCT NAME | C97: CASES*9 | D97: CASES*12 | E97: CASES*24 | F97: CASES*30
A98: 1 | B98: ='SALES & RATE'!B98 -> COOL DRINKS | C98: 0 | D98: 0 | E98: 1 | F98: 10
A99: 2 | B99: ='SALES & RATE'!B99 -> SODA*12/REDBULL*24 | C99: 0 | D99: 0 | E99: 10 | F99: 1
A100: 3 | B100: ='SALES & RATE'!B100 -> MIN WATER | C100: 5 | D100: 60 | E100: 25 | F100: 0

Sheet TOTAL STOCK
A1: Mahavishnu | C1: TOTAL STOCK
C2: 750 ML | E2: 375 ML | G2: 180 ML | I2: 90 ML | K2: 60 ML
A3: SL. | B3: PRODUCT NAME | C3: CASES*12 | D3: BTLS | E3: CASES*24 | F3: BTLS | G3: CASES*48 | H3: BTLS | I3: CASES*96 | J3: BTLS | K3: BOX*25 | L3: BTLS
A4: 1 | B4: ='SALES & RATE'!B4 -> M H BRANDY | C4: ='OPENING STOCK'!C4+RECIEPTS!C4 -> 0 | D4: ='OPENING STOCK'!D4 -> 10 | E4: ='OPENING STOCK'!E4+RECIEPTS!D4 -> 1 | F4: ='OPENING STOCK'!F4 -> 11 | G4: ='OPENING STOCK'!G4+RECIEPTS!E4 -> 10 | H4: ='OPENING STOCK'!H4 -> 41 | I4: ='OPENING STOCK'!I4+RECIEPTS!F4 -> 7 | J4: ='OPENING STOCK'!J4 -> 70 | K4: ='OPENING STOCK'!K4+RECIEPTS!G4 -> 0 | L4: ='OPENING STOCK'!L4 -> 0
A5: 2 | B5: ='SALES & RATE'!B5 -> MC BRANDY | C5: ='OPENING STOCK'!C5+RECIEPTS!C5 -> 0 | D5: ='OPENING STOCK'!D5 -> 14 | E5: ='OPENING STOCK'!E5+RECIEPTS!D5 -> 1 | F5: ='OPENING STOCK'!F5 -> 11 | G5: ='OPENING STOCK'!G5+RECIEPTS!E5 -> 12 | H5: ='OPENING STOCK'!H5 -> 97 | I5: ='OPENING STOCK'!I5+RECIEPTS!F5 -> 7 | J5: ='OPENING STOCK'!J5 -> 72 | K5: ='OPENING STOCK'!K5+RECIEPTS!G5 -> 0 | L5: ='OPENING STOCK'!L5 -> 0
A6: 3 | B6: ='SALES & RATE'!B6 -> O.C.BRANDY | C6: ='OPENING STOCK'!C6+RECIEPTS!C6 -> 0 | D6: ='OPENING STOCK'!D6 -> 0 | E6: ='OPENING STOCK'!E6+RECIEPTS!D6 -> 0 | F6: ='OPENING STOCK'!F6 -> 0 | G6: ='OPENING STOCK'!G6+RECIEPTS!E6 -> 6 | H6: ='OPENING STOCK'!H6 -> 89 | I6: ='OPENING STOCK'!I6+RECIEPTS!F6 -> 5 | J6: ='OPENING STOCK'!J6 -> 42 | K6: ='OPENING STOCK'!K6+RECIEPTS!G6 -> 0 | L6: ='OPENING STOCK'!L6 -> 0
A7: 4 | B7: ='SALES & RATE'!B7 -> AMRUT SILVER CUP | C7: ='OPENING STOCK'!C7+RECIEPTS!C7 -> 0 | D7: ='OPENING STOCK'!D7 -> 0 | E7: ='OPENING STOCK'!E7+RECIEPTS!D7 -> 0 | F7: ='OPENING STOCK'!F7 -> 0 | G7: ='OPENING STOCK'!G7+RECIEPTS!E7 -> 8 | H7: ='OPENING STOCK'!H7 -> 46 | I7: ='OPENING STOCK'!I7+RECIEPTS!F7 -> 6 | J7: ='OPENING STOCK'!J7 -> 2 | K7: ='OPENING STOCK'!K7+RECIEPTS!G7 -> 0 | L7: ='OPENING STOCK'!L7 -> 0
A8: 5 | B8: ='SALES & RATE'!B8 -> HONEY BEE BRANDY | C8: ='OPENING STOCK'!C8+RECIEPTS!C8 -> 0 | D8: ='OPENING STOCK'!D8 -> 0 | E8: ='OPENING STOCK'!E8+RECIEPTS!D8 -> 0 | F8: ='OPENING STOCK'!F8 -> 0 | G8: ='OPENING STOCK'!G8+RECIEPTS!E8 -> 0 | H8: ='OPENING STOCK'!H8 -> 26 | I8: ='OPENING STOCK'!I8+RECIEPTS!F8 -> 0 | J8: ='OPENING STOCK'!J8 -> 54 | K8: ='OPENING STOCK'!K8+RECIEPTS!G8 -> 0 | L8: ='OPENING STOCK'!L8 -> 0
A9: 6 | B9: ='SALES & RATE'!B9 -> O A BRANDY | C9: ='OPENING STOCK'!C9+RECIEPTS!C9 -> 0 | D9: ='OPENING STOCK'!D9 -> 3 | E9: ='OPENING STOCK'!E9+RECIEPTS!D9 -> 0 | F9: ='OPENING STOCK'!F9 -> 0 | G9: ='OPENING STOCK'!G9+RECIEPTS!E9 -> 3 | H9: ='OPENING STOCK'!H9 -> 92 | I9: ='OPENING STOCK'!I9+RECIEPTS!F9 -> 4 | J9: ='OPENING STOCK'!J9 -> 61 | K9: ='OPENING STOCK'!K9+RECIEPTS!G9 -> 0 | L9: ='OPENING STOCK'!L9 -> 0
A10: 7 | B10: ='SALES & RATE'!B10 -> BEJOIS BRANDY | C10: ='OPENING STOCK'!C10+RECIEPTS!C10 -> 0 | D10: ='OPENING STOCK'!D10 -> 6 | E10: ='OPENING STOCK'!E10+RECIEPTS!D10 -> 0 | F10: ='OPENING STOCK'!F10 -> 0 | G10: ='OPENING STOCK'!G10+RECIEPTS!E10 -> 8 | H10: ='OPENING STOCK'!H10 -> 59 | I10: ='OPENING STOCK'!I10+RECIEPTS!F10 -> 7 | J10: ='OPENING STOCK'!J10 -> 19 | K10: ='OPENING STOCK'!K10+RECIEPTS!G10 -> 0 | L10: ='OPENING STOCK'!L10 -> 0
A11: 8 | B11: ='SALES & RATE'!B11 -> MORPHIS BRANDY | C11: ='OPENING STOCK'!C11+RECIEPTS!C11 -> 0 | D11: ='OPENING STOCK'!D11 -> 0 | E11: ='OPENING STOCK'!E11+RECIEPTS!D11 -> 0 | F11: ='OPENING STOCK'!F11 -> 0 | G11: ='OPENING STOCK'!G11+RECIEPTS!E11 -> 0 | H11: ='OPENING STOCK'!H11 -> 35 | I11: ='OPENING STOCK'!I11+RECIEPTS!F11 -> 0 | J11: ='OPENING STOCK'!J11 -> 0 | K11: ='OPENING STOCK'!K11+RECIEPTS!G11 -> 0 | L11: ='OPENING STOCK'!L11 -> 33
A12: 9 | B12: ='SALES & RATE'!B12 -> M C WHISKY | C12: ='OPENING STOCK'!C12+RECIEPTS!C12 -> 0 | D12: ='OPENING STOCK'!D12 -> 10 | E12: ='OPENING STOCK'!E12+RECIEPTS!D12 -> 0 | F12: ='OPENING STOCK'!F12 -> 15 | G12: ='OPENING STOCK'!G12+RECIEPTS!E12 -> 2 | H12: ='OPENING STOCK'!H12 -> 52 | I12: ='OPENING STOCK'!I12+RECIEPTS!F12 -> 1 | J12: ='OPENING STOCK'!J12 -> 95 | K12: ='OPENING STOCK'!K12+RECIEPTS!G12 -> 0 | L12: ='OPENING STOCK'!L12 -> 0
A13: 10 | B13: ='SALES & RATE'!B13 -> BAGPIPER (W) | C13: ='OPENING STOCK'!C13+RECIEPTS!C13 -> 0 | D13: ='OPENING STOCK'!D13 -> 11 | E13: ='OPENING STOCK'!E13+RECIEPTS!D13 -> 0 | F13: ='OPENING STOCK'!F13 -> 9 | G13: ='OPENING STOCK'!G13+RECIEPTS!E13 -> 16 | H13: ='OPENING STOCK'!H13 -> 51 | I13: ='OPENING STOCK'!I13+RECIEPTS!F13 -> 6 | J13: ='OPENING STOCK'!J13 -> 49 | K13: ='OPENING STOCK'!K13+RECIEPTS!G13 -> 0 | L13: ='OPENING STOCK'!L13 -> 0
A14: 11 | B14: ='SALES & RATE'!B14 -> SIGNATURE (W) | C14: ='OPENING STOCK'!C14+RECIEPTS!C14 -> 0 | D14: ='OPENING STOCK'!D14 -> 0 | E14: ='OPENING STOCK'!E14+RECIEPTS!D14 -> 0 | F14: ='OPENING STOCK'!F14 -> 0 | G14: ='OPENING STOCK'!G14+RECIEPTS!E14 -> 0 | H14: ='OPENING STOCK'!H14 -> 31 | I14: ='OPENING STOCK'!I14+RECIEPTS!F14 -> 0 | J14: ='OPENING STOCK'!J14 -> 0 | K14: ='OPENING STOCK'!K14+RECIEPTS!G14 -> 0 | L14: ='OPENING STOCK'!L14 -> 0
A15: 12 | B15: ='SALES & RATE'!B15 -> O T WHISKY | C15: ='OPENING STOCK'!C15+RECIEPTS!C15 -> 0 | D15: ='OPENING STOCK'!D15 -> 0 | E15: ='OPENING STOCK'!E15+RECIEPTS!D15 -> 0 | F15: ='OPENING STOCK'!F15 -> 0 | G15: ='OPENING STOCK'!G15+RECIEPTS!E15 -> 2 | H15: ='OPENING STOCK'!H15 -> 23 | I15: ='OPENING STOCK'!I15+RECIEPTS!F15 -> 0 | J15: ='OPENING STOCK'!J15 -> 99 | K15: ='OPENING STOCK'!K15+RECIEPTS!G15 -> 0 | L15: ='OPENING STOCK'!L15 -> 0
... A50: 47 | B50: ='SALES & RATE'!B50 -> 0 | C50: ='OPENING STOCK'!C50+RECIEPTS!C50 -> 0 | D50: ='OPENING STOCK'!D50 -> 0 | E50: ='OPENING STOCK'!E50+RECIEPTS!D50 -> 0 | F50: ='OPENING STOCK'!F50 -> 0 | G50: ='OPENING STOCK'!G50+RECIEPTS!E50 -> 0 | H50: ='OPENING STOCK'!H50 -> 0 | I50: ='OPENING STOCK'!I50+RECIEPTS!F50 -> 0 | J50: ='OPENING STOCK'!J50 -> 0 | K50: ='OPENING STOCK'!K50+RECIEPTS!G50 -> 0 | L50: ='OPENING STOCK'!L50 -> 0
A51: Mahavishnu PAGE 2 | C51: TOTAL STOCK PAGE 2
C52: 750 ML | E52: 375 ML | G52: 180 ML | I52: 90 ML | K52: 60 ML
A53: SL. | B53: PRODUCT NAME | C53: CASES*12 | D53: BTLS | E53: CASES*24 | F53: BTLS | G53: CASES*48 | H53: BTLS | I53: CASES*96 | J53: BTLS | K53: BOX*25 | L53: BTLS
A54: 1 | B54: ='SALES & RATE'!B54 -> CARNIVAL GIN | C54: ='OPENING STOCK'!C54+RECIEPTS!C54 -> 0 | D54: ='OPENING STOCK'!D54 -> 0 | E54: ='OPENING STOCK'!E54+RECIEPTS!D54 -> 0 | F54: ='OPENING STOCK'!F54 -> 0 | G54: ='OPENING STOCK'!G54+RECIEPTS!E54 -> 1 | H54: ='OPENING STOCK'!H54 -> 16 | I54: ='OPENING STOCK'!I54+RECIEPTS!F54 -> 0 | J54: ='OPENING STOCK'!J54 -> 82 | K54: ='OPENING STOCK'!K54+RECIEPTS!G54 -> 0 | L54: ='OPENING STOCK'!L54 -> 0
A55: 2 | B55: ='SALES & RATE'!B55 -> SMIRNOFF VODKA | C55: ='OPENING STOCK'!C55+RECIEPTS!C55 -> 0 | D55: ='OPENING STOCK'!D55 -> 4 | E55: ='OPENING STOCK'!E55+RECIEPTS!D55 -> 0 | F55: ='OPENING STOCK'!F55 -> 0 | G55: ='OPENING STOCK'!G55+RECIEPTS!E55 -> 0 | H55: ='OPENING STOCK'!H55 -> 59 | I55: ='OPENING STOCK'!I55+RECIEPTS!F55 -> 0 | J55: ='OPENING STOCK'!J55 -> 0 | K55: ='OPENING STOCK'!K55+RECIEPTS!G55 -> 0 | L55: ='OPENING STOCK'!L55 -> 20
A56: 3 | B56: ='SALES & RATE'!B56 -> MUSCOVY LEMON | C56: ='OPENING STOCK'!C56+RECIEPTS!C56 -> 0 | D56: ='OPENING STOCK'!D56 -> 0 | E56: ='OPENING STOCK'!E56+RECIEPTS!D56 -> 0 | F56: ='OPENING STOCK'!F56 -> 0 | G56: ='OPENING STOCK'!G56+RECIEPTS!E56 -> 0 | H56: ='OPENING STOCK'!H56 -> 48 | I56: ='OPENING STOCK'!I56+RECIEPTS!F56 -> 0 | J56: ='OPENING STOCK'!J56 -> 0 | K56: ='OPENING STOCK'!K56+RECIEPTS!G56 -> 0 | L56: ='OPENING STOCK'!L56 -> 0
A57: 4 | B57: ='SALES & RATE'!B57 -> MUSCOVY VODKA | C57: ='OPENING STOCK'!C57+RECIEPTS!C57 -> 0 | D57: ='OPENING STOCK'!D57 -> 0 | E57: ='OPENING STOCK'!E57+RECIEPTS!D57 -> 0 | F57: ='OPENING STOCK'!F57 -> 0 | G57: ='OPENING STOCK'!G57+RECIEPTS!E57 -> 4 | H57: ='OPENING STOCK'!H57 -> 89 | I57: ='OPENING STOCK'!I57+RECIEPTS!F57 -> 1 | J57: ='OPENING STOCK'!J57 -> 95 | K57: ='OPENING STOCK'!K57+RECIEPTS!G57 -> 0 | L57: ='OPENING STOCK'!L57 -> 0
A58: 5 | B58: ='SALES & RATE'!B58 -> ROMANOV VODKA | C58: ='OPENING STOCK'!C58+RECIEPTS!C58 -> 0 | D58: ='OPENING STOCK'!D58 -> 0 | E58: ='OPENING STOCK'!E58+RECIEPTS!D58 -> 0 | F58: ='OPENING STOCK'!F58 -> 0 | G58: ='OPENING STOCK'!G58+RECIEPTS!E58 -> 1 | H58: ='OPENING STOCK'!H58 -> 56 | I58: ='OPENING STOCK'!I58+RECIEPTS!F58 -> 1 | J58: ='OPENING STOCK'!J58 -> 96 | K58: ='OPENING STOCK'!K58+RECIEPTS!G58 -> 0 | L58: ='OPENING STOCK'!L58 -> 0
A59: 6 | B59: ='SALES & RATE'!B59 -> GONAS WINE | C59: ='OPENING STOCK'!C59+RECIEPTS!C59 -> 0 | D59: ='OPENING STOCK'!D59 -> 0 | E59: ='OPENING STOCK'!E59+RECIEPTS!D59 -> 0 | F59: ='OPENING STOCK'!F59 -> 0 | G59: ='OPENING STOCK'!G59+RECIEPTS!E59 -> 0 | H59: ='OPENING STOCK'!H59 -> 39 | I59: ='OPENING STOCK'!I59+RECIEPTS!F59 -> 0 | J59: ='OPENING STOCK'!J59 -> 0 | K59: ='OPENING STOCK'!K59+RECIEPTS!G59 -> 0 | L59: ='OPENING STOCK'!L59 -> 0
A60: 7 | B60: ='SALES & RATE'!B60 -> MAGIC PORT WINE | C60: ='OPENING STOCK'!C60+RECIEPTS!C60 -> 0 | D60: ='OPENING STOCK'!D60 -> 20 | E60: ='OPENING STOCK'!E60+RECIEPTS!D60 -> 0 | F60: ='OPENING STOCK'!F60 -> 24 | G60: ='OPENING STOCK'!G60+RECIEPTS!E60 -> 0 | H60: ='OPENING STOCK'!H60 -> 12 | I60: ='OPENING STOCK'!I60+RECIEPTS!F60 -> 0 | J60: ='OPENING STOCK'!J60 -> 0 | K60: ='OPENING STOCK'!K60+RECIEPTS!G60 -> 0 | L60: ='OPENING STOCK'!L60 -> 0
A61: 8 | B61: ='SALES & RATE'!B61 -> SIDDUS WINE | C61: ='OPENING STOCK'!C61+RECIEPTS!C61 -> 0 | D61: ='OPENING STOCK'!D61 -> 1 | E61: ='OPENING STOCK'!E61+RECIEPTS!D61 -> 0 | F61: ='OPENING STOCK'!F61 -> 1 | G61: ='OPENING STOCK'!G61+RECIEPTS!E61 -> 0 | H61: ='OPENING STOCK'!H61 -> 34 | I61: ='OPENING STOCK'!I61+RECIEPTS!F61 -> 0 | J61: ='OPENING STOCK'!J61 -> 0 | K61: ='OPENING STOCK'!K61+RECIEPTS!G61 -> 0 | L61: ='OPENING STOCK'!L61 -> 0
A62: 9 | B62: ='SALES & RATE'!B62 -> VEGA WINE | C62: ='OPENING STOCK'!C62+RECIEPTS!C62 -> 0 | D62: ='OPENING STOCK'!D62 -> 0 | E62: ='OPENING STOCK'!E62+RECIEPTS!D62 -> 0 | F62: ='OPENING STOCK'!F62 -> 13 | G62: ='OPENING STOCK'!G62+RECIEPTS!E62 -> 0 | H62: ='OPENING STOCK'!H62 -> 0 | I62: ='OPENING STOCK'!I62+RECIEPTS!F62 -> 0 | J62: ='OPENING STOCK'!J62 -> 0 | K62: ='OPENING STOCK'!K62+RECIEPTS!G62 -> 0 | L62: ='OPENING STOCK'!L62 -> 0
A63: 10 | B63: ='SALES & RATE'!B63 -> 0 | C63: ='OPENING STOCK'!C63+RECIEPTS!C63 -> 0 | D63: ='OPENING STOCK'!D63 -> 0 | E63: ='OPENING STOCK'!E63+RECIEPTS!D63 -> 0 | F63: ='OPENING STOCK'!F63 -> 0 | G63: ='OPENING STOCK'!G63+RECIEPTS!E63 -> 0 | H63: ='OPENING STOCK'!H63 -> 0 | I63: ='OPENING STOCK'!I63+RECIEPTS!F63 -> 0 | J63: ='OPENING STOCK'!J63 -> 0 | K63: ='OPENING STOCK'!K63+RECIEPTS!G63 -> 0 | L63: ='OPENING STOCK'!L63 -> 0
A64: 11 | B64: ='SALES & RATE'!B64 -> MAGIC MOMENTS | C64: ='OPENING STOCK'!C64+RECIEPTS!C64 -> 0 | D64: ='OPENING STOCK'!D64 -> 2 | E64: ='OPENING STOCK'!E64+RECIEPTS!D64 -> 0 | F64: ='OPENING STOCK'!F64 -> 0 | G64: ='OPENING STOCK'!G64+RECIEPTS!E64 -> 1 | H64: ='OPENING STOCK'!H64 -> 0 | I64: ='OPENING STOCK'!I64+RECIEPTS!F64 -> 0 | J64: ='OPENING STOCK'!J64 -> 0 | K64: ='OPENING STOCK'!K64+RECIEPTS!G64 -> 1 | L64: ='OPENING STOCK'!L64 -> 6
A65: 12 | B65: ='SALES & RATE'!B65 -> BRO CODE | C65: ='OPENING STOCK'!C65+RECIEPTS!C65 -> 0 | D65: ='OPENING STOCK'!D65 -> 0 | E65: ='OPENING STOCK'!E65+RECIEPTS!D65 -> 0 | F65: ='OPENING STOCK'!F65 -> 26 | G65: ='OPENING STOCK'!G65+RECIEPTS!E65 -> 0 | H65: ='OPENING STOCK'!H65 -> 0 | I65: ='OPENING STOCK'!I65+RECIEPTS!F65 -> 0 | J65: ='OPENING STOCK'!J65 -> 0 | K65: ='OPENING STOCK'!K65+RECIEPTS!G65 -> 0 | L65: ='OPENING STOCK'!L65 -> 0
... A71: 18 | B71: ='SALES & RATE'!B71 -> 0 | C71: ='OPENING STOCK'!C71+RECIEPTS!C71 -> 0 | D71: ='OPENING STOCK'!D71 -> 0 | E71: ='OPENING STOCK'!E71+RECIEPTS!D71 -> 0 | F71: ='OPENING STOCK'!F71 -> 0 | G71: ='OPENING STOCK'!G71+RECIEPTS!E71 -> 0 | H71: ='OPENING STOCK'!H71 -> 0 | I71: ='OPENING STOCK'!I71+RECIEPTS!F71 -> 0 | J71: ='OPENING STOCK'!J71 -> 0 | K71: ='OPENING STOCK'!K71+RECIEPTS!G71 -> 0 | L71: ='OPENING STOCK'!L71 -> 0
A72: BEERS | C72: TOTAL STOCK
C73: 650 ML | E73: 500 ML TIN(CAN) | G73: 330 ML (PINT) | I73: 330 ML TIN(CAN)
A74: SL. | B74: PRODUCT NAME | C74: CASES*12 | D74: BTLS | E74: CASES*24 | F74: BTLS | G74: CASES*24 | H74: BTLS | I74: CASES*24 | J74: BTLS
A75: 1 | B75: ='SALES & RATE'!B75 -> K.F PREMIUM | C75: ='OPENING STOCK'!C75+RECIEPTS!C75 -> 1 | D75: ='OPENING STOCK'!D75 -> 15 | E75: ='OPENING STOCK'!E75+RECIEPTS!D75 -> 0 | F75: ='OPENING STOCK'!F75 -> 0 | G75: ='OPENING STOCK'!G75+RECIEPTS!E75 -> 0 | H75: ='OPENING STOCK'!H75 -> 0 | I75: ='OPENING STOCK'!I75+RECIEPTS!F75 -> 0 | J75: ='OPENING STOCK'!J75 -> 0
A76: 2 | B76: ='SALES & RATE'!B76 -> K.F STRONG | C76: ='OPENING STOCK'!C76+RECIEPTS!C76 -> 97 | D76: ='OPENING STOCK'!D76 -> 32 | E76: ='OPENING STOCK'!E76+RECIEPTS!D76 -> 2 | F76: ='OPENING STOCK'!F76 -> 1 | G76: ='OPENING STOCK'!G76+RECIEPTS!E76 -> 3 | H76: ='OPENING STOCK'!H76 -> 0 | I76: ='OPENING STOCK'!I76+RECIEPTS!F76 -> 1 | J76: ='OPENING STOCK'!J76 -> 0
A77: 3 | B77: ='SALES & RATE'!B77 -> U.B EXPORT | C77: ='OPENING STOCK'!C77+RECIEPTS!C77 -> 1 | D77: ='OPENING STOCK'!D77 -> 28 | E77: ='OPENING STOCK'!E77+RECIEPTS!D77 -> 0 | F77: ='OPENING STOCK'!F77 -> 0 | G77: ='OPENING STOCK'!G77+RECIEPTS!E77 -> 0 | H77: ='OPENING STOCK'!H77 -> 0 | I77: ='OPENING STOCK'!I77+RECIEPTS!F77 -> 0 | J77: ='OPENING STOCK'!J77 -> 0
A78: 4 | B78: ='SALES & RATE'!B78 -> KNOCK OUT | C78: ='OPENING STOCK'!C78+RECIEPTS!C78 -> 5 | D78: ='OPENING STOCK'!D78 -> 0 | E78: ='OPENING STOCK'!E78+RECIEPTS!D78 -> 0 | F78: ='OPENING STOCK'!F78 -> 0 | G78: ='OPENING STOCK'!G78+RECIEPTS!E78 -> 1 | H78: ='OPENING STOCK'!H78 -> 10 | I78: ='OPENING STOCK'!I78+RECIEPTS!F78 -> 0 | J78: ='OPENING STOCK'!J78 -> 0
A79: 5 | B79: ='SALES & RATE'!B79 -> K.F STROM | C79: ='OPENING STOCK'!C79+RECIEPTS!C79 -> 0 | D79: ='OPENING STOCK'!D79 -> 0 | E79: ='OPENING STOCK'!E79+RECIEPTS!D79 -> 0 | F79: ='OPENING STOCK'!F79 -> 0 | G79: ='OPENING STOCK'!G79+RECIEPTS!E79 -> 0 | H79: ='OPENING STOCK'!H79 -> 0 | I79: ='OPENING STOCK'!I79+RECIEPTS!F79 -> 0 | J79: ='OPENING STOCK'!J79 -> 0
A80: 6 | B80: ='SALES & RATE'!B80 -> BUDWISER MAGNUM | C80: ='OPENING STOCK'!C80+RECIEPTS!C80 -> 28 | D80: ='OPENING STOCK'!D80 -> 39 | E80: ='OPENING STOCK'!E80+RECIEPTS!D80 -> 0 | F80: ='OPENING STOCK'!F80 -> 34 | G80: ='OPENING STOCK'!G80+RECIEPTS!E80 -> 0 | H80: ='OPENING STOCK'!H80 -> 0 | I80: ='OPENING STOCK'!I80+RECIEPTS!F80 -> 0 | J80: ='OPENING STOCK'!J80 -> 0
A81: 7 | B81: ='SALES & RATE'!B81 -> BUDWISER PREM | C81: ='OPENING STOCK'!C81+RECIEPTS!C81 -> 3 | D81: ='OPENING STOCK'!D81 -> 2 | E81: ='OPENING STOCK'!E81+RECIEPTS!D81 -> 0 | F81: ='OPENING STOCK'!F81 -> 24 | G81: ='OPENING STOCK'!G81+RECIEPTS!E81 -> 0 | H81: ='OPENING STOCK'!H81 -> 0 | I81: ='OPENING STOCK'!I81+RECIEPTS!F81 -> 0 | J81: ='OPENING STOCK'!J81 -> 0
A82: 8 | B82: ='SALES & RATE'!B82 -> K.F ULTRA/ WITT BEER | C82: ='OPENING STOCK'!C82+RECIEPTS!C82 -> 0 | D82: ='OPENING STOCK'!D82 -> 22 | E82: ='OPENING STOCK'!E82+RECIEPTS!D82 -> 0 | F82: ='OPENING STOCK'!F82 -> 0 | G82: ='OPENING STOCK'!G82+RECIEPTS!E82 -> 0 | H82: ='OPENING STOCK'!H82 -> 0 | I82: ='OPENING STOCK'!I82+RECIEPTS!F82 -> 0 | J82: ='OPENING STOCK'!J82 -> 0
A83: 9 | B83: ='SALES & RATE'!B83 -> TOBURG STRONG BEER | C83: ='OPENING STOCK'!C83+RECIEPTS!C83 -> 24 | D83: ='OPENING STOCK'!D83 -> 21 | E83: ='OPENING STOCK'!E83+RECIEPTS!D83 -> 1 | F83: ='OPENING STOCK'!F83 -> 14 | G83: ='OPENING STOCK'!G83+RECIEPTS!E83 -> 3 | H83: ='OPENING STOCK'!H83 -> 0 | I83: ='OPENING STOCK'!I83+RECIEPTS!F83 -> 0 | J83: ='OPENING STOCK'!J83 -> 0
A84: 10 | B84: ='SALES & RATE'!B84 -> POWERCOOL | C84: ='OPENING STOCK'!C84+RECIEPTS!C84 -> 7 | D84: ='OPENING STOCK'!D84 -> 24 | E84: ='OPENING STOCK'!E84+RECIEPTS!D84 -> 0 | F84: ='OPENING STOCK'!F84 -> 22 | G84: ='OPENING STOCK'!G84+RECIEPTS!E84 -> 0 | H84: ='OPENING STOCK'!H84 -> 7 | I84: ='OPENING STOCK'!I84+RECIEPTS!F84 -> 0 | J84: ='OPENING STOCK'!J84 -> 0
A85: 11 | B85: ='SALES & RATE'!B85 -> BACARDI + | C85: ='OPENING STOCK'!C85+RECIEPTS!C85 -> 0 | D85: ='OPENING STOCK'!D85 -> 0 | E85: ='OPENING STOCK'!E85+RECIEPTS!D85 -> 0 | F85: ='OPENING STOCK'!F85 -> 0 | G85: ='OPENING STOCK'!G85+RECIEPTS!E85 -> 3 | H85: ='OPENING STOCK'!H85 -> 27 | I85: ='OPENING STOCK'!I85+RECIEPTS!F85 -> 0 | J85: ='OPENING STOCK'!J85 -> 0
A86: 12 | B86: ='SALES & RATE'!B86 -> BACARDI BREEZER | C86: ='OPENING STOCK'!C86+RECIEPTS!C86 -> 0 | D86: ='OPENING STOCK'!D86 -> 0 | E86: ='OPENING STOCK'!E86+RECIEPTS!D86 -> 0 | F86: ='OPENING STOCK'!F86 -> 0 | G86: ='OPENING STOCK'!G86+RECIEPTS!E86 -> 0 | H86: ='OPENING STOCK'!H86 -> 26 | I86: ='OPENING STOCK'!I86+RECIEPTS!F86 -> 0 | J86: ='OPENING STOCK'!J86 -> 0
... A94: 20 | B94: ='SALES & RATE'!B94 -> 0 | C94: ='OPENING STOCK'!C94+RECIEPTS!C94 -> 0 | D94: ='OPENING STOCK'!D94 -> 0 | E94: ='OPENING STOCK'!E94+RECIEPTS!D94 -> 0 | F94: ='OPENING STOCK'!F94 -> 0 | G94: ='OPENING STOCK'!G94+RECIEPTS!E94 -> 0 | H94: ='OPENING STOCK'!H94 -> 0 | I94: ='OPENING STOCK'!I94+RECIEPTS!F94 -> 0 | J94: ='OPENING STOCK'!J94 -> 0
A95: BEVERAGES | C95: TOTAL STOCK
C96: 2 LTRS | E96: 1 LTRS | G96: 500 ML-600 ML | I96: 250 ML
A97: SL. | B97: PRODUCT NAME | C97: CASES*9 | D97: BTLS | E97: CASES*12 | F97: BTLS | G97: CASES*24 | H97: BTLS | I97: CASES*30 | J97: BTLS
A98: 1 | B98: ='SALES & RATE'!B98 -> COOL DRINKS | C98: ='OPENING STOCK'!C98+RECIEPTS!C98 -> 0 | D98: ='OPENING STOCK'!D98 -> 0 | E98: ='OPENING STOCK'!E98+RECIEPTS!D98 -> 0 | F98: ='OPENING STOCK'!F98 -> 0 | G98: ='OPENING STOCK'!G98+RECIEPTS!E98 -> 6 | H98: ='OPENING STOCK'!H98 -> 116 | I98: ='OPENING STOCK'!I98+RECIEPTS!F98 -> 12 | J98: ='OPENING STOCK'!J98 -> 82
A99: 2 | B99: ='SALES & RATE'!B99 -> SODA*12/REDBULL*24 | C99: ='OPENING STOCK'!C99+RECIEPTS!C99 -> 0 | D99: ='OPENING STOCK'!D99 -> 0 | E99: ='OPENING STOCK'!E99+RECIEPTS!D99 -> 0 | F99: ='OPENING STOCK'!F99 -> 0 | G99: ='OPENING STOCK'!G99+RECIEPTS!E99 -> 12 | H99: ='OPENING STOCK'!H99 -> 10 | I99: ='OPENING STOCK'!I99+RECIEPTS!F99 -> 1 | J99: ='OPENING STOCK'!J99 -> 6
A100: 3 | B100: ='SALES & RATE'!B100 -> MIN WATER | C100: ='OPENING STOCK'!C100+RECIEPTS!C100 -> 15 | D100: ='OPENING STOCK'!D100 -> 21 | E100: ='OPENING STOCK'!E100+RECIEPTS!D100 -> 70 | F100: ='OPENING STOCK'!F100 -> 30 | G100: ='OPENING STOCK'!G100+RECIEPTS!E100 -> 27 | H100: ='OPENING STOCK'!H100 -> 98 | I100: ='OPENING STOCK'!I100+RECIEPTS!F100 -> 0 | J100: ='OPENING STOCK'!J100 -> 0

Sheet CLOSING STOCK
A1: Mahavishnu | C1: CLOSING STOCK
C2: 750 ML | E2: 375 ML | G2: 180 ML | I2: 90 ML | K2: 60 ML
A3: SL. | B3: PRODUCT NAME | C3: CASES*12 | D3: BTLS | E3: CASES*24 | F3: BTLS | G3: CASES*48 | H3: BTLS | I3: CASES*96 | J3: BTLS | K3: BOX*25 | L3: BTLS
A4: 1 | B4: ='SALES & RATE'!B4 -> M H BRANDY | C4: ='TOTAL STOCK'!C4 -> 0 | D4: 8 | E4: 0 | F4: 24 | G4: 6 | H4: 47 | I4: 6 | J4: 73 | K4: ='TOTAL STOCK'!K4 -> 0 | L4: ='TOTAL STOCK'!L4 -> 0
A5: 2 | B5: ='SALES & RATE'!B5 -> MC BRANDY | C5: ='TOTAL STOCK'!C5 -> 0 | D5: 11 | E5: ='TOTAL STOCK'!E5 -> 1 | F5: 7 | G5: 6 | H5: 54 | I5: 5 | J5: 81 | K5: ='TOTAL STOCK'!K5 -> 0 | L5: ='TOTAL STOCK'!L5 -> 0
A6: 3 | B6: ='SALES & RATE'!B6 -> O.C.BRANDY | C6: ='TOTAL STOCK'!C6 -> 0 | D6: ='TOTAL STOCK'!D6 -> 0 | E6: ='TOTAL STOCK'!E6 -> 0 | F6: ='TOTAL STOCK'!F6 -> 0 | G6: 3 | H6: 55 | I6: 3 | J6: 64 | K6: ='TOTAL STOCK'!K6 -> 0 | L6: ='TOTAL STOCK'!L6 -> 0
A7: 4 | B7: ='SALES & RATE'!B7 -> AMRUT SILVER CUP | C7: ='TOTAL STOCK'!C7 -> 0 | D7: ='TOTAL STOCK'!D7 -> 0 | E7: ='TOTAL STOCK'!E7 -> 0 | F7: ='TOTAL STOCK'!F7 -> 0 | G7: ='TOTAL STOCK'!G7 -> 8 | H7: 26 | I7: 4 | J7: 25 | K7: ='TOTAL STOCK'!K7 -> 0 | L7: ='TOTAL STOCK'!L7 -> 0
A8: 5 | B8: ='SALES & RATE'!B8 -> HONEY BEE BRANDY | C8: ='TOTAL STOCK'!C8 -> 0 | D8: ='TOTAL STOCK'!D8 -> 0 | E8: ='TOTAL STOCK'!E8 -> 0 | F8: ='TOTAL STOCK'!F8 -> 0 | G8: ='TOTAL STOCK'!G8 -> 0 | H8: 14 | I8: ='TOTAL STOCK'!I8 -> 0 | J8: 42 | K8: ='TOTAL STOCK'!K8 -> 0 | L8: ='TOTAL STOCK'!L8 -> 0
A9: 6 | B9: ='SALES & RATE'!B9 -> O A BRANDY | C9: ='TOTAL STOCK'!C9 -> 0 | D9: ='TOTAL STOCK'!D9 -> 3 | E9: ='TOTAL STOCK'!E9 -> 0 | F9: ='TOTAL STOCK'!F9 -> 0 | G9: 1 | H9: 90 | I9: 3 | J9: 103 | K9: ='TOTAL STOCK'!K9 -> 0 | L9: ='TOTAL STOCK'!L9 -> 0
A10: 7 | B10: ='SALES & RATE'!B10 -> BEJOIS BRANDY | C10: ='TOTAL STOCK'!C10 -> 0 | D10: ='TOTAL STOCK'!D10 -> 6 | E10: ='TOTAL STOCK'!E10 -> 0 | F10: ='TOTAL STOCK'!F10 -> 0 | G10: 5 | H10: 56 | I10: 6 | J10: 21 | K10: ='TOTAL STOCK'!K10 -> 0 | L10: ='TOTAL STOCK'!L10 -> 0
A11: 8 | B11: ='SALES & RATE'!B11 -> MORPHIS BRANDY | C11: ='TOTAL STOCK'!C11 -> 0 | D11: ='TOTAL STOCK'!D11 -> 0 | E11: ='TOTAL STOCK'!E11 -> 0 | F11: ='TOTAL STOCK'!F11 -> 0 | G11: ='TOTAL STOCK'!G11 -> 0 | H11: 26 | I11: ='TOTAL STOCK'!I11 -> 0 | J11: ='TOTAL STOCK'!J11 -> 0 | K11: ='TOTAL STOCK'!K11 -> 0 | L11: 19
A12: 9 | B12: ='SALES & RATE'!B12 -> M C WHISKY | C12: ='TOTAL STOCK'!C12 -> 0 | D12: 9 | E12: ='TOTAL STOCK'!E12 -> 0 | F12: 13 | G12: 1 | H12: 22 | I12: ='TOTAL STOCK'!I12 -> 1 | J12: 41 | K12: ='TOTAL STOCK'!K12 -> 0 | L12: ='TOTAL STOCK'!L12 -> 0
A13: 10 | B13: ='SALES & RATE'!B13 -> BAGPIPER (W) | C13: ='TOTAL STOCK'!C13 -> 0 | D13: ='TOTAL STOCK'!D13 -> 11 | E13: ='TOTAL STOCK'!E13 -> 0 | F13: 7 | G13: 9 | H13: 74 | I13: 4 | J13: 15 | K13: ='TOTAL STOCK'!K13 -> 0 | L13: ='TOTAL STOCK'!L13 -> 0
A14: 11 | B14: ='SALES & RATE'!B14 -> SIGNATURE (W) | C14: ='TOTAL STOCK'!C14 -> 0 | D14: ='TOTAL STOCK'!D14 -> 0 | E14: ='TOTAL STOCK'!E14 -> 0 | F14: ='TOTAL STOCK'!F14 -> 0 | G14: ='TOTAL STOCK'!G14 -> 0 | H14: ='TOTAL STOCK'!H14 -> 31 | I14: ='TOTAL STOCK'!I14 -> 0 | J14: ='TOTAL STOCK'!J14 -> 0 | ... L14: ='TOTAL STOCK'!L14 -> 0
A15: 12 | B15: ='SALES & RATE'!B15 -> O T WHISKY | C15: ='TOTAL STOCK'!C15 -> 0 | D15: ='TOTAL STOCK'!D15 -> 0 | E15: ='TOTAL STOCK'!E15 -> 0 | F15: ='TOTAL STOCK'!F15 -> 0 | G15: ='TOTAL STOCK'!G15 -> 2 | H15: 17 | I15: ='TOTAL STOCK'!I15 -> 0 | J15: 90 | K15: ='TOTAL STOCK'!K15 -> 0 | L15: ='TOTAL STOCK'!L15 -> 0
A16: 13 | B16: ='SALES & RATE'!B16 -> DSP BLACK(W) | C16: ='TOTAL STOCK'!C16 -> 0 | D16: 7 | E16: ='TOTAL STOCK'!E16 -> 0 | F16: 0 | G16: 5 | H16: 23 | I16: 5 | J16: 101 | K16: ='TOTAL STOCK'!K16 -> 0 | L16: ='TOTAL STOCK'!L16 -> 0
A17: 14 | B17: ='SALES & RATE'!B17 -> O C WHISKY | C17: ='TOTAL STOCK'!C17 -> 0 | D17: ='TOTAL STOCK'!D17 -> 0 | E17: ='TOTAL STOCK'!E17 -> 0 | F17: ='TOTAL STOCK'!F17 -> 0 | G17: 7 | H17: 85 | I17: 3 | J17: 71 | K17: ='TOTAL STOCK'!K17 -> 0 | L17: ='TOTAL STOCK'!L17 -> 0
A18: 15 | B18: ='SALES & RATE'!B18 -> R C WHISKY | C18: ='TOTAL STOCK'!C18 -> 0 | D18: ='TOTAL STOCK'!D18 -> 0 | E18: ='TOTAL STOCK'!E18 -> 0 | F18: ='TOTAL STOCK'!F18 -> 0 | G18: ='TOTAL STOCK'!G18 -> 0 | H18: ='TOTAL STOCK'!H18 -> 0 | I18: ='TOTAL STOCK'!I18 -> 0 | J18: ='TOTAL STOCK'!J18 -> 0 | ... L18: ='TOTAL STOCK'!L18 -> 0
A19: 16 | B19: ='SALES & RATE'!B19 -> BLENDERS PRIDE | C19: ='TOTAL STOCK'!C19 -> 0 | D19: ='TOTAL STOCK'!D19 -> 0 | E19: ='TOTAL STOCK'!E19 -> 0 | F19: ='TOTAL STOCK'!F19 -> 0 | G19: ='TOTAL STOCK'!G19 -> 0 | H19: 26 | I19: ='TOTAL STOCK'!I19 -> 0 | J19: ='TOTAL STOCK'!J19 -> 0 | K19: ='TOTAL STOCK'!K19 -> 0 | L19: 4
A20: 17 | B20: ='SALES & RATE'!B20 -> AFTER DARK | C20: ='TOTAL STOCK'!C20 -> 0 | D20: ='TOTAL STOCK'!D20 -> 0 | E20: ='TOTAL STOCK'!E20 -> 0 | F20: ='TOTAL STOCK'!F20 -> 0 | G20: ='TOTAL STOCK'!G20 -> 0 | H20: ='TOTAL STOCK'!H20 -> 0 | I20: ='TOTAL STOCK'!I20 -> 0 | J20: ='TOTAL STOCK'!J20 -> 0 | ... L20: ='TOTAL STOCK'!L20 -> 0
A21: 18 | B21: ='SALES & RATE'!B21 -> B'LORE MALT (W) | C21: ='TOTAL STOCK'!C21 -> 0 | D21: ='TOTAL STOCK'!D21 -> 0 | E21: ='TOTAL STOCK'!E21 -> 0 | F21: ='TOTAL STOCK'!F21 -> 0 | G21: ='TOTAL STOCK'!G21 -> 4 | H21: 44 | I21: 4 | J21: 91 | K21: ='TOTAL STOCK'!K21 -> 0 | L21: ='TOTAL STOCK'!L21 -> 0
A22: 19 | B22: ='SALES & RATE'!B22 -> 0 | C22: ='TOTAL STOCK'!C22 -> 0 | D22: ='TOTAL STOCK'!D22 -> 0 | E22: ='TOTAL STOCK'!E22 -> 0 | F22: ='TOTAL STOCK'!F22 -> 0 | G22: ='TOTAL STOCK'!G22 -> 0 | H22: ='TOTAL STOCK'!H22 -> 0 | I22: ='TOTAL STOCK'!I22 -> 0 | J22: ='TOTAL STOCK'!J22 -> 0 | ... L22: ='TOTAL STOCK'!L22 -> 0
A23: 20 | B23: ='SALES & RATE'!B23 -> ROYAL STAGE | C23: ='TOTAL STOCK'!C23 -> 0 | D23: 4 | E23: ='TOTAL STOCK'!E23 -> 0 | F23: 7 | G23: 0 | H23: 56 | I23: ='TOTAL STOCK'!I23 -> 0 | J23: 92 | K23: ='TOTAL STOCK'!K23 -> 0 | L23: ='TOTAL STOCK'!L23 -> 0
A24: 21 | B24: ='SALES & RATE'!B24 -> HAYWARDS(W) | C24: ='TOTAL STOCK'!C24 -> 0 | D24: ='TOTAL STOCK'!D24 -> 0 | E24: ='TOTAL STOCK'!E24 -> 0 | F24: ='TOTAL STOCK'!F24 -> 0 | G24: 4 | H24: 59 | I24: 2 | J24: 68 | K24: ='TOTAL STOCK'!K24 -> 0 | L24: ='TOTAL STOCK'!L24 -> 0
A25: 22 | B25: ='SALES & RATE'!B25 -> CNB RED | C25: ='TOTAL STOCK'!C25 -> 0 | D25: ='TOTAL STOCK'!D25 -> 0 | E25: ='TOTAL STOCK'!E25 -> 0 | F25: ='TOTAL STOCK'!F25 -> 0 | G25: ='TOTAL STOCK'!G25 -> 0 | H25: 16 | I25: ='TOTAL STOCK'!I25 -> 0 | J25: ='TOTAL STOCK'!J25 -> 78 | K25: ='TOTAL STOCK'!K25 -> 0 | L25: ='TOTAL STOCK'!L25 -> 0
A26: 23 | B26: ='SALES & RATE'!B26 -> 8.PM (W) | C26: ='TOTAL STOCK'!C26 -> 0 | D26: ='TOTAL STOCK'!D26 -> 4 | E26: ='TOTAL STOCK'!E26 -> 0 | F26: ='TOTAL STOCK'!F26 -> 3 | G26: 0 | H26: 90 | I26: 0 | J26: 269 | K26: ='TOTAL STOCK'!K26 -> 0 | L26: ='TOTAL STOCK'!L26 -> 0
A27: 24 | B27: ='SALES & RATE'!B27 -> IMPERIAL BLUE(W) | C27: ='TOTAL STOCK'!C27 -> 0 | D27: 0 | E27: ='TOTAL STOCK'!E27 -> 0 | F27: 15 | G27: 5 | H27: 26 | I27: 4 | J27: 91 | K27: ='TOTAL STOCK'!K27 -> 0 | L27: ='TOTAL STOCK'!L27 -> 0
A28: 25 | B28: ='SALES & RATE'!B28 -> BLACK DOG(8)YRS | C28: ='TOTAL STOCK'!C28 -> 0 | D28: ='TOTAL STOCK'!D28 -> 0 | E28: ='TOTAL STOCK'!E28 -> 0 | F28: ='TOTAL STOCK'!F28 -> 0 | G28: ='TOTAL STOCK'!G28 -> 0 | H28: ='TOTAL STOCK'!H28 -> 13 | I28: ='TOTAL STOCK'!I28 -> 0 | J28: ='TOTAL STOCK'!J28 -> 0 | ... L28: ='TOTAL STOCK'!L28 -> 0
A29: 26 | B29: ='SALES & RATE'!B29 -> 100 PIPERS | C29: ='TOTAL STOCK'!C29 -> 0 | D29: ='TOTAL STOCK'!D29 -> 0 | E29: ='TOTAL STOCK'!E29 -> 0 | F29: ='TOTAL STOCK'!F29 -> 0 | G29: ='TOTAL STOCK'!G29 -> 0 | H29: 14 | I29: ='TOTAL STOCK'!I29 -> 0 | J29: ='TOTAL STOCK'!J29 -> 0 | K29: ='TOTAL STOCK'!K29 -> 0 | L29: 16
A30: 27 | B30: ='SALES & RATE'!B30 -> 8.PM (W) BLUE | C30: ='TOTAL STOCK'!C30 -> 0 | D30: ='TOTAL STOCK'!D30 -> 0 | E30: ='TOTAL STOCK'!E30 -> 0 | F30: ='TOTAL STOCK'!F30 -> 0 | G30: ='TOTAL STOCK'!G30 -> 0 | H30: ='TOTAL STOCK'!H30 -> 0 | I30: ='TOTAL STOCK'!I30 -> 0 | J30: ='TOTAL STOCK'!J30 -> 0 | ... L30: ='TOTAL STOCK'!L30 -> 0
A31: 28 | B31: ='SALES & RATE'!B31 -> TEACHERS HIGH | C31: ='TOTAL STOCK'!C31 -> 0 | D31: ='TOTAL STOCK'!D31 -> 0 | E31: ='TOTAL STOCK'!E31 -> 0 | F31: ='TOTAL STOCK'!F31 -> 0 | G31: ='TOTAL STOCK'!G31 -> 0 | H31: ='TOTAL STOCK'!H31 -> 0 | I31: ='TOTAL STOCK'!I31 -> 0 | J31: ='TOTAL STOCK'!J31 -> 0 | ... L31: ='TOTAL STOCK'!L31 -> 0
A32: 29 | B32: ='SALES & RATE'!B32 -> ANTIQUITY BLUE(W) | C32: ='TOTAL STOCK'!C32 -> 0 | D32: ='TOTAL STOCK'!D32 -> 0 | E32: ='TOTAL STOCK'!E32 -> 0 | F32: ='TOTAL STOCK'!F32 -> 0 | G32: ='TOTAL STOCK'!G32 -> 0 | H32: ='TOTAL STOCK'!H32 -> 0 | I32: ='TOTAL STOCK'!I32 -> 0 | J32: ='TOTAL STOCK'!J32 -> 0 | ... L32: ='TOTAL STOCK'!L32 -> 0
A33: 30 | B33: ='SALES & RATE'!B33 -> 0 | C33: ='TOTAL STOCK'!C33 -> 0 | D33: ='TOTAL STOCK'!D33 -> 0 | E33: ='TOTAL STOCK'!E33 -> 0 | F33: ='TOTAL STOCK'!F33 -> 0 | G33: ='TOTAL STOCK'!G33 -> 0 | H33: ='TOTAL STOCK'!H33 -> 0 | I33: ='TOTAL STOCK'!I33 -> 0 | J33: ='TOTAL STOCK'!J33 -> 0 | ... L33: ='TOTAL STOCK'!L33 -> 0
A34: 31 | B34: ='SALES & RATE'!B34 -> VAT 69 | C34: ='TOTAL STOCK'!C34 -> 0 | D34: ='TOTAL STOCK'!D34 -> 0 | E34: ='TOTAL STOCK'!E34 -> 0 | F34: ='TOTAL STOCK'!F34 -> 0 | G34: ='TOTAL STOCK'!G34 -> 0 | H34: ='TOTAL STOCK'!H34 -> 23 | I34: ='TOTAL STOCK'!I34 -> 0 | J34: ='TOTAL STOCK'!J34 -> 0 | ... L34: ='TOTAL STOCK'!L34 -> 0
A35: 32 | B35: ='SALES & RATE'!B35 -> HERCULES RUM | C35: ='TOTAL STOCK'!C35 -> 0 | D35: ='TOTAL STOCK'!D35 -> 5 | E35: ='TOTAL STOCK'!E35 -> 0 | F35: 19 | G35: 0 | H35: ='TOTAL STOCK'!H35 -> 54 | I35: ='TOTAL STOCK'!I35 -> 0 | J35: ='TOTAL STOCK'!J35 -> 0 | K35: ='TOTAL STOCK'!K35 -> 0 | L35: ='TOTAL STOCK'!L35 -> 0
A36: 33 | B36: ='SALES & RATE'!B36 -> M C RUM | C36: ='TOTAL STOCK'!C36 -> 0 | D36: ='TOTAL STOCK'!D36 -> 7 | E36: ='TOTAL STOCK'!E36 -> 0 | F36: ='TOTAL STOCK'!F36 -> 19 | G36: ='TOTAL STOCK'!G36 -> 0 | H36: ='TOTAL STOCK'!H36 -> 0 | I36: ='TOTAL STOCK'!I36 -> 0 | J36: ='TOTAL STOCK'!J36 -> 0 | ... L36: ='TOTAL STOCK'!L36 -> 0
A37: 34 | B37: ='SALES & RATE'!B37 -> OLD MONK RUM | C37: ='TOTAL STOCK'!C37 -> 0 | D37: 6 | E37: ='TOTAL STOCK'!E37 -> 1 | F37: 8 | G37: 8 | H37: 55 | I37: 5 | J37: 42 | K37: ='TOTAL STOCK'!K37 -> 0 | L37: ='TOTAL STOCK'!L37 -> 0
A38: 35 | B38: ='SALES & RATE'!B38 -> MC RUM CLASSIC | C38: ='TOTAL STOCK'!C38 -> 0 | D38: ='TOTAL STOCK'!D38 -> 0 | E38: ='TOTAL STOCK'!E38 -> 0 | F38: ='TOTAL STOCK'!F38 -> 0 | G38: 2 | H38: 41 | I38: 2 | J38: 115 | K38: ='TOTAL STOCK'!K38 -> 0 | L38: ='TOTAL STOCK'!L38 -> 0
A39: 36 | B39: ='SALES & RATE'!B39 -> 0 | C39: ='TOTAL STOCK'!C39 -> 0 | D39: ='TOTAL STOCK'!D39 -> 0 | E39: ='TOTAL STOCK'!E39 -> 0 | F39: ='TOTAL STOCK'!F39 -> 0 | G39: ='TOTAL STOCK'!G39 -> 0 | H39: ='TOTAL STOCK'!H39 -> 0 | I39: ='TOTAL STOCK'!I39 -> 0 | J39: ='TOTAL STOCK'!J39 -> 0 | ... L39: ='TOTAL STOCK'!L39 -> 0
A40: 37 | B40: ='SALES & RATE'!B40 -> BAGPIPER RUM | C40: ='TOTAL STOCK'!C40 -> 0 | D40: ='TOTAL STOCK'!D40 -> 0 | E40: ='TOTAL STOCK'!E40 -> 0 | F40: ='TOTAL STOCK'!F40 -> 0 | G40: 4 | H40: 67 | I40: ='TOTAL STOCK'!I40 -> 5 | J40: 33 | K40: ='TOTAL STOCK'!K40 -> 0 | L40: ='TOTAL STOCK'!L40 -> 0
A41: 38 | B41: ='SALES & RATE'!B41 -> BACARDI ORN+APP+LIM | C41: ='TOTAL STOCK'!C41 -> 0 | D41: ='TOTAL STOCK'!D41 -> 2 | E41: ='TOTAL STOCK'!E41 -> 0 | F41: ='TOTAL STOCK'!F41 -> 7 | G41: ='TOTAL STOCK'!G41 -> 0 | H41: 31 | I41: ='TOTAL STOCK'!I41 -> 0 | J41: ='TOTAL STOCK'!J41 -> 0 | K41: ='TOTAL STOCK'!K41 -> 0 | L41: 16
A42: 39 | B42: ='SALES & RATE'!B42 -> LEGACY RUM | C42: ='TOTAL STOCK'!C42 -> 0 | D42: ='TOTAL STOCK'!D42 -> 0 | E42: ='TOTAL STOCK'!E42 -> 0 | F42: ='TOTAL STOCK'!F42 -> 0 | G42: ='TOTAL STOCK'!G42 -> 4 | H42: 41 | I42: ='TOTAL STOCK'!I42 -> 0 | J42: ='TOTAL STOCK'!J42 -> 0 | K42: ='TOTAL STOCK'!K42 -> 0 | L42: ='TOTAL STOCK'!L42 -> 0
A43: 40 | B43: ='SALES & RATE'!B43 -> B'LORE RUM | C43: ='TOTAL STOCK'!C43 -> 0 | D43: ='TOTAL STOCK'!D43 -> 0 | E43: ='TOTAL STOCK'!E43 -> 0 | F43: ='TOTAL STOCK'!F43 -> 0 | G43: ='TOTAL STOCK'!G43 -> 4 | H43: 111 | I43: 2 | J43: 48 | K43: ='TOTAL STOCK'!K43 -> 0 | L43: ='TOTAL STOCK'!L43 -> 0
A44: 41 | B44: ='SALES & RATE'!B44 -> AMRUT RUM | C44: ='TOTAL STOCK'!C44 -> 0 | D44: ='TOTAL STOCK'!D44 -> 0 | E44: ='TOTAL STOCK'!E44 -> 0 | F44: ='TOTAL STOCK'!F44 -> 0 | G44: 2 | H44: 86 | I44: 3 | J44: 62 | K44: ='TOTAL STOCK'!K44 -> 0 | L44: ='TOTAL STOCK'!L44 -> 0
A45: 42 | B45: ='SALES & RATE'!B45 -> BLACK & WHITE (8)YRS | C45: ='TOTAL STOCK'!C45 -> 0 | D45: ='TOTAL STOCK'!D45 -> 0 | E45: ='TOTAL STOCK'!E45 -> 0 | F45: ='TOTAL STOCK'!F45 -> 0 | G45: ='TOTAL STOCK'!G45 -> 0 | H45: 10 | I45: ='TOTAL STOCK'!I45 -> 0 | J45: ='TOTAL STOCK'!J45 -> 0 | K45: ='TOTAL STOCK'!K45 -> 0 | L45: 0
A46: 43 | B46: ='SALES & RATE'!B46 -> COURIOR NEPOLIN BRANDY | C46: ='TOTAL STOCK'!C46 -> 0 | D46: 0 | E46: ='TOTAL STOCK'!E46 -> 0 | F46: ='TOTAL STOCK'!F46 -> 0 | G46: ='TOTAL STOCK'!G46 -> 0 | H46: 25 | I46: ='TOTAL STOCK'!I46 -> 0 | J46: ='TOTAL STOCK'!J46 -> 0 | K46: ='TOTAL STOCK'!K46 -> 0 | L46: ='TOTAL STOCK'!L46 -> 22
A47: 44 | B47: ='SALES & RATE'!B47 -> FIREBALL | C47: ='TOTAL STOCK'!C47 -> 0 | D47: ='TOTAL STOCK'!D47 -> 0 | E47: ='TOTAL STOCK'!E47 -> 0 | F47: ='TOTAL STOCK'!F47 -> 0 | G47: ='TOTAL STOCK'!G47 -> 0 | H47: 15 | I47: ='TOTAL STOCK'!I47 -> 0 | J47: 36 | K47: ='TOTAL STOCK'!K47 -> 0 | L47: ='TOTAL STOCK'!L47 -> 0
A48: 45 | B48: ='SALES & RATE'!B48 -> HONEY CUP BRANDY | C48: ='TOTAL STOCK'!C48 -> 0 | D48: ='TOTAL STOCK'!D48 -> 0 | E48: ='TOTAL STOCK'!E48 -> 0 | F48: ='TOTAL STOCK'!F48 -> 0 | G48: ='TOTAL STOCK'!G48 -> 0 | H48: ='TOTAL STOCK'!H48 -> 0 | I48: ='TOTAL STOCK'!I48 -> 0 | J48: 57 | K48: ='TOTAL STOCK'!K48 -> 0 | L48: ='TOTAL STOCK'!L48 -> 0
A49: 46 | B49: ='SALES & RATE'!B49 -> ROULETTE BRANDY | C49: ='TOTAL STOCK'!C49 -> 0 | D49: ='TOTAL STOCK'!D49 -> 0 | E49: ='TOTAL STOCK'!E49 -> 0 | F49: ='TOTAL STOCK'!F49 -> 0 | G49: ='TOTAL STOCK'!G49 -> 0 | H49: ='TOTAL STOCK'!H49 -> 0 | I49: ='TOTAL STOCK'!I49 -> 0 | J49: ='TOTAL STOCK'!J49 -> 0 | ... L49: ='TOTAL STOCK'!L49 -> 0
A50: 47 | B50: ='SALES & RATE'!B50 -> 0 | C50: ='TOTAL STOCK'!C50 -> 0 | D50: ='TOTAL STOCK'!D50 -> 0 | E50: ='TOTAL STOCK'!E50 -> 0 | F50: ='TOTAL STOCK'!F50 -> 0 | G50: ='TOTAL STOCK'!G50 -> 0 | H50: ='TOTAL STOCK'!H50 -> 0 | I50: ='TOTAL STOCK'!I50 -> 0 | J50: ='TOTAL STOCK'!J50 -> 0 | ... L50: ='TOTAL STOCK'!L50 -> 0
A51: Mahavishnu PAGE 2 | C51: CLOSING STOCK PAGE 2
C52: 750 ML | E52: 375 ML | G52: 180 ML | I52: 90 ML | K52: 60 ML
A53: SL. | B53: PRODUCT NAME | C53: CASES*12 | D53: BTLS | E53: CASES*24 | F53: BTLS | G53: CASES*48 | H53: BTLS | I53: CASES*96 | J53: BTLS | K53: BOX*25 | L53: BTLS
A54: 1 | B54: ='SALES & RATE'!B54 -> CARNIVAL GIN | C54: ='TOTAL STOCK'!C54 -> 0 | D54: ='TOTAL STOCK'!D54 -> 0 | E54: ='TOTAL STOCK'!E54 -> 0 | F54: ='TOTAL STOCK'!F54 -> 0 | G54: 0 | H54: 46 | I54: ='TOTAL STOCK'!I54 -> 0 | J54: 5 | K54: ='TOTAL STOCK'!K54 -> 0 | L54: ='TOTAL STOCK'!L54 -> 0
A55: 2 | B55: ='SALES & RATE'!B55 -> SMIRNOFF VODKA | C55: ='TOTAL STOCK'!C55 -> 0 | D55: ='TOTAL STOCK'!D55 -> 4 | E55: ='TOTAL STOCK'!E55 -> 0 | F55: ='TOTAL STOCK'!F55 -> 0 | G55: ='TOTAL STOCK'!G55 -> 0 | H55: 52 | I55: ='TOTAL STOCK'!I55 -> 0 | J55: ='TOTAL STOCK'!J55 -> 0 | K55: ='TOTAL STOCK'!K55 -> 0 | L55: 20
A56: 3 | B56: ='SALES & RATE'!B56 -> MUSCOVY LEMON | C56: ='TOTAL STOCK'!C56 -> 0 | D56: ='TOTAL STOCK'!D56 -> 0 | E56: ='TOTAL STOCK'!E56 -> 0 | F56: ='TOTAL STOCK'!F56 -> 0 | G56: ='TOTAL STOCK'!G56 -> 0 | H56: ='TOTAL STOCK'!H56 -> 48 | I56: ='TOTAL STOCK'!I56 -> 0 | J56: ='TOTAL STOCK'!J56 -> 0 | ... L56: ='TOTAL STOCK'!L56 -> 0
A57: 4 | B57: ='SALES & RATE'!B57 -> MUSCOVY VODKA | C57: ='TOTAL STOCK'!C57 -> 0 | D57: ='TOTAL STOCK'!D57 -> 0 | E57: ='TOTAL STOCK'!E57 -> 0 | F57: ='TOTAL STOCK'!F57 -> 0 | G57: 2 | H57: 55 | I57: 0 | J57: 105 | K57: ='TOTAL STOCK'!K57 -> 0 | L57: ='TOTAL STOCK'!L57 -> 0
A58: 5 | B58: ='SALES & RATE'!B58 -> ROMANOV VODKA | C58: ='TOTAL STOCK'!C58 -> 0 | D58: ='TOTAL STOCK'!D58 -> 0 | E58: ='TOTAL STOCK'!E58 -> 0 | F58: ='TOTAL STOCK'!F58 -> 0 | G58: ='TOTAL STOCK'!G58 -> 1 | H58: 41 | I58: ='TOTAL STOCK'!I58 -> 1 | J58: 88 | K58: ='TOTAL STOCK'!K58 -> 0 | L58: ='TOTAL STOCK'!L58 -> 0
A59: 6 | B59: ='SALES & RATE'!B59 -> GONAS WINE | C59: ='TOTAL STOCK'!C59 -> 0 | D59: ='TOTAL STOCK'!D59 -> 0 | E59: ='TOTAL STOCK'!E59 -> 0 | F59: ='TOTAL STOCK'!F59 -> 0 | G59: ='TOTAL STOCK'!G59 -> 0 | H59: 24 | I59: ='TOTAL STOCK'!I59 -> 0 | J59: ='TOTAL STOCK'!J59 -> 0 | K59: ='TOTAL STOCK'!K59 -> 0 | L59: ='TOTAL STOCK'!L59 -> 0
A60: 7 | B60: ='SALES & RATE'!B60 -> MAGIC PORT WINE | C60: ='TOTAL STOCK'!C60 -> 0 | D60: 18 | E60: ='TOTAL STOCK'!E60 -> 0 | F60: 21 | G60: ='TOTAL STOCK'!G60 -> 0 | H60: 0 | I60: ='TOTAL STOCK'!I60 -> 0 | J60: ='TOTAL STOCK'!J60 -> 0 | K60: ='TOTAL STOCK'!K60 -> 0 | L60: ='TOTAL STOCK'!L60 -> 0
A61: 8 | B61: ='SALES & RATE'!B61 -> SIDDUS WINE | C61: ='TOTAL STOCK'!C61 -> 0 | D61: 1 | E61: ='TOTAL STOCK'!E61 -> 0 | F61: 0 | G61: ='TOTAL STOCK'!G61 -> 0 | H61: 32 | I61: ='TOTAL STOCK'!I61 -> 0 | J61: ='TOTAL STOCK'!J61 -> 0 | K61: ='TOTAL STOCK'!K61 -> 0 | L61: ='TOTAL STOCK'!L61 -> 0
A62: 9 | B62: ='SALES & RATE'!B62 -> VEGA WINE | C62: ='TOTAL STOCK'!C62 -> 0 | D62: ='TOTAL STOCK'!D62 -> 0 | E62: ='TOTAL STOCK'!E62 -> 0 | F62: ='TOTAL STOCK'!F62 -> 13 | G62: ='TOTAL STOCK'!G62 -> 0 | H62: ='TOTAL STOCK'!H62 -> 0 | I62: ='TOTAL STOCK'!I62 -> 0 | J62: ='TOTAL STOCK'!J62 -> 0 | ... L62: ='TOTAL STOCK'!L62 -> 0
A63: 10 | B63: ='SALES & RATE'!B63 -> 0 | C63: ='TOTAL STOCK'!C63 -> 0 | D63: ='TOTAL STOCK'!D63 -> 0 | E63: ='TOTAL STOCK'!E63 -> 0 | F63: ='TOTAL STOCK'!F63 -> 0 | G63: ='TOTAL STOCK'!G63 -> 0 | H63: ='TOTAL STOCK'!H63 -> 0 | I63: ='TOTAL STOCK'!I63 -> 0 | J63: ='TOTAL STOCK'!J63 -> 0 | ... L63: ='TOTAL STOCK'!L63 -> 0
A64: 11 | B64: ='SALES & RATE'!B64 -> MAGIC MOMENTS | C64: ='TOTAL STOCK'!C64 -> 0 | D64: ='TOTAL STOCK'!D64 -> 2 | E64: ='TOTAL STOCK'!E64 -> 0 | F64: ='TOTAL STOCK'!F64 -> 0 | G64: 0 | H64: 31 | I64: ='TOTAL STOCK'!I64 -> 0 | J64: ='TOTAL STOCK'!J64 -> 0 | K64: 0 | L64: 26
A65: 12 | B65: ='SALES & RATE'!B65 -> BRO CODE | C65: ='TOTAL STOCK'!C65 -> 0 | D65: ='TOTAL STOCK'!D65 -> 0 | E65: ='TOTAL STOCK'!E65 -> 0 | F65: 0 | G65: ='TOTAL STOCK'!G65 -> 0 | H65: ='TOTAL STOCK'!H65 -> 0 | I65: ='TOTAL STOCK'!I65 -> 0 | J65: ='TOTAL STOCK'!J65 -> 0 | K65: ='TOTAL STOCK'!K65 -> 0 | L65: ='TOTAL STOCK'!L65 -> 0
A66: 13 | B66: ='SALES & RATE'!B66 -> TANGO RED WINE | C66: ='TOTAL STOCK'!C66 -> 0 | D66: ='TOTAL STOCK'!D66 -> 0 | E66: ='TOTAL STOCK'!E66 -> 0 | F66: ='TOTAL STOCK'!F66 -> 0 | G66: ='TOTAL STOCK'!G66 -> 0 | H66: ='TOTAL STOCK'!H66 -> 0 | I66: ='TOTAL STOCK'!I66 -> 0 | J66: ='TOTAL STOCK'!J66 -> 0 | ... L66: ='TOTAL STOCK'!L66 -> 0
A67: 14 | B67: ='SALES & RATE'!B67 -> BUZZ BALL | C67: ='TOTAL STOCK'!C67 -> 0 | D67: ='TOTAL STOCK'!D67 -> 0 | E67: ='TOTAL STOCK'!E67 -> 0 | F67: ='TOTAL STOCK'!F67 -> 0 | G67: 0 | H67: ='TOTAL STOCK'!H67 -> 0 | I67: ='TOTAL STOCK'!I67 -> 0 | J67: ='TOTAL STOCK'!J67 -> 0 | K67: ='TOTAL STOCK'!K67 -> 0 | L67: ='TOTAL STOCK'!L67 -> 0
A68: 15 | B68: ='SALES & RATE'!B68 -> 0 | C68: ='TOTAL STOCK'!C68 -> 0 | D68: ='TOTAL STOCK'!D68 -> 0 | E68: ='TOTAL STOCK'!E68 -> 0 | F68: ='TOTAL STOCK'!F68 -> 0 | G68: ='TOTAL STOCK'!G68 -> 0 | H68: ='TOTAL STOCK'!H68 -> 0 | I68: ='TOTAL STOCK'!I68 -> 0 | J68: ='TOTAL STOCK'!J68 -> 0 | ... L68: ='TOTAL STOCK'!L68 -> 0
A69: 16 | B69: ='SALES & RATE'!B69 -> 0 | C69: ='TOTAL STOCK'!C69 -> 0 | D69: ='TOTAL STOCK'!D69 -> 0 | E69: ='TOTAL STOCK'!E69 -> 0 | F69: ='TOTAL STOCK'!F69 -> 0 | G69: ='TOTAL STOCK'!G69 -> 0 | H69: ='TOTAL STOCK'!H69 -> 0 | I69: ='TOTAL STOCK'!I69 -> 0 | J69: ='TOTAL STOCK'!J69 -> 0 | ... L69: ='TOTAL STOCK'!L69 -> 0
A70: 17 | B70: ='SALES & RATE'!B70 -> 0 | C70: ='TOTAL STOCK'!C70 -> 0 | D70: ='TOTAL STOCK'!D70 -> 0 | E70: ='TOTAL STOCK'!E70 -> 0 | F70: ='TOTAL STOCK'!F70 -> 0 | G70: ='TOTAL STOCK'!G70 -> 0 | H70: ='TOTAL STOCK'!H70 -> 0 | I70: ='TOTAL STOCK'!I70 -> 0 | J70: ='TOTAL STOCK'!J70 -> 0 | ... L70: ='TOTAL STOCK'!L70 -> 0
A71: 18 | B71: ='SALES & RATE'!B71 -> 0 | C71: ='TOTAL STOCK'!C71 -> 0 | D71: ='TOTAL STOCK'!D71 -> 0 | E71: ='TOTAL STOCK'!E71 -> 0 | F71: ='TOTAL STOCK'!F71 -> 0 | G71: ='TOTAL STOCK'!G71 -> 0 | H71: ='TOTAL STOCK'!H71 -> 0 | I71: ='TOTAL STOCK'!I71 -> 0 | J71: ='TOTAL STOCK'!J71 -> 0 | ... L71: ='TOTAL STOCK'!L71 -> 0
A72: BEERS | C72: CLOSING STOCK
C73: 650 ML | E73: 500 ML TIN(CAN) | G73: 330 ML (PINT) | I73: 330 ML TIN(CAN) | M73: PRESENT CLOSINGS
A74: SL. | B74: PRODUCT NAME | C74: CASES*12 | D74: BTLS | E74: CASES*24 | F74: BTLS | G74: CASES*24 | H74: BTLS | I74: CASES*24 | J74: BTLS | M74: CREDIT BILLS
A75: 1 | B75: ='SALES & RATE'!B75 -> K.F PREMIUM | C75: 0 | D75: 0 | E75: ='TOTAL STOCK'!E75 -> 0 | F75: ='TOTAL STOCK'!F75 -> 0 | G75: ='TOTAL STOCK'!G75 -> 0 | H75: ='TOTAL STOCK'!H75 -> 0 | I75: ='TOTAL STOCK'!I75 -> 0 | J75: ='TOTAL STOCK'!J75 -> 0 | M75: 95450
A76: 2 | B76: ='SALES & RATE'!B76 -> K.F STRONG | C76: 58 | D76: 42 | E76: 0 | F76: 34 | G76: 0 | H76: 9 | I76: 0 | J76: 13 | M76: GALLA CASH
A77: 3 | B77: ='SALES & RATE'!B77 -> U.B EXPORT | C77: 0 | D77: 27 | E77: ='TOTAL STOCK'!E77 -> 0 | F77: ='TOTAL STOCK'!F77 -> 0 | G77: ='TOTAL STOCK'!G77 -> 0 | H77: ='TOTAL STOCK'!H77 -> 0 | I77: ='TOTAL STOCK'!I77 -> 0 | J77: ='TOTAL STOCK'!J77 -> 0 | M77: 34750
A78: 4 | B78: ='SALES & RATE'!B78 -> KNOCK OUT | C78: 0 | D78: 10 | E78: ='TOTAL STOCK'!E78 -> 0 | F78: 0 | G78: 0 | H78: 3 | I78: ='TOTAL STOCK'!I78 -> 0 | J78: ='TOTAL STOCK'!J78 -> 0 | M78: CIGRETE
A79: 5 | B79: ='SALES & RATE'!B79 -> K.F STROM | C79: ='TOTAL STOCK'!C79 -> 0 | D79: ='TOTAL STOCK'!D79 -> 0 | E79: ='TOTAL STOCK'!E79 -> 0 | F79: ='TOTAL STOCK'!F79 -> 0 | G79: ='TOTAL STOCK'!G79 -> 0 | H79: ='TOTAL STOCK'!H79 -> 0 | I79: ='TOTAL STOCK'!I79 -> 0 | J79: ='TOTAL STOCK'!J79 -> 0 | M79: 34400
A80: 6 | B80: ='SALES & RATE'!B80 -> BUDWISER MAGNUM | C80: 9 | D80: 42 | E80: ='TOTAL STOCK'!E80 -> 0 | F80: 11 | G80: ='TOTAL STOCK'!G80 -> 0 | H80: ='TOTAL STOCK'!H80 -> 0 | I80: ='TOTAL STOCK'!I80 -> 0 | J80: ='TOTAL STOCK'!J80 -> 0 | M80: EXPENCES
A81: 7 | B81: ='SALES & RATE'!B81 -> BUDWISER PREM | C81: 0 | D81: 5 | E81: ='TOTAL STOCK'!E81 -> 0 | F81: 18 | G81: ='TOTAL STOCK'!G81 -> 0 | H81: ='TOTAL STOCK'!H81 -> 0 | I81: ='TOTAL STOCK'!I81 -> 0 | J81: ='TOTAL STOCK'!J81 -> 0 | M81: =EXPENDITURE!C10 -> 147440
A82: 8 | B82: ='SALES & RATE'!B82 -> K.F ULTRA/ WITT BEER | C82: ='TOTAL STOCK'!C82 -> 0 | D82: 0 | E82: ='TOTAL STOCK'!E82 -> 0 | F82: ='TOTAL STOCK'!F82 -> 0 | G82: ='TOTAL STOCK'!G82 -> 0 | H82: ='TOTAL STOCK'!H82 -> 0 | I82: ='TOTAL STOCK'!I82 -> 0 | J82: ='TOTAL STOCK'!J82 -> 0 | M82: CASH TO BANK
A83: 9 | B83: ='SALES & RATE'!B83 -> TOBURG STRONG BEER | C83: 0 | D83: 3 | E83: 0 | F83: 27 | G83: 1 | H83: 19 | I83: ='TOTAL STOCK'!I83 -> 0 | J83: ='TOTAL STOCK'!J83 -> 0 | M83: 265000
A84: 10 | B84: ='SALES & RATE'!B84 -> POWERCOOL | C84: 3 | D84: 9 | E84: ='TOTAL STOCK'!E84 -> 0 | F84: 11 | G84: ='TOTAL STOCK'!G84 -> 0 | H84: 0 | I84: ='TOTAL STOCK'!I84 -> 0 | J84: ='TOTAL STOCK'!J84 -> 0 | M84: CASH SALES
A85: 11 | B85: ='SALES & RATE'!B85 -> BACARDI + | C85: ='TOTAL STOCK'!C85 -> 0 | D85: ='TOTAL STOCK'!D85 -> 0 | E85: ='TOTAL STOCK'!E85 -> 0 | F85: ='TOTAL STOCK'!F85 -> 0 | G85: 0 | H85: 55 | I85: ='TOTAL STOCK'!I85 -> 0 | J85: ='TOTAL STOCK'!J85 -> 0 | M85: 270000
A86: 12 | B86: ='SALES & RATE'!B86 -> BACARDI BREEZER | C86: ='TOTAL STOCK'!C86 -> 0 | D86: ='TOTAL STOCK'!D86 -> 0 | E86: ='TOTAL STOCK'!E86 -> 0 | F86: ='TOTAL STOCK'!F86 -> 0 | G86: ='TOTAL STOCK'!G86 -> 0 | H86: 0 | I86: ='TOTAL STOCK'!I86 -> 0 | J86: ='TOTAL STOCK'!J86 -> 0 | M86: CARD SALE + PAYTM
A87: 13 | B87: ='SALES & RATE'!B87 -> RC / BULLET BEER | C87: 0 | D87: 0 | E87: ='TOTAL STOCK'!E87 -> 0 | F87: 2 | G87: ='TOTAL STOCK'!G87 -> 0 | H87: ='TOTAL STOCK'!H87 -> 0 | I87: ='TOTAL STOCK'!I87 -> 0 | J87: ='TOTAL STOCK'!J87 -> 0 | M87: 692507
A88: 14 | B88: ='SALES & RATE'!B88 -> HUNTER | C88: ='TOTAL STOCK'!C88 -> 0 | D88: ='TOTAL STOCK'!D88 -> 0 | E88: ='TOTAL STOCK'!E88 -> 0 | F88: ='TOTAL STOCK'!F88 -> 0 | G88: ='TOTAL STOCK'!G88 -> 0 | H88: ='TOTAL STOCK'!H88 -> 0 | I88: ='TOTAL STOCK'!I88 -> 0 | J88: ='TOTAL STOCK'!J88 -> 0 | M88: TOTAL SALES
A89: 15 | B89: ='SALES & RATE'!B89 -> CARLSBERG ELE STRONG | C89: 0 | D89: 18 | E89: 0 | F89: 24 | G89: ='TOTAL STOCK'!G89 -> 0 | H89: ='TOTAL STOCK'!H89 -> 0 | I89: ='TOTAL STOCK'!I89 -> 0 | J89: ='TOTAL STOCK'!J89 -> 0 | M89: ='OPENING STOCK'!M75+'OPENING STOCK'!M77+'OPENING STOCK'!M79+'SALES & RATE'!M101 -> 1263810
A90: 16 | B90: ='SALES & RATE'!B90 -> SUNNY STRONG | C90: 0 | D90: ='TOTAL STOCK'!D90 -> 0 | E90: ='TOTAL STOCK'!E90 -> 0 | F90: ='TOTAL STOCK'!F90 -> 0 | G90: ='TOTAL STOCK'!G90 -> 0 | H90: ='TOTAL STOCK'!H90 -> 0 | I90: ='TOTAL STOCK'!I90 -> 0 | J90: ='TOTAL STOCK'!J90 -> 0 | M90: TOTAL COLLECTION
A91: 17 | B91: ='SALES & RATE'!B91 -> FOSTERS BEER | C91: ='TOTAL STOCK'!C91 -> 0 | D91: ='TOTAL STOCK'!D91 -> 0 | E91: ='TOTAL STOCK'!E91 -> 0 | F91: ='TOTAL STOCK'!F91 -> 0 | G91: ='TOTAL STOCK'!G91 -> 0 | H91: ='TOTAL STOCK'!H91 -> 0 | I91: ='TOTAL STOCK'!I91 -> 0 | J91: ='TOTAL STOCK'!J91 -> 0 | M91: =M85+M87 -> 962507
A92: 18 | B92: ='SALES & RATE'!B92 -> HEINEKEN BEER | C92: ='TOTAL STOCK'!C92 -> 0 | D92: ='TOTAL STOCK'!D92 -> 0 | E92: ='TOTAL STOCK'!E92 -> 0 | F92: ='TOTAL STOCK'!F92 -> 0 | G92: ='TOTAL STOCK'!G92 -> 0 | H92: ='TOTAL STOCK'!H92 -> 0 | I92: ='TOTAL STOCK'!I92 -> 0 | J92: ='TOTAL STOCK'!J92 -> 0 | M92: DIFFRENCE
A93: 19 | B93: ='SALES & RATE'!B93 -> TUBORG CLASSIC | C93: ='TOTAL STOCK'!C93 -> 0 | D93: 11 | E93: ='TOTAL STOCK'!E93 -> 0 | F93: ='TOTAL STOCK'!F93 -> 0 | G93: ='TOTAL STOCK'!G93 -> 0 | H93: ='TOTAL STOCK'!H93 -> 0 | I93: ='TOTAL STOCK'!I93 -> 0 | J93: ='TOTAL STOCK'!J93 -> 0 | M93: =M91-M95 -> 10737
A94: 20 | B94: ='SALES & RATE'!B94 -> 0 | C94: ='TOTAL STOCK'!C94 -> 0 | D94: ='TOTAL STOCK'!D94 -> 0 | E94: ='TOTAL STOCK'!E94 -> 0 | F94: ='TOTAL STOCK'!F94 -> 0 | G94: ='TOTAL STOCK'!G94 -> 0 | H94: ='TOTAL STOCK'!H94 -> 0 | I94: ='TOTAL STOCK'!I94 -> 0 | J94: ='TOTAL STOCK'!J94 -> 0 | M94: BALANCE AMOUNT
A95: BEVERAGES | C95: CLOSING STOCK | M95: =M89-(M75+M77+M79+M81) -> 951770
C96: 2 LTRS | E96: 1 LTRS | G96: 500 ML-600 ML | I96: 250 ML | M96: GRAND TOTAL
A97: SL. | B97: PRODUCT NAME | C97: CASES*9 | D97: BTLS | E97: CASES*12 | F97: BTLS | G97: CASES*24 | H97: BTLS | I97: CASES*30 | J97: BTLS | M97: =M91+'OPENING STOCK'!M99 -> 1027507
A98: 1 | B98: ='SALES & RATE'!B98 -> COOL DRINKS | C98: ='TOTAL STOCK'!C98 -> 0 | D98: ='TOTAL STOCK'!D98 -> 0 | E98: ='TOTAL STOCK'!E98 -> 0 | F98: ='TOTAL STOCK'!F98 -> 0 | G98: 2 | H98: 68 | I98: 5 | J98: 87 | M98: TOTAL- CASH IN LOCKER
A99: 2 | B99: ='SALES & RATE'!B99 -> SODA*12/REDBULL*24 | C99: ='TOTAL STOCK'!C99 -> 0 | D99: ='TOTAL STOCK'!D99 -> 0 | E99: ='TOTAL STOCK'!E99 -> 0 | F99: ='TOTAL STOCK'!F99 -> 0 | G99: 5 | H99: 5 | I99: 0 | J99: 11 | M99: =M97-(M87+M83) -> 70000
A100: 3 | B100: ='SALES & RATE'!B100 -> MIN WATER | C100: 6 | D100: ='TOTAL STOCK'!D100 -> 21 | E100: 2 | F100: 31 | G100: 2 | H100: 27 | I100: ='TOTAL STOCK'!I100 -> 0 | J100: ='TOTAL STOCK'!J100 -> 0

Sheet SALES & RATE
A1: Mahavishnu | C1: SALES | M1: AMOUNT | N1: RATES
C2: 750 ML | E2: 375 ML | G2: 180 ML | I2: 90 ML | K2: 60 ML | N2: 750 ML | O2: 375 ML | P2: 180 ML | Q2: 90 ML | R2: 60 ML
A3: SL. | B3: PRODUCT NAME | C3: CASES*12 | D3: BTLS | E3: CASES*24 | F3: BTLS | G3: CASES*48 | H3: BTLS | I3: CASES*96 | J3: BTLS | K3: BOX*25 | L3: BTLS | N3: RATE | O3: RATE | P3: RATE | Q3: RATE | R3: RATE
A4: 1 | B4: M H BRANDY | C4: ='TOTAL STOCK'!C4-'CLOSING STOCK'!C4 -> 0 | D4: ='TOTAL STOCK'!D4-'CLOSING STOCK'!D4 -> 2 | E4: ='TOTAL STOCK'!E4-'CLOSING STOCK'!E4 -> 1 | F4: ='TOTAL STOCK'!F4-'CLOSING STOCK'!F4 -> -13 | G4: ='TOTAL STOCK'!G4-'CLOSING STOCK'!G4 -> 4 | H4: ='TOTAL STOCK'!H4-'CLOSING STOCK'!H4 -> -6 | I4: ='TOTAL STOCK'!I4-'CLOSING STOCK'!I4 -> 1 | J4: ='TOTAL STOCK'!J4-'CLOSING STOCK'!J4 -> -3 | ... L4: ='TOTAL STOCK'!L4-'CLOSING STOCK'!L4 -> 0 | M4: =(C4*12*N4)+(D4*N4)+(E4*24*O4)+(F4*O4)+(G4*48*P4)+(H4*P4)+(I4*96*Q4)+(J4*Q4)+(K4*25*R4)+(L4*R4) -> 73350 | N4: 1100 | O4: 550 | P4: 275 | Q4: 150 | R4: 140
A5: 2 | B5: MC BRANDY | C5: ='TOTAL STOCK'!C5-'CLOSING STOCK'!C5 -> 0 | D5: ='TOTAL STOCK'!D5-'CLOSING STOCK'!D5 -> 3 | E5: ='TOTAL STOCK'!E5-'CLOSING STOCK'!E5 -> 0 | F5: ='TOTAL STOCK'!F5-'CLOSING STOCK'!F5 -> 4 | G5: ='TOTAL STOCK'!G5-'CLOSING STOCK'!G5 -> 6 | H5: ='TOTAL STOCK'!H5-'CLOSING STOCK'!H5 -> 43 | I5: ='TOTAL STOCK'!I5-'CLOSING STOCK'!I5 -> 2 | J5: ='TOTAL STOCK'!J5-'CLOSING STOCK'!J5 -> -9 | ... L5: ='TOTAL STOCK'!L5-'CLOSING STOCK'!L5 -> 0 | M5: =(C5*12*N5)+(D5*N5)+(E5*24*O5)+(F5*O5)+(G5*48*P5)+(H5*P5)+(I5*96*Q5)+(J5*Q5)+(K5*25*R5)+(L5*R5) -> 97425 | N5: 860 | O5: 430 | P5: 215 | Q5: 120 | R5: 90
A6: 3 | B6: O.C.BRANDY | C6: ='TOTAL STOCK'!C6-'CLOSING STOCK'!C6 -> 0 | D6: ='TOTAL STOCK'!D6-'CLOSING STOCK'!D6 -> 0 | E6: ='TOTAL STOCK'!E6-'CLOSING STOCK'!E6 -> 0 | F6: ='TOTAL STOCK'!F6-'CLOSING STOCK'!F6 -> 0 | G6: ='TOTAL STOCK'!G6-'CLOSING STOCK'!G6 -> 3 | H6: ='TOTAL STOCK'!H6-'CLOSING STOCK'!H6 -> 34 | I6: ='TOTAL STOCK'!I6-'CLOSING STOCK'!I6 -> 2 | J6: ='TOTAL STOCK'!J6-'CLOSING STOCK'!J6 -> -22 | ... L6: ='TOTAL STOCK'!L6-'CLOSING STOCK'!L6 -> 0 | M6: =(C6*12*N6)+(D6*N6)+(E6*24*O6)+(F6*O6)+(G6*48*P6)+(H6*P6)+(I6*96*Q6)+(J6*Q6)+(K6*25*R6)+(L6*R6) -> 28930 | N6: 400 | O6: 200 | P6: 110 | Q6: 55
A7: 4 | B7: AMRUT SILVER CUP | C7: ='TOTAL STOCK'!C7-'CLOSING STOCK'!C7 -> 0 | D7: ='TOTAL STOCK'!D7-'CLOSING STOCK'!D7 -> 0 | E7: ='TOTAL STOCK'!E7-'CLOSING STOCK'!E7 -> 0 | F7: ='TOTAL STOCK'!F7-'CLOSING STOCK'!F7 -> 0 | G7: ='TOTAL STOCK'!G7-'CLOSING STOCK'!G7 -> 0 | H7: ='TOTAL STOCK'!H7-'CLOSING STOCK'!H7 -> 20 | I7: ='TOTAL STOCK'!I7-'CLOSING STOCK'!I7 -> 2 | J7: ='TOTAL STOCK'!J7-'CLOSING STOCK'!J7 -> -23 | ... L7: ='TOTAL STOCK'!L7-'CLOSING STOCK'!L7 -> 0 | M7: =(C7*12*N7)+(D7*N7)+(E7*24*O7)+(F7*O7)+(G7*48*P7)+(H7*P7)+(I7*96*Q7)+(J7*Q7)+(K7*25*R7)+(L7*R7) -> 10650 | N7: 400 | O7: 200 | P7: 110 | Q7: 50
A8: 5 | B8: HONEY BEE BRANDY | C8: ='TOTAL STOCK'!C8-'CLOSING STOCK'!C8 -> 0 | D8: ='TOTAL STOCK'!D8-'CLOSING STOCK'!D8 -> 0 | E8: ='TOTAL STOCK'!E8-'CLOSING STOCK'!E8 -> 0 | F8: ='TOTAL STOCK'!F8-'CLOSING STOCK'!F8 -> 0 | G8: ='TOTAL STOCK'!G8-'CLOSING STOCK'!G8 -> 0 | H8: ='TOTAL STOCK'!H8-'CLOSING STOCK'!H8 -> 12 | I8: ='TOTAL STOCK'!I8-'CLOSING STOCK'!I8 -> 0 | J8: ='TOTAL STOCK'!J8-'CLOSING STOCK'!J8 -> 12 | ... L8: ='TOTAL STOCK'!L8-'CLOSING STOCK'!L8 -> 0 | M8: =(C8*12*N8)+(D8*N8)+(E8*24*O8)+(F8*O8)+(G8*48*P8)+(H8*P8)+(I8*96*Q8)+(J8*Q8)+(K8*25*R8)+(L8*R8) -> 3240 | N8: 720 | O8: 360 | P8: 180 | Q8: 90
A9: 6 | B9: O A BRANDY | C9: ='TOTAL STOCK'!C9-'CLOSING STOCK'!C9 -> 0 | D9: ='TOTAL STOCK'!D9-'CLOSING STOCK'!D9 -> 0 | E9: ='TOTAL STOCK'!E9-'CLOSING STOCK'!E9 -> 0 | F9: ='TOTAL STOCK'!F9-'CLOSING STOCK'!F9 -> 0 | G9: ='TOTAL STOCK'!G9-'CLOSING STOCK'!G9 -> 2 | H9: ='TOTAL STOCK'!H9-'CLOSING STOCK'!H9 -> 2 | I9: ='TOTAL STOCK'!I9-'CLOSING STOCK'!I9 -> 1 | J9: ='TOTAL STOCK'!J9-'CLOSING STOCK'!J9 -> -42 | ... L9: ='TOTAL STOCK'!L9-'CLOSING STOCK'!L9 -> 0 | M9: =(C9*9*N9)+(D9*N9)+(E9*24*O9)+(F9*O9)+(G9*48*P9)+(H9*P9)+(I9*96*Q9)+(J9*Q9)+(K9*25*R9)+(L9*R9) -> 19780 | N9: 700 | O9: 350 | P9: 155 | Q9: 85
A10: 7 | B10: BEJOIS BRANDY | C10: ='TOTAL STOCK'!C10-'CLOSING STOCK'!C10 -> 0 | D10: ='TOTAL STOCK'!D10-'CLOSING STOCK'!D10 -> 0 | E10: ='TOTAL STOCK'!E10-'CLOSING STOCK'!E10 -> 0 | F10: ='TOTAL STOCK'!F10-'CLOSING STOCK'!F10 -> 0 | G10: ='TOTAL STOCK'!G10-'CLOSING STOCK'!G10 -> 3 | H10: ='TOTAL STOCK'!H10-'CLOSING STOCK'!H10 -> 3 | I10: ='TOTAL STOCK'!I10-'CLOSING STOCK'!I10 -> 1 | J10: ='TOTAL STOCK'!J10-'CLOSING STOCK'!J10 -> -2 | ... L10: ='TOTAL STOCK'!L10-'CLOSING STOCK'!L10 -> 0 | M10: =(C10*9*N10)+(D10*N10)+(E10*24*O10)+(F10*O10)+(G10*48*P10)+(H10*P10)+(I10*96*Q10)+(J10*Q10)+(K10*25*R10)+(L10*R10) -> 30775 | N10: 700 | O10: 350 | P10: 155 | Q10: 85
A11: 8 | B11: MORPHIS BRANDY | C11: ='TOTAL STOCK'!C11-'CLOSING STOCK'!C11 -> 0 | D11: ='TOTAL STOCK'!D11-'CLOSING STOCK'!D11 -> 0 | E11: ='TOTAL STOCK'!E11-'CLOSING STOCK'!E11 -> 0 | F11: ='TOTAL STOCK'!F11-'CLOSING STOCK'!F11 -> 0 | G11: ='TOTAL STOCK'!G11-'CLOSING STOCK'!G11 -> 0 | H11: ='TOTAL STOCK'!H11-'CLOSING STOCK'!H11 -> 9 | I11: ='TOTAL STOCK'!I11-'CLOSING STOCK'!I11 -> 0 | J11: ='TOTAL STOCK'!J11-'CLOSING STOCK'!J11 -> 0 | ... L11: ='TOTAL STOCK'!L11-'CLOSING STOCK'!L11 -> 14 | M11: =(C11*12*N11)+(D11*N11)+(E11*24*O11)+(F11*O11)+(G11*48*P11)+(H11*P11)+(I11*96*Q11)+(J11*Q11)+(K11*25*R11)+(L11*R11) -> 6290 | N11: 1800 | O11: 900 | P11: 450 | Q11: 225 | R11: 160
A12: 9 | B12: M C WHISKY | C12: ='TOTAL STOCK'!C12-'CLOSING STOCK'!C12 -> 0 | D12: ='TOTAL STOCK'!D12-'CLOSING STOCK'!D12 -> 1 | E12: ='TOTAL STOCK'!E12-'CLOSING STOCK'!E12 -> 0 | F12: ='TOTAL STOCK'!F12-'CLOSING STOCK'!F12 -> 2 | G12: ='TOTAL STOCK'!G12-'CLOSING STOCK'!G12 -> 1 | H12: ='TOTAL STOCK'!H12-'CLOSING STOCK'!H12 -> 30 | I12: ='TOTAL STOCK'!I12-'CLOSING STOCK'!I12 -> 0 | J12: ='TOTAL STOCK'!J12-'CLOSING STOCK'!J12 -> 54 | ... L12: ='TOTAL STOCK'!L12-'CLOSING STOCK'!L12 -> 0 | M12: =(C12*12*N12)+(D12*N12)+(E12*24*O12)+(F12*O12)+(G12*48*P12)+(H12*P12)+(I12*96*Q12)+(J12*Q12)+(K12*25*R12)+(L12*R12) -> 31210 | N12: 1100 | O12: 550 | P12: 275 | Q12: 140
A13: 10 | B13: BAGPIPER (W) | C13: ='TOTAL STOCK'!C13-'CLOSING STOCK'!C13 -> 0 | D13: ='TOTAL STOCK'!D13-'CLOSING STOCK'!D13 -> 0 | E13: ='TOTAL STOCK'!E13-'CLOSING STOCK'!E13 -> 0 | F13: ='TOTAL STOCK'!F13-'CLOSING STOCK'!F13 -> 2 | G13: ='TOTAL STOCK'!G13-'CLOSING STOCK'!G13 -> 7 | H13: ='TOTAL STOCK'!H13-'CLOSING STOCK'!H13 -> -23 | I13: ='TOTAL STOCK'!I13-'CLOSING STOCK'!I13 -> 2 | J13: ='TOTAL STOCK'!J13-'CLOSING STOCK'!J13 -> 34 | ... L13: ='TOTAL STOCK'!L13-'CLOSING STOCK'!L13 -> 0 | M13: =(C13*12*N13)+(D13*N13)+(E13*24*O13)+(F13*O13)+(G13*48*P13)+(H13*P13)+(I13*96*Q13)+(J13*Q13)+(K13*25*R13)+(L13*R13) -> 68425 | N13: 700 | O13: 350 | P13: 155 | Q13: 85
A14: 11 | B14: SIGNATURE (W) | C14: ='TOTAL STOCK'!C14-'CLOSING STOCK'!C14 -> 0 | D14: ='TOTAL STOCK'!D14-'CLOSING STOCK'!D14 -> 0 | E14: ='TOTAL STOCK'!E14-'CLOSING STOCK'!E14 -> 0 | F14: ='TOTAL STOCK'!F14-'CLOSING STOCK'!F14 -> 0 | G14: ='TOTAL STOCK'!G14-'CLOSING STOCK'!G14 -> 0 | H14: ='TOTAL STOCK'!H14-'CLOSING STOCK'!H14 -> 0 | I14: ='TOTAL STOCK'!I14-'CLOSING STOCK'!I14 -> 0 | J14: ='TOTAL STOCK'!J14-'CLOSING STOCK'!J14 -> 0 | ... L14: ='TOTAL STOCK'!L14-'CLOSING STOCK'!L14 -> 0 | M14: =(C14*12*N14)+(D14*N14)+(E14*24*O14)+(F14*O14)+(G14*48*P14)+(H14*P14)+(I14*96*Q14)+(J14*Q14)+(K14*25*R14)+(L14*R14) -> 0 | N14: 2000 | O14: 1000 | P14: 500 | Q14: 250 | R14: 200
A15: 12 | B15: O T WHISKY | C15: ='TOTAL STOCK'!C15-'CLOSING STOCK'!C15 -> 0 | D15: ='TOTAL STOCK'!D15-'CLOSING STOCK'!D15 -> 0 | E15: ='TOTAL STOCK'!E15-'CLOSING STOCK'!E15 -> 0 | F15: ='TOTAL STOCK'!F15-'CLOSING STOCK'!F15 -> 0 | G15: ='TOTAL STOCK'!G15-'CLOSING STOCK'!G15 -> 0 | H15: ='TOTAL STOCK'!H15-'CLOSING STOCK'!H15 -> 6 | I15: ='TOTAL STOCK'!I15-'CLOSING STOCK'!I15 -> 0 | J15: ='TOTAL STOCK'!J15-'CLOSING STOCK'!J15 -> 9 | ... L15: ='TOTAL STOCK'!L15-'CLOSING STOCK'!L15 -> 0 | M15: =(C15*12*N15)+(D15*N15)+(E15*24*O15)+(F15*O15)+(G15*48*P15)+(H15*P15)+(I15*96*Q15)+(J15*Q15)+(K15*25*R15)+(L15*R15) -> 1695 | N15: 520 | O15: 260 | P15: 155 | Q15: 85
A16: 13 | B16: DSP BLACK(W) | C16: ='TOTAL STOCK'!C16-'CLOSING STOCK'!C16 -> 0 | D16: ='TOTAL STOCK'!D16-'CLOSING STOCK'!D16 -> 1 | E16: ='TOTAL STOCK'!E16-'CLOSING STOCK'!E16 -> 0 | F16: ='TOTAL STOCK'!F16-'CLOSING STOCK'!F16 -> 4 | G16: ='TOTAL STOCK'!G16-'CLOSING STOCK'!G16 -> 2 | H16: ='TOTAL STOCK'!H16-'CLOSING STOCK'!H16 -> 31 | I16: ='TOTAL STOCK'!I16-'CLOSING STOCK'!I16 -> 1 | J16: ='TOTAL STOCK'!J16-'CLOSING STOCK'!J16 -> -36 | ... L16: ='TOTAL STOCK'!L16-'CLOSING STOCK'!L16 -> 0 | M16: =(C16*12*N16)+(D16*N16)+(E16*24*O16)+(F16*O16)+(G16*48*P16)+(H16*P16)+(I16*96*Q16)+(J16*Q16)+(K16*25*R16)+(L16*R16) -> 37085 | N16: 860 | O16: 430 | P16: 215 | Q16: 120
A17: 14 | B17: O C WHISKY | C17: ='TOTAL STOCK'!C17-'CLOSING STOCK'!C17 -> 0 | D17: ='TOTAL STOCK'!D17-'CLOSING STOCK'!D17 -> 0 | E17: ='TOTAL STOCK'!E17-'CLOSING STOCK'!E17 -> 0 | F17: ='TOTAL STOCK'!F17-'CLOSING STOCK'!F17 -> 0 | G17: ='TOTAL STOCK'!G17-'CLOSING STOCK'!G17 -> 4 | H17: ='TOTAL STOCK'!H17-'CLOSING STOCK'!H17 -> -12 | I17: ='TOTAL STOCK'!I17-'CLOSING STOCK'!I17 -> 2 | J17: ='TOTAL STOCK'!J17-'CLOSING STOCK'!J17 -> 14 | ... L17: ='TOTAL STOCK'!L17-'CLOSING STOCK'!L17 -> 0 | M17: =(C17*12*N17)+(D17*N17)+(E17*24*O17)+(F17*O17)+(G17*48*P17)+(H17*P17)+(I17*96*Q17)+(J17*Q17)+(K17*25*R17)+(L17*R17) -> 31130 | N17: 400 | O17: 200 | P17: 110 | Q17: 55
A18: 15 | B18: R C WHISKY | C18: ='TOTAL STOCK'!C18-'CLOSING STOCK'!C18 -> 0 | D18: ='TOTAL STOCK'!D18-'CLOSING STOCK'!D18 -> 0 | E18: ='TOTAL STOCK'!E18-'CLOSING STOCK'!E18 -> 0 | F18: ='TOTAL STOCK'!F18-'CLOSING STOCK'!F18 -> 0 | G18: ='TOTAL STOCK'!G18-'CLOSING STOCK'!G18 -> 0 | H18: ='TOTAL STOCK'!H18-'CLOSING STOCK'!H18 -> 0 | I18: ='TOTAL STOCK'!I18-'CLOSING STOCK'!I18 -> 0 | J18: ='TOTAL STOCK'!J18-'CLOSING STOCK'!J18 -> 0 | ... L18: ='TOTAL STOCK'!L18-'CLOSING STOCK'!L18 -> 0 | M18: =(C18*12*N18)+(D18*N18)+(E18*24*O18)+(F18*O18)+(G18*48*P18)+(H18*P18)+(I18*96*Q18)+(J18*Q18)+(K18*25*R18)+(L18*R18) -> 0 | N18: 1800 | O18: 900 | P18: 340 | Q18: 195
A19: 16 | B19: BLENDERS PRIDE | C19: ='TOTAL STOCK'!C19-'CLOSING STOCK'!C19 -> 0 | D19: ='TOTAL STOCK'!D19-'CLOSING STOCK'!D19 -> 0 | E19: ='TOTAL STOCK'!E19-'CLOSING STOCK'!E19 -> 0 | F19: ='TOTAL STOCK'!F19-'CLOSING STOCK'!F19 -> 0 | G19: ='TOTAL STOCK'!G19-'CLOSING STOCK'!G19 -> 0 | H19: ='TOTAL STOCK'!H19-'CLOSING STOCK'!H19 -> 4 | I19: ='TOTAL STOCK'!I19-'CLOSING STOCK'!I19 -> 0 | J19: ='TOTAL STOCK'!J19-'CLOSING STOCK'!J19 -> 0 | ... L19: ='TOTAL STOCK'!L19-'CLOSING STOCK'!L19 -> 11 | M19: =(C19*12*N19)+(D19*N19)+(E19*24*O19)+(F19*O19)+(G19*48*P19)+(H19*P19)+(I19*96*Q19)+(J19*Q19)+(K19*25*R19)+(L19*R19) -> 3910 | N19: 2000 | O19: 1000 | P19: 510 | Q19: 240 | R19: 170
A20: 17 | B20: AFTER DARK | C20: ='TOTAL STOCK'!C20-'CLOSING STOCK'!C20 -> 0 | D20: ='TOTAL STOCK'!D20-'CLOSING STOCK'!D20 -> 0 | E20: ='TOTAL STOCK'!E20-'CLOSING STOCK'!E20 -> 0 | F20: ='TOTAL STOCK'!F20-'CLOSING STOCK'!F20 -> 0 | G20: ='TOTAL STOCK'!G20-'CLOSING STOCK'!G20 -> 0 | H20: ='TOTAL STOCK'!H20-'CLOSING STOCK'!H20 -> 0 | I20: ='TOTAL STOCK'!I20-'CLOSING STOCK'!I20 -> 0 | J20: ='TOTAL STOCK'!J20-'CLOSING STOCK'!J20 -> 0 | ... L20: ='TOTAL STOCK'!L20-'CLOSING STOCK'!L20 -> 0 | M20: =(C20*12*N20)+(D20*N20)+(E20*24*O20)+(F20*O20)+(G20*48*P20)+(H20*P20)+(I20*96*Q20)+(J20*Q20)+(K20*25*R20)+(L20*R20) -> 0 | N20: 1080 | O20: 540 | P20: 270 | Q20: 150
A21: 18 | B21: B'LORE MALT (W) | C21: ='TOTAL STOCK'!C21-'CLOSING STOCK'!C21 -> 0 | D21: ='TOTAL STOCK'!D21-'CLOSING STOCK'!D21 -> 0 | E21: ='TOTAL STOCK'!E21-'CLOSING STOCK'!E21 -> 0 | F21: ='TOTAL STOCK'!F21-'CLOSING STOCK'!F21 -> 0 | G21: ='TOTAL STOCK'!G21-'CLOSING STOCK'!G21 -> 0 | H21: ='TOTAL STOCK'!H21-'CLOSING STOCK'!H21 -> 2 | I21: ='TOTAL STOCK'!I21-'CLOSING STOCK'!I21 -> 1 | J21: ='TOTAL STOCK'!J21-'CLOSING STOCK'!J21 -> -71 | ... L21: ='TOTAL STOCK'!L21-'CLOSING STOCK'!L21 -> 0 | M21: =(C21*12*N21)+(D21*N21)+(E21*24*O21)+(F21*O21)+(G21*48*P21)+(H21*P21)+(I21*96*Q21)+(J21*Q21)+(K21*25*R21)+(L21*R21) -> 1450 | N21: 340 | O21: 170 | P21: 100 | Q21: 50
A22: 19 | B22: 0 | C22: ='TOTAL STOCK'!C22-'CLOSING STOCK'!C22 -> 0 | D22: ='TOTAL STOCK'!D22-'CLOSING STOCK'!D22 -> 0 | E22: ='TOTAL STOCK'!E22-'CLOSING STOCK'!E22 -> 0 | F22: ='TOTAL STOCK'!F22-'CLOSING STOCK'!F22 -> 0 | G22: ='TOTAL STOCK'!G22-'CLOSING STOCK'!G22 -> 0 | H22: ='TOTAL STOCK'!H22-'CLOSING STOCK'!H22 -> 0 | I22: ='TOTAL STOCK'!I22-'CLOSING STOCK'!I22 -> 0 | J22: ='TOTAL STOCK'!J22-'CLOSING STOCK'!J22 -> 0 | ... L22: ='TOTAL STOCK'!L22-'CLOSING STOCK'!L22 -> 0 | M22: =(C22*12*N22)+(D22*N22)+(E22*24*O22)+(F22*O22)+(G22*48*P22)+(H22*P22)+(I22*96*Q22)+(J22*Q22)+(K22*25*R22)+(L22*R22) -> 0 | N22: 480 | O22: 240 | P22: 120 | Q22: 75
A23: 20 | B23: ROYAL STAGE | C23: ='TOTAL STOCK'!C23-'CLOSING STOCK'!C23 -> 0 | D23: ='TOTAL STOCK'!D23-'CLOSING STOCK'!D23 -> 1 | E23: ='TOTAL STOCK'!E23-'CLOSING STOCK'!E23 -> 0 | F23: ='TOTAL STOCK'!F23-'CLOSING STOCK'!F23 -> 4 | G23: ='TOTAL STOCK'!G23-'CLOSING STOCK'!G23 -> 1 | H23: ='TOTAL STOCK'!H23-'CLOSING STOCK'!H23 -> -34 | I23: ='TOTAL STOCK'!I23-'CLOSING STOCK'!I23 -> 0 | J23: ='TOTAL STOCK'!J23-'CLOSING STOCK'!J23 -> -2 | ... L23: ='TOTAL STOCK'!L23-'CLOSING STOCK'!L23 -> 0 | M23: =(C23*12*N23)+(D23*N23)+(E23*24*O23)+(F23*O23)+(G23*48*P23)+(H23*P23)+(I23*96*Q23)+(J23*Q23)+(K23*25*R23)+(L23*R23) -> 8740 | N23: 1400 | O23: 700 | P23: 350 | Q23: 180 | R23: 120
A24: 21 | B24: HAYWARDS(W) | C24: ='TOTAL STOCK'!C24-'CLOSING STOCK'!C24 -> 0 | D24: ='TOTAL STOCK'!D24-'CLOSING STOCK'!D24 -> 0 | E24: ='TOTAL STOCK'!E24-'CLOSING STOCK'!E24 -> 0 | F24: ='TOTAL STOCK'!F24-'CLOSING STOCK'!F24 -> 0 | G24: ='TOTAL STOCK'!G24-'CLOSING STOCK'!G24 -> 1 | H24: ='TOTAL STOCK'!H24-'CLOSING STOCK'!H24 -> -26 | I24: ='TOTAL STOCK'!I24-'CLOSING STOCK'!I24 -> 1 | J24: ='TOTAL STOCK'!J24-'CLOSING STOCK'!J24 -> -20 | ... L24: ='TOTAL STOCK'!L24-'CLOSING STOCK'!L24 -> 0 | M24: =(C24*12*N24)+(D24*N24)+(E24*24*O24)+(F24*O24)+(G24*48*P24)+(H24*P24)+(I24*96*Q24)+(J24*Q24)+(K24*25*R24)+(L24*R24) -> 7200 | N24: 400 | O24: 200 | P24: 120 | Q24: 60
A25: 22 | B25: CNB RED | C25: ='TOTAL STOCK'!C25-'CLOSING STOCK'!C25 -> 0 | D25: ='TOTAL STOCK'!D25-'CLOSING STOCK'!D25 -> 0 | E25: ='TOTAL STOCK'!E25-'CLOSING STOCK'!E25 -> 0 | F25: ='TOTAL STOCK'!F25-'CLOSING STOCK'!F25 -> 0 | G25: ='TOTAL STOCK'!G25-'CLOSING STOCK'!G25 -> 0 | H25: ='TOTAL STOCK'!H25-'CLOSING STOCK'!H25 -> 1 | I25: ='TOTAL STOCK'!I25-'CLOSING STOCK'!I25 -> 0 | J25: ='TOTAL STOCK'!J25-'CLOSING STOCK'!J25 -> 0 | ... L25: ='TOTAL STOCK'!L25-'CLOSING STOCK'!L25 -> 0 | M25: =(C25*12*N25)+(D25*N25)+(E25*24*O25)+(F25*O25)+(G25*48*P25)+(H25*P25)+(I25*96*Q25)+(J25*Q25)+(K25*25*R25)+(L25*R25) -> 220 | N25: 880 | O25: 440 | P25: 220 | Q25: 120
A26: 23 | B26: 8.PM (W) | C26: ='TOTAL STOCK'!C26-'CLOSING STOCK'!C26 -> 0 | D26: ='TOTAL STOCK'!D26-'CLOSING STOCK'!D26 -> 0 | E26: ='TOTAL STOCK'!E26-'CLOSING STOCK'!E26 -> 0 | F26: ='TOTAL STOCK'!F26-'CLOSING STOCK'!F26 -> 0 | G26: ='TOTAL STOCK'!G26-'CLOSING STOCK'!G26 -> 1 | H26: ='TOTAL STOCK'!H26-'CLOSING STOCK'!H26 -> -17 | I26: ='TOTAL STOCK'!I26-'CLOSING STOCK'!I26 -> 1 | J26: ='TOTAL STOCK'!J26-'CLOSING STOCK'!J26 -> -73 | ... L26: ='TOTAL STOCK'!L26-'CLOSING STOCK'!L26 -> 0 | M26: =(C26*12*N26)+(D26*N26)+(E26*24*O26)+(F26*O26)+(G26*48*P26)+(H26*P26)+(I26*96*Q26)+(J26*Q26)+(K26*25*R26)+(L26*R26) -> 6760 | N26: 600 | O26: 300 | P26: 155 | Q26: 85
A27: 24 | B27: IMPERIAL BLUE(W) | C27: ='TOTAL STOCK'!C27-'CLOSING STOCK'!C27 -> 0 | D27: ='TOTAL STOCK'!D27-'CLOSING STOCK'!D27 -> 2 | E27: ='TOTAL STOCK'!E27-'CLOSING STOCK'!E27 -> 0 | F27: ='TOTAL STOCK'!F27-'CLOSING STOCK'!F27 -> 9 | G27: ='TOTAL STOCK'!G27-'CLOSING STOCK'!G27 -> 2 | H27: ='TOTAL STOCK'!H27-'CLOSING STOCK'!H27 -> 3 | I27: ='TOTAL STOCK'!I27-'CLOSING STOCK'!I27 -> 1 | J27: ='TOTAL STOCK'!J27-'CLOSING STOCK'!J27 -> -34 | ... L27: ='TOTAL STOCK'!L27-'CLOSING STOCK'!L27 -> 0 | M27: =(C27*12*N27)+(D27*N27)+(E27*24*O27)+(F27*O27)+(G27*48*P27)+(H27*P27)+(I27*96*Q27)+(J27*Q27)+(K27*25*R27)+(L27*R27) -> 43675 | N27: 1100 | O27: 550 | P27: 275 | Q27: 150
A28: 25 | B28: BLACK DOG(8)YRS | C28: ='TOTAL STOCK'!C28-'CLOSING STOCK'!C28 -> 0 | D28: ='TOTAL STOCK'!D28-'CLOSING STOCK'!D28 -> 0 | E28: ='TOTAL STOCK'!E28-'CLOSING STOCK'!E28 -> 0 | F28: ='TOTAL STOCK'!F28-'CLOSING STOCK'!F28 -> 0 | G28: ='TOTAL STOCK'!G28-'CLOSING STOCK'!G28 -> 0 | H28: ='TOTAL STOCK'!H28-'CLOSING STOCK'!H28 -> 0 | I28: ='TOTAL STOCK'!I28-'CLOSING STOCK'!I28 -> 0 | J28: ='TOTAL STOCK'!J28-'CLOSING STOCK'!J28 -> 0 | ... L28: ='TOTAL STOCK'!L28-'CLOSING STOCK'!L28 -> 0 | M28: =(C28*12*N28)+(D28*N28)+(E28*24*O28)+(F28*O28)+(G28*48*P28)+(H28*P28)+(I28*96*Q28)+(J28*Q28)+(K28*25*R28)+(L28*R28) -> 0 | N28: 2720 | O28: 1360 | P28: 680 | Q28: 340 | R28: 250
A29: 26 | B29: 100 PIPERS | C29: ='TOTAL STOCK'!C29-'CLOSING STOCK'!C29 -> 0 | D29: ='TOTAL STOCK'!D29-'CLOSING STOCK'!D29 -> 0 | E29: ='TOTAL STOCK'!E29-'CLOSING STOCK'!E29 -> 0 | F29: ='TOTAL STOCK'!F29-'CLOSING STOCK'!F29 -> 0 | G29: ='TOTAL STOCK'!G29-'CLOSING STOCK'!G29 -> 0 | H29: ='TOTAL STOCK'!H29-'CLOSING STOCK'!H29 -> 1 | I29: ='TOTAL STOCK'!I29-'CLOSING STOCK'!I29 -> 0 | J29: ='TOTAL STOCK'!J29-'CLOSING STOCK'!J29 -> 0 | ... L29: ='TOTAL STOCK'!L29-'CLOSING STOCK'!L29 -> 6 | M29: =(C29*12*N29)+(D29*N29)+(E29*24*O29)+(F29*O29)+(G29*48*P29)+(H29*P29)+(I29*96*Q29)+(J29*Q29)+(K29*25*R29)+(L29*R29) -> 2180 | N29: 2720 | O29: 1360 | P29: 680 | Q29: 340 | R29: 250
A30: 27 | B30: 8.PM (W) BLUE | C30: ='TOTAL STOCK'!C30-'CLOSING STOCK'!C30 -> 0 | D30: ='TOTAL STOCK'!D30-'CLOSING STOCK'!D30 -> 0 | E30: ='TOTAL STOCK'!E30-'CLOSING STOCK'!E30 -> 0 | F30: ='TOTAL STOCK'!F30-'CLOSING STOCK'!F30 -> 0 | G30: ='TOTAL STOCK'!G30-'CLOSING STOCK'!G30 -> 0 | H30: ='TOTAL STOCK'!H30-'CLOSING STOCK'!H30 -> 0 | I30: ='TOTAL STOCK'!I30-'CLOSING STOCK'!I30 -> 0 | J30: ='TOTAL STOCK'!J30-'CLOSING STOCK'!J30 -> 0 | ... L30: ='TOTAL STOCK'!L30-'CLOSING STOCK'!L30 -> 0 | M30: =(C30*12*N30)+(D30*N30)+(E30*24*O30)+(F30*O30)+(G30*48*P30)+(H30*P30)+(I30*96*Q30)+(J30*Q30)+(K30*25*R30)+(L30*R30) -> 0 | N30: 720 | O30: 360 | P30: 180 | Q30: 90
A31: 28 | B31: TEACHERS HIGH | C31: ='TOTAL STOCK'!C31-'CLOSING STOCK'!C31 -> 0 | D31: ='TOTAL STOCK'!D31-'CLOSING STOCK'!D31 -> 0 | E31: ='TOTAL STOCK'!E31-'CLOSING STOCK'!E31 -> 0 | F31: ='TOTAL STOCK'!F31-'CLOSING STOCK'!F31 -> 0 | G31: ='TOTAL STOCK'!G31-'CLOSING STOCK'!G31 -> 0 | H31: ='TOTAL STOCK'!H31-'CLOSING STOCK'!H31 -> 0 | I31: ='TOTAL STOCK'!I31-'CLOSING STOCK'!I31 -> 0 | J31: ='TOTAL STOCK'!J31-'CLOSING STOCK'!J31 -> 0 | ... L31: ='TOTAL STOCK'!L31-'CLOSING STOCK'!L31 -> 0 | M31: =(C31*12*N31)+(D31*N31)+(E31*24*O31)+(F31*O31)+(G31*48*P31)+(H31*P31)+(I31*96*Q31)+(J31*Q31)+(K31*25*R31)+(L31*R31) -> 0 | N31: 2600 | O31: 1300 | P31: 750 | R31: 250
A32: 29 | B32: ANTIQUITY BLUE(W) | C32: ='TOTAL STOCK'!C32-'CLOSING STOCK'!C32 -> 0 | D32: ='TOTAL STOCK'!D32-'CLOSING STOCK'!D32 -> 0 | E32: ='TOTAL STOCK'!E32-'CLOSING STOCK'!E32 -> 0 | F32: ='TOTAL STOCK'!F32-'CLOSING STOCK'!F32 -> 0 | G32: ='TOTAL STOCK'!G32-'CLOSING STOCK'!G32 -> 0 | H32: ='TOTAL STOCK'!H32-'CLOSING STOCK'!H32 -> 0 | I32: ='TOTAL STOCK'!I32-'CLOSING STOCK'!I32 -> 0 | J32: ='TOTAL STOCK'!J32-'CLOSING STOCK'!J32 -> 0 | ... L32: ='TOTAL STOCK'!L32-'CLOSING STOCK'!L32 -> 0 | M32: =(C32*12*N32)+(D32*N32)+(E32*24*O32)+(F32*O32)+(G32*48*P32)+(H32*P32)+(I32*96*Q32)+(J32*Q32)+(K32*25*R32)+(L32*R32) -> 0 | N32: 1920 | O32: 960 | P32: 480 | Q32: 240 | R32: 170
A33: 30 | B33: 0 | C33: ='TOTAL STOCK'!C33-'CLOSING STOCK'!C33 -> 0 | D33: ='TOTAL STOCK'!D33-'CLOSING STOCK'!D33 -> 0 | E33: ='TOTAL STOCK'!E33-'CLOSING STOCK'!E33 -> 0 | F33: ='TOTAL STOCK'!F33-'CLOSING STOCK'!F33 -> 0 | G33: ='TOTAL STOCK'!G33-'CLOSING STOCK'!G33 -> 0 | H33: ='TOTAL STOCK'!H33-'CLOSING STOCK'!H33 -> 0 | I33: ='TOTAL STOCK'!I33-'CLOSING STOCK'!I33 -> 0 | J33: ='TOTAL STOCK'!J33-'CLOSING STOCK'!J33 -> 0 | ... L33: ='TOTAL STOCK'!L33-'CLOSING STOCK'!L33 -> 0 | M33: =(C33*12*N33)+(D33*N33)+(E33*24*O33)+(F33*O33)+(G33*48*P33)+(H33*P33)+(I33*96*Q33)+(J33*Q33)+(K33*25*R33)+(L33*R33) -> 0
A34: 31 | B34: VAT 69 | C34: ='TOTAL STOCK'!C34-'CLOSING STOCK'!C34 -> 0 | D34: ='TOTAL STOCK'!D34-'CLOSING STOCK'!D34 -> 0 | E34: ='TOTAL STOCK'!E34-'CLOSING STOCK'!E34 -> 0 | F34: ='TOTAL STOCK'!F34-'CLOSING STOCK'!F34 -> 0 | G34: ='TOTAL STOCK'!G34-'CLOSING STOCK'!G34 -> 0 | H34: ='TOTAL STOCK'!H34-'CLOSING STOCK'!H34 -> 0 | I34: ='TOTAL STOCK'!I34-'CLOSING STOCK'!I34 -> 0 | J34: ='TOTAL STOCK'!J34-'CLOSING STOCK'!J34 -> 0 | ... L34: ='TOTAL STOCK'!L34-'CLOSING STOCK'!L34 -> 0 | M34: =(C34*12*N34)+(D34*N34)+(E34*24*O34)+(F34*O34)+(G34*48*P34)+(H34*P34)+(I34*96*Q34)+(J34*Q34)+(K34*25*R34)+(L34*R34) -> 0 | N34: 2700 | O34: 1350 | P34: 670 | Q34: 340 | R34: 240
A35: 32 | B35: HERCULES RUM | C35: ='TOTAL STOCK'!C35-'CLOSING STOCK'!C35 -> 0 | D35: ='TOTAL STOCK'!D35-'CLOSING STOCK'!D35 -> 0 | E35: ='TOTAL STOCK'!E35-'CLOSING STOCK'!E35 -> 0 | F35: ='TOTAL STOCK'!F35-'CLOSING STOCK'!F35 -> 2 | G35: ='TOTAL STOCK'!G35-'CLOSING STOCK'!G35 -> 1 | H35: ='TOTAL STOCK'!H35-'CLOSING STOCK'!H35 -> 0 | I35: ='TOTAL STOCK'!I35-'CLOSING STOCK'!I35 -> 0 | J35: ='TOTAL STOCK'!J35-'CLOSING STOCK'!J35 -> 0 | ... L35: ='TOTAL STOCK'!L35-'CLOSING STOCK'!L35 -> 0 | M35: =(C35*12*N35)+(D35*N35)+(E35*24*O35)+(F35*O35)+(G35*48*P35)+(H35*P35)+(I35*96*Q35)+(J35*Q35)+(K35*25*R35)+(L35*R35) -> 14560 | N35: 1120 | O35: 560 | P35: 280 | Q35: 140
A36: 33 | B36: M C RUM | C36: ='TOTAL STOCK'!C36-'CLOSING STOCK'!C36 -> 0 | D36: ='TOTAL STOCK'!D36-'CLOSING STOCK'!D36 -> 0 | E36: ='TOTAL STOCK'!E36-'CLOSING STOCK'!E36 -> 0 | F36: ='TOTAL STOCK'!F36-'CLOSING STOCK'!F36 -> 0 | G36: ='TOTAL STOCK'!G36-'CLOSING STOCK'!G36 -> 0 | H36: ='TOTAL STOCK'!H36-'CLOSING STOCK'!H36 -> 0 | I36: ='TOTAL STOCK'!I36-'CLOSING STOCK'!I36 -> 0 | J36: ='TOTAL STOCK'!J36-'CLOSING STOCK'!J36 -> 0 | ... L36: ='TOTAL STOCK'!L36-'CLOSING STOCK'!L36 -> 0 | M36: =(C36*12*N36)+(D36*N36)+(E36*24*O36)+(F36*O36)+(G36*48*P36)+(H36*P36)+(I36*96*Q36)+(J36*Q36)+(K36*25*R36)+(L36*R36) -> 0 | N36: 880 | O36: 440 | P36: 170 | Q36: 90
A37: 34 | B37: OLD MONK RUM | C37: ='TOTAL STOCK'!C37-'CLOSING STOCK'!C37 -> 0 | D37: ='TOTAL STOCK'!D37-'CLOSING STOCK'!D37 -> 1 | E37: ='TOTAL STOCK'!E37-'CLOSING STOCK'!E37 -> 0 | F37: ='TOTAL STOCK'!F37-'CLOSING STOCK'!F37 -> 1 | G37: ='TOTAL STOCK'!G37-'CLOSING STOCK'!G37 -> 3 | H37: ='TOTAL STOCK'!H37-'CLOSING STOCK'!H37 -> 29 | I37: ='TOTAL STOCK'!I37-'CLOSING STOCK'!I37 -> 1 | J37: ='TOTAL STOCK'!J37-'CLOSING STOCK'!J37 -> 8 | ... L37: ='TOTAL STOCK'!L37-'CLOSING STOCK'!L37 -> 0 | M37: =(C37*12*N37)+(D37*N37)+(E37*24*O37)+(F37*O37)+(G37*48*P37)+(H37*P37)+(I37*96*Q37)+(J37*Q37)+(K37*25*R37)+(L37*R37) -> 40955 | N37: 880 | O37: 440 | P37: 175 | Q37: 90
A38: 35 | B38: MC RUM CLASSIC | C38: ='TOTAL STOCK'!C38-'CLOSING STOCK'!C38 -> 0 | D38: ='TOTAL STOCK'!D38-'CLOSING STOCK'!D38 -> 0 | E38: ='TOTAL STOCK'!E38-'CLOSING STOCK'!E38 -> 0 | F38: ='TOTAL STOCK'!F38-'CLOSING STOCK'!F38 -> 0 | G38: ='TOTAL STOCK'!G38-'CLOSING STOCK'!G38 -> 1 | H38: ='TOTAL STOCK'!H38-'CLOSING STOCK'!H38 -> 8 | I38: ='TOTAL STOCK'!I38-'CLOSING STOCK'!I38 -> 1 | J38: ='TOTAL STOCK'!J38-'CLOSING STOCK'!J38 -> -42 | ... L38: ='TOTAL STOCK'!L38-'CLOSING STOCK'!L38 -> 0 | M38: =(C38*12*N38)+(D38*N38)+(E38*24*O38)+(F38*O38)+(G38*48*P38)+(H38*P38)+(I38*96*Q38)+(J38*Q38)+(K38*25*R38)+(L38*R38) -> 13270 | N38: 600 | O38: 300 | P38: 155 | Q38: 85
A39: 36 | B39: 0 | C39: ='TOTAL STOCK'!C39-'CLOSING STOCK'!C39 -> 0 | D39: ='TOTAL STOCK'!D39-'CLOSING STOCK'!D39 -> 0 | E39: ='TOTAL STOCK'!E39-'CLOSING STOCK'!E39 -> 0 | F39: ='TOTAL STOCK'!F39-'CLOSING STOCK'!F39 -> 0 | G39: ='TOTAL STOCK'!G39-'CLOSING STOCK'!G39 -> 0 | H39: ='TOTAL STOCK'!H39-'CLOSING STOCK'!H39 -> 0 | I39: ='TOTAL STOCK'!I39-'CLOSING STOCK'!I39 -> 0 | J39: ='TOTAL STOCK'!J39-'CLOSING STOCK'!J39 -> 0 | ... L39: ='TOTAL STOCK'!L39-'CLOSING STOCK'!L39 -> 0 | M39: =(C39*12*N39)+(D39*N39)+(E39*24*O39)+(F39*O39)+(G39*48*P39)+(H39*P39)+(I39*96*Q39)+(J39*Q39)+(K39*25*R39)+(L39*R39) -> 0
A40: 37 | B40: BAGPIPER RUM | C40: ='TOTAL STOCK'!C40-'CLOSING STOCK'!C40 -> 0 | D40: ='TOTAL STOCK'!D40-'CLOSING STOCK'!D40 -> 0 | E40: ='TOTAL STOCK'!E40-'CLOSING STOCK'!E40 -> 0 | F40: ='TOTAL STOCK'!F40-'CLOSING STOCK'!F40 -> 0 | G40: ='TOTAL STOCK'!G40-'CLOSING STOCK'!G40 -> 1 | H40: ='TOTAL STOCK'!H40-'CLOSING STOCK'!H40 -> 10 | I40: ='TOTAL STOCK'!I40-'CLOSING STOCK'!I40 -> 0 | J40: ='TOTAL STOCK'!J40-'CLOSING STOCK'!J40 -> 26 | ... L40: ='TOTAL STOCK'!L40-'CLOSING STOCK'!L40 -> 0 | M40: =(C40*12*N40)+(D40*N40)+(E40*24*O40)+(F40*O40)+(G40*48*P40)+(H40*P40)+(I40*96*Q40)+(J40*Q40)+(K40*25*R40)+(L40*R40) -> 9360 | N40: 400 | O40: 200 | P40: 130 | Q40: 70
A41: 38 | B41: BACARDI ORN+APP+LIM | C41: ='TOTAL STOCK'!C41-'CLOSING STOCK'!C41 -> 0 | D41: ='TOTAL STOCK'!D41-'CLOSING STOCK'!D41 -> 0 | E41: ='TOTAL STOCK'!E41-'CLOSING STOCK'!E41 -> 0 | F41: ='TOTAL STOCK'!F41-'CLOSING STOCK'!F41 -> 0 | G41: ='TOTAL STOCK'!G41-'CLOSING STOCK'!G41 -> 0 | H41: ='TOTAL STOCK'!H41-'CLOSING STOCK'!H41 -> 5 | I41: ='TOTAL STOCK'!I41-'CLOSING STOCK'!I41 -> 0 | J41: ='TOTAL STOCK'!J41-'CLOSING STOCK'!J41 -> 0 | ... L41: ='TOTAL STOCK'!L41-'CLOSING STOCK'!L41 -> 3 | M41: =(C41*12*N41)+(D41*N41)+(E41*24*O41)+(F41*O41)+(G41*48*P41)+(H41*P41)+(I41*96*Q41)+(J41*Q41)+(K41*25*R41)+(L41*R41) -> 2880 | N41: 1920 | O41: 960 | P41: 480 | Q41: 240 | R41: 160
A42: 39 | B42: LEGACY RUM | C42: ='TOTAL STOCK'!C42-'CLOSING STOCK'!C42 -> 0 | D42: ='TOTAL STOCK'!D42-'CLOSING STOCK'!D42 -> 0 | E42: ='TOTAL STOCK'!E42-'CLOSING STOCK'!E42 -> 0 | F42: ='TOTAL STOCK'!F42-'CLOSING STOCK'!F42 -> 0 | G42: ='TOTAL STOCK'!G42-'CLOSING STOCK'!G42 -> 0 | H42: ='TOTAL STOCK'!H42-'CLOSING STOCK'!H42 -> 1 | I42: ='TOTAL STOCK'!I42-'CLOSING STOCK'!I42 -> 0 | J42: ='TOTAL STOCK'!J42-'CLOSING STOCK'!J42 -> 0 | ... L42: ='TOTAL STOCK'!L42-'CLOSING STOCK'!L42 -> 0 | M42: =(C42*12*N42)+(D42*N42)+(E42*24*O42)+(F42*O42)+(G42*48*P42)+(H42*P42)+(I42*96*Q42)+(J42*Q42)+(K42*25*R42)+(L42*R42) -> 95 | N42: 300 | O42: 150 | P42: 95 | Q42: 50
A43: 40 | B43: B'LORE RUM | C43: ='TOTAL STOCK'!C43-'CLOSING STOCK'!C43 -> 0 | D43: ='TOTAL STOCK'!D43-'CLOSING STOCK'!D43 -> 0 | E43: ='TOTAL STOCK'!E43-'CLOSING STOCK'!E43 -> 0 | F43: ='TOTAL STOCK'!F43-'CLOSING STOCK'!F43 -> 0 | G43: ='TOTAL STOCK'!G43-'CLOSING STOCK'!G43 -> 0 | H43: ='TOTAL STOCK'!H43-'CLOSING STOCK'!H43 -> 4 | I43: ='TOTAL STOCK'!I43-'CLOSING STOCK'!I43 -> 1 | J43: ='TOTAL STOCK'!J43-'CLOSING STOCK'!J43 -> -23 | ... L43: ='TOTAL STOCK'!L43-'CLOSING STOCK'!L43 -> 0 | M43: =(C43*12*N43)+(D43*N43)+(E43*24*O43)+(F43*O43)+(G43*48*P43)+(H43*P43)+(I43*96*Q43)+(J43*Q43)+(K43*25*R43)+(L43*R43) -> 4050 | N43: 300 | O43: 150 | P43: 100 | Q43: 50
A44: 41 | B44: AMRUT RUM | C44: ='TOTAL STOCK'!C44-'CLOSING STOCK'!C44 -> 0 | D44: ='TOTAL STOCK'!D44-'CLOSING STOCK'!D44 -> 0 | E44: ='TOTAL STOCK'!E44-'CLOSING STOCK'!E44 -> 0 | F44: ='TOTAL STOCK'!F44-'CLOSING STOCK'!F44 -> 0 | G44: ='TOTAL STOCK'!G44-'CLOSING STOCK'!G44 -> 2 | H44: ='TOTAL STOCK'!H44-'CLOSING STOCK'!H44 -> -10 | I44: ='TOTAL STOCK'!I44-'CLOSING STOCK'!I44 -> 1 | J44: ='TOTAL STOCK'!J44-'CLOSING STOCK'!J44 -> -13 | ... L44: ='TOTAL STOCK'!L44-'CLOSING STOCK'!L44 -> 0 | M44: =(C44*12*N44)+(D44*N44)+(E44*24*O44)+(F44*O44)+(G44*48*P44)+(H44*P44)+(I44*96*Q44)+(J44*Q44)+(K44*25*R44)+(L44*R44) -> 14025 | N44: 360 | O44: 180 | P44: 110 | Q44: 55
A45: 42 | B45: BLACK & WHITE (8)YRS | C45: ='TOTAL STOCK'!C45-'CLOSING STOCK'!C45 -> 0 | D45: ='TOTAL STOCK'!D45-'CLOSING STOCK'!D45 -> 0 | E45: ='TOTAL STOCK'!E45-'CLOSING STOCK'!E45 -> 0 | F45: ='TOTAL STOCK'!F45-'CLOSING STOCK'!F45 -> 0 | G45: ='TOTAL STOCK'!G45-'CLOSING STOCK'!G45 -> 0 | H45: ='TOTAL STOCK'!H45-'CLOSING STOCK'!H45 -> 9 | I45: ='TOTAL STOCK'!I45-'CLOSING STOCK'!I45 -> 0 | J45: ='TOTAL STOCK'!J45-'CLOSING STOCK'!J45 -> 0 | ... L45: ='TOTAL STOCK'!L45-'CLOSING STOCK'!L45 -> 5 | M45: =(C45*12*N45)+(D45*N45)+(E45*24*O45)+(F45*O45)+(G45*48*P45)+(H45*P45)+(I45*96*Q45)+(J45*Q45)+(K45*25*R45)+(L45*R45) -> 7370 | N45: 2700 | O45: 1350 | P45: 680 | R45: 250
A46: 43 | B46: COURIOR NEPOLIN BRANDY | C46: ='TOTAL STOCK'!C46-'CLOSING STOCK'!C46 -> 0 | D46: ='TOTAL STOCK'!D46-'CLOSING STOCK'!D46 -> 3 | E46: ='TOTAL STOCK'!E46-'CLOSING STOCK'!E46 -> 0 | F46: ='TOTAL STOCK'!F46-'CLOSING STOCK'!F46 -> 0 | G46: ='TOTAL STOCK'!G46-'CLOSING STOCK'!G46 -> 0 | H46: ='TOTAL STOCK'!H46-'CLOSING STOCK'!H46 -> 1 | I46: ='TOTAL STOCK'!I46-'CLOSING STOCK'!I46 -> 0 | J46: ='TOTAL STOCK'!J46-'CLOSING STOCK'!J46 -> 0 | ... L46: ='TOTAL STOCK'!L46-'CLOSING STOCK'!L46 -> 0 | M46: =(C46*12*N46)+(D46*N46)+(E46*24*O46)+(F46*O46)+(G46*48*P46)+(H46*P46)+(I46*96*Q46)+(J46*Q46)+(K46*25*R46)+(L46*R46) -> 5200 | N46: 1600 | O46: 800 | P46: 400 | Q46: 250 | R46: 140
A47: 44 | B47: FIREBALL | C47: ='TOTAL STOCK'!C47-'CLOSING STOCK'!C47 -> 0 | D47: ='TOTAL STOCK'!D47-'CLOSING STOCK'!D47 -> 0 | E47: ='TOTAL STOCK'!E47-'CLOSING STOCK'!E47 -> 0 | F47: ='TOTAL STOCK'!F47-'CLOSING STOCK'!F47 -> 0 | G47: ='TOTAL STOCK'!G47-'CLOSING STOCK'!G47 -> 0 | H47: ='TOTAL STOCK'!H47-'CLOSING STOCK'!H47 -> 2 | I47: ='TOTAL STOCK'!I47-'CLOSING STOCK'!I47 -> 0 | J47: ='TOTAL STOCK'!J47-'CLOSING STOCK'!J47 -> 13 | ... L47: ='TOTAL STOCK'!L47-'CLOSING STOCK'!L47 -> 0 | M47: =(C47*12*N47)+(D47*N47)+(E47*24*O47)+(F47*O47)+(G47*48*P47)+(H47*P47)+(I47*96*Q47)+(J47*Q47)+(K47*25*R47)+(L47*R47) -> 2000 | N47: 880 | O47: 440 | P47: 220 | Q47: 120 | R47: 60
A48: 45 | B48: HONEY CUP BRANDY | C48: ='TOTAL STOCK'!C48-'CLOSING STOCK'!C48 -> 0 | D48: ='TOTAL STOCK'!D48-'CLOSING STOCK'!D48 -> 0 | E48: ='TOTAL STOCK'!E48-'CLOSING STOCK'!E48 -> 0 | F48: ='TOTAL STOCK'!F48-'CLOSING STOCK'!F48 -> 0 | G48: ='TOTAL STOCK'!G48-'CLOSING STOCK'!G48 -> 0 | H48: ='TOTAL STOCK'!H48-'CLOSING STOCK'!H48 -> 0 | I48: ='TOTAL STOCK'!I48-'CLOSING STOCK'!I48 -> 0 | J48: ='TOTAL STOCK'!J48-'CLOSING STOCK'!J48 -> 4 | ... L48: ='TOTAL STOCK'!L48-'CLOSING STOCK'!L48 -> 0 | M48: =(C48*12*N48)+(D48*N48)+(E48*24*O48)+(F48*O48)+(G48*48*P48)+(H48*P48)+(I48*96*Q48)+(J48*Q48)+(K48*25*R48)+(L48*R48) -> 280 | N48: 520 | O48: 260 | P48: 130 | Q48: 70
A49: 46 | B49: ROULETTE BRANDY | C49: ='TOTAL STOCK'!C49-'CLOSING STOCK'!C49 -> 0 | D49: ='TOTAL STOCK'!D49-'CLOSING STOCK'!D49 -> 0 | E49: ='TOTAL STOCK'!E49-'CLOSING STOCK'!E49 -> 0 | F49: ='TOTAL STOCK'!F49-'CLOSING STOCK'!F49 -> 0 | G49: ='TOTAL STOCK'!G49-'CLOSING STOCK'!G49 -> 0 | H49: ='TOTAL STOCK'!H49-'CLOSING STOCK'!H49 -> 0 | I49: ='TOTAL STOCK'!I49-'CLOSING STOCK'!I49 -> 0 | J49: ='TOTAL STOCK'!J49-'CLOSING STOCK'!J49 -> 0 | ... L49: ='TOTAL STOCK'!L49-'CLOSING STOCK'!L49 -> 0 | M49: =(C49*12*N49)+(D49*N49)+(E49*24*O49)+(F49*O49)+(G49*48*P49)+(H49*P49)+(I49*96*Q49)+(J49*Q49)+(K49*25*R49)+(L49*R49) -> 0 | N49: 2000 | O49: 1000 | P49: 500 | Q49: 270
A50: 47 | B50: 0 | C50: ='TOTAL STOCK'!C50-'CLOSING STOCK'!C50 -> 0 | D50: ='TOTAL STOCK'!D50-'CLOSING STOCK'!D50 -> 0 | E50: ='TOTAL STOCK'!E50-'CLOSING STOCK'!E50 -> 0 | F50: ='TOTAL STOCK'!F50-'CLOSING STOCK'!F50 -> 0 | G50: ='TOTAL STOCK'!G50-'CLOSING STOCK'!G50 -> 0 | H50: ='TOTAL STOCK'!H50-'CLOSING STOCK'!H50 -> 0 | I50: ='TOTAL STOCK'!I50-'CLOSING STOCK'!I50 -> 0 | J50: ='TOTAL STOCK'!J50-'CLOSING STOCK'!J50 -> 0 | ... L50: ='TOTAL STOCK'!L50-'CLOSING STOCK'!L50 -> 0 | M50: =(C50*12*N50)+(D50*N50)+(E50*24*O50)+(F50*O50)+(G50*48*P50)+(H50*P50)+(I50*96*Q50)+(J50*Q50)+(K50*25*R50)+(L50*R50) -> 0
A51: Mahavishnu PAGE 2 | C51: SALES PAGE 2 | N51: RATES PAGE 2
C52: 750 ML | E52: 375 ML | G52: 180 ML | I52: 90 ML | K52: 60 ML | N52: 750 ML | O52: 375 ML | P52: 180 ML | Q52: 90 ML | R52: 60 ML
A53: SL. | B53: PRODUCT NAME | C53: CASES*12 | D53: BTLS | E53: CASES*24 | F53: BTLS | G53: CASES*48 | H53: BTLS | I53: CASES*96 | J53: BTLS | K53: BOX*25 | L53: BTLS | N53: RATE | O53: RATE | P53: RATE | Q53: RATE | R53: RATE
A54: 1 | B54: CARNIVAL GIN | C54: ='TOTAL STOCK'!C54-'CLOSING STOCK'!C54 -> 0 | D54: ='TOTAL STOCK'!D54-'CLOSING STOCK'!D54 -> 0 | E54: ='TOTAL STOCK'!E54-'CLOSING STOCK'!E54 -> 0 | F54: ='TOTAL STOCK'!F54-'CLOSING STOCK'!F54 -> 0 | G54: ='TOTAL STOCK'!G54-'CLOSING STOCK'!G54 -> 1 | H54: ='TOTAL STOCK'!H54-'CLOSING STOCK'!H54 -> -30 | I54: ='TOTAL STOCK'!I54-'CLOSING STOCK'!I54 -> 0 | J54: ='TOTAL STOCK'!J54-'CLOSING STOCK'!J54 -> 77 | ... L54: ='TOTAL STOCK'!L54-'CLOSING STOCK'!L54 -> 0 | M54: =(C54*12*N54)+(D54*N54)+(E54*24*O54)+(F54*O54)+(G54*48*P54)+(H54*P54)+(I54*96*Q54)+(J54*Q54)+(K54*25*R54)+(L54*R54) -> 6600 | N54: 340 | O54: 170 | P54: 110 | Q54: 60
A55: 2 | B55: SMIRNOFF VODKA | C55: ='TOTAL STOCK'!C55-'CLOSING STOCK'!C55 -> 0 | D55: ='TOTAL STOCK'!D55-'CLOSING STOCK'!D55 -> 0 | E55: ='TOTAL STOCK'!E55-'CLOSING STOCK'!E55 -> 0 | F55: ='TOTAL STOCK'!F55-'CLOSING STOCK'!F55 -> 0 | G55: ='TOTAL STOCK'!G55-'CLOSING STOCK'!G55 -> 0 | H55: ='TOTAL STOCK'!H55-'CLOSING STOCK'!H55 -> 7 | I55: ='TOTAL STOCK'!I55-'CLOSING STOCK'!I55 -> 0 | J55: ='TOTAL STOCK'!J55-'CLOSING STOCK'!J55 -> 0 | ... L55: ='TOTAL STOCK'!L55-'CLOSING STOCK'!L55 -> 0 | M55: =(C55*12*N55)+(D55*N55)+(E55*24*O55)+(F55*O55)+(G55*48*P55)+(H55*P55)+(I55*96*Q55)+(J55*Q55)+(K55*25*R55)+(L55*R55) -> 3570 | N55: 2000 | O55: 1000 | P55: 510 | Q55: 260 | R55: 180
A56: 3 | B56: MUSCOVY LEMON | C56: ='TOTAL STOCK'!C56-'CLOSING STOCK'!C56 -> 0 | D56: ='TOTAL STOCK'!D56-'CLOSING STOCK'!D56 -> 0 | E56: ='TOTAL STOCK'!E56-'CLOSING STOCK'!E56 -> 0 | F56: ='TOTAL STOCK'!F56-'CLOSING STOCK'!F56 -> 0 | G56: ='TOTAL STOCK'!G56-'CLOSING STOCK'!G56 -> 0 | H56: ='TOTAL STOCK'!H56-'CLOSING STOCK'!H56 -> 0 | I56: ='TOTAL STOCK'!I56-'CLOSING STOCK'!I56 -> 0 | J56: ='TOTAL STOCK'!J56-'CLOSING STOCK'!J56 -> 0 | ... L56: ='TOTAL STOCK'!L56-'CLOSING STOCK'!L56 -> 0 | M56: =(C56*12*N56)+(D56*N56)+(E56*24*O56)+(F56*O56)+(G56*48*P56)+(H56*P56)+(I56*96*Q56)+(J56*Q56)+(K56*25*R56)+(L56*R56) -> 0 | N56: 920 | O56: 460 | P56: 230 | Q56: 130
A57: 4 | B57: MUSCOVY VODKA | C57: ='TOTAL STOCK'!C57-'CLOSING STOCK'!C57 -> 0 | D57: ='TOTAL STOCK'!D57-'CLOSING STOCK'!D57 -> 0 | E57: ='TOTAL STOCK'!E57-'CLOSING STOCK'!E57 -> 0 | F57: ='TOTAL STOCK'!F57-'CLOSING STOCK'!F57 -> 0 | G57: ='TOTAL STOCK'!G57-'CLOSING STOCK'!G57 -> 2 | H57: ='TOTAL STOCK'!H57-'CLOSING STOCK'!H57 -> 34 | I57: ='TOTAL STOCK'!I57-'CLOSING STOCK'!I57 -> 1 | J57: ='TOTAL STOCK'!J57-'CLOSING STOCK'!J57 -> -10 | ... L57: ='TOTAL STOCK'!L57-'CLOSING STOCK'!L57 -> 0 | M57: =(C57*12*N57)+(D57*N57)+(E57*24*O57)+(F57*O57)+(G57*48*P57)+(H57*P57)+(I57*96*Q57)+(J57*Q57)+(K57*25*R57)+(L57*R57) -> 37620 | N57: 960 | O57: 480 | P57: 210 | Q57: 120
A58: 5 | B58: ROMANOV VODKA | C58: ='TOTAL STOCK'!C58-'CLOSING STOCK'!C58 -> 0 | D58: ='TOTAL STOCK'!D58-'CLOSING STOCK'!D58 -> 0 | E58: ='TOTAL STOCK'!E58-'CLOSING STOCK'!E58 -> 0 | F58: ='TOTAL STOCK'!F58-'CLOSING STOCK'!F58 -> 0 | G58: ='TOTAL STOCK'!G58-'CLOSING STOCK'!G58 -> 0 | H58: ='TOTAL STOCK'!H58-'CLOSING STOCK'!H58 -> 15 | I58: ='TOTAL STOCK'!I58-'CLOSING STOCK'!I58 -> 0 | J58: ='TOTAL STOCK'!J58-'CLOSING STOCK'!J58 -> 8 | ... L58: ='TOTAL STOCK'!L58-'CLOSING STOCK'!L58 -> 0 | M58: =(C58*12*N58)+(D58*N58)+(E58*24*O58)+(F58*O58)+(G58*48*P58)+(H58*P58)+(I58*96*Q58)+(J58*Q58)+(K58*25*R58)+(L58*R58) -> 5170 | N58: 1100 | O58: 560 | P58: 270 | Q58: 140 | R58: 100
A59: 6 | B59: GONAS WINE | C59: ='TOTAL STOCK'!C59-'CLOSING STOCK'!C59 -> 0 | D59: ='TOTAL STOCK'!D59-'CLOSING STOCK'!D59 -> 0 | E59: ='TOTAL STOCK'!E59-'CLOSING STOCK'!E59 -> 0 | F59: ='TOTAL STOCK'!F59-'CLOSING STOCK'!F59 -> 0 | G59: ='TOTAL STOCK'!G59-'CLOSING STOCK'!G59 -> 0 | H59: ='TOTAL STOCK'!H59-'CLOSING STOCK'!H59 -> 15 | I59: ='TOTAL STOCK'!I59-'CLOSING STOCK'!I59 -> 0 | J59: ='TOTAL STOCK'!J59-'CLOSING STOCK'!J59 -> 0 | ... L59: ='TOTAL STOCK'!L59-'CLOSING STOCK'!L59 -> 0 | M59: =(C59*12*N59)+(D59*N59)+(E59*24*O59)+(F59*O59)+(G59*48*P59)+(H59*P59)+(I59*96*Q59)+(J59*Q59)+(K59*25*R59)+(L59*R59) -> 750 | N59: 180 | O59: 100 | P59: 50
A60: 7 | B60: MAGIC PORT WINE | C60: ='TOTAL STOCK'!C60-'CLOSING STOCK'!C60 -> 0 | D60: ='TOTAL STOCK'!D60-'CLOSING STOCK'!D60 -> 2 | E60: ='TOTAL STOCK'!E60-'CLOSING STOCK'!E60 -> 0 | F60: ='TOTAL STOCK'!F60-'CLOSING STOCK'!F60 -> 3 | G60: ='TOTAL STOCK'!G60-'CLOSING STOCK'!G60 -> 0 | H60: ='TOTAL STOCK'!H60-'CLOSING STOCK'!H60 -> 12 | I60: ='TOTAL STOCK'!I60-'CLOSING STOCK'!I60 -> 0 | J60: ='TOTAL STOCK'!J60-'CLOSING STOCK'!J60 -> 0 | ... L60: ='TOTAL STOCK'!L60-'CLOSING STOCK'!L60 -> 0 | M60: =(C60*12*N60)+(D60*N60)+(E60*24*O60)+(F60*O60)+(G60*48*P60)+(H60*P60)+(I60*96*Q60)+(J60*Q60)+(K60*25*R60)+(L60*R60) -> 1260 | N60: 180 | O60: 100 | P60: 50
A61: 8 | B61: SIDDUS WINE | C61: ='TOTAL STOCK'!C61-'CLOSING STOCK'!C61 -> 0 | D61: ='TOTAL STOCK'!D61-'CLOSING STOCK'!D61 -> 0 | E61: ='TOTAL STOCK'!E61-'CLOSING STOCK'!E61 -> 0 | F61: ='TOTAL STOCK'!F61-'CLOSING STOCK'!F61 -> 1 | G61: ='TOTAL STOCK'!G61-'CLOSING STOCK'!G61 -> 0 | H61: ='TOTAL STOCK'!H61-'CLOSING STOCK'!H61 -> 2 | I61: ='TOTAL STOCK'!I61-'CLOSING STOCK'!I61 -> 0 | J61: ='TOTAL STOCK'!J61-'CLOSING STOCK'!J61 -> 0 | ... L61: ='TOTAL STOCK'!L61-'CLOSING STOCK'!L61 -> 0 | M61: =(C61*12*N61)+(D61*N61)+(E61*24*O61)+(F61*O61)+(G61*48*P61)+(H61*P61)+(I61*96*Q61)+(J61*Q61)+(K61*25*R61)+(L61*R61) -> 380 | N61: 360 | O61: 180 | P61: 100
A62: 9 | B62: VEGA WINE | C62: ='TOTAL STOCK'!C62-'CLOSING STOCK'!C62 -> 0 | D62: ='TOTAL STOCK'!D62-'CLOSING STOCK'!D62 -> 0 | E62: ='TOTAL STOCK'!E62-'CLOSING STOCK'!E62 -> 0 | F62: ='TOTAL STOCK'!F62-'CLOSING STOCK'!F62 -> 0 | G62: ='TOTAL STOCK'!G62-'CLOSING STOCK'!G62 -> 0 | H62: ='TOTAL STOCK'!H62-'CLOSING STOCK'!H62 -> 0 | I62: ='TOTAL STOCK'!I62-'CLOSING STOCK'!I62 -> 0 | J62: ='TOTAL STOCK'!J62-'CLOSING STOCK'!J62 -> 0 | ... L62: ='TOTAL STOCK'!L62-'CLOSING STOCK'!L62 -> 0 | M62: =(C62*12*N62)+(D62*N62)+(E62*24*O62)+(F62*O62)+(G62*48*P62)+(H62*P62)+(I62*96*Q62)+(J62*Q62)+(K62*25*R62)+(L62*R62) -> 0 | N62: 300 | O62: 150 | P62: 100
A63: 10 | B63: 0 | C63: ='TOTAL STOCK'!C63-'CLOSING STOCK'!C63 -> 0 | D63: ='TOTAL STOCK'!D63-'CLOSING STOCK'!D63 -> 0 | E63: ='TOTAL STOCK'!E63-'CLOSING STOCK'!E63 -> 0 | F63: ='TOTAL STOCK'!F63-'CLOSING STOCK'!F63 -> 0 | G63: ='TOTAL STOCK'!G63-'CLOSING STOCK'!G63 -> 0 | H63: ='TOTAL STOCK'!H63-'CLOSING STOCK'!H63 -> 0 | I63: ='TOTAL STOCK'!I63-'CLOSING STOCK'!I63 -> 0 | J63: ='TOTAL STOCK'!J63-'CLOSING STOCK'!J63 -> 0 | ... L63: ='TOTAL STOCK'!L63-'CLOSING STOCK'!L63 -> 0 | M63: =(C63*12*N63)+(D63*N63)+(E63*24*O63)+(F63*O63)+(G63*48*P63)+(H63*P63)+(I63*96*Q63)+(J63*Q63)+(K63*25*R63)+(L63*R63) -> 0 | N63: 850 | O63: 450 | P63: 50
A64: 11 | B64: MAGIC MOMENTS | C64: ='TOTAL STOCK'!C64-'CLOSING STOCK'!C64 -> 0 | D64: ='TOTAL STOCK'!D64-'CLOSING STOCK'!D64 -> 0 | E64: ='TOTAL STOCK'!E64-'CLOSING STOCK'!E64 -> 0 | F64: ='TOTAL STOCK'!F64-'CLOSING STOCK'!F64 -> 0 | G64: ='TOTAL STOCK'!G64-'CLOSING STOCK'!G64 -> 1 | H64: ='TOTAL STOCK'!H64-'CLOSING STOCK'!H64 -> -31 | I64: ='TOTAL STOCK'!I64-'CLOSING STOCK'!I64 -> 0 | J64: ='TOTAL STOCK'!J64-'CLOSING STOCK'!J64 -> 0 | ... L64: ='TOTAL STOCK'!L64-'CLOSING STOCK'!L64 -> -20 | M64: =(C64*12*N64)+(D64*N64)+(E64*24*O64)+(F64*O64)+(G64*48*P64)+(H64*P64)+(I64*96*Q64)+(J64*Q64)+(K64*25*R64)+(L64*R64) -> 6600 | N64: 1400 | O64: 700 | P64: 350 | R64: 130
A65: 12 | B65: BRO CODE | C65: ='TOTAL STOCK'!C65-'CLOSING STOCK'!C65 -> 0 | D65: ='TOTAL STOCK'!D65-'CLOSING STOCK'!D65 -> 0 | E65: ='TOTAL STOCK'!E65-'CLOSING STOCK'!E65 -> 0 | F65: ='TOTAL STOCK'!F65-'CLOSING STOCK'!F65 -> 26 | G65: ='TOTAL STOCK'!G65-'CLOSING STOCK'!G65 -> 0 | H65: ='TOTAL STOCK'!H65-'CLOSING STOCK'!H65 -> 0 | I65: ='TOTAL STOCK'!I65-'CLOSING STOCK'!I65 -> 0 | J65: ='TOTAL STOCK'!J65-'CLOSING STOCK'!J65 -> 0 | ... L65: ='TOTAL STOCK'!L65-'CLOSING STOCK'!L65 -> 0 | M65: =(C65*12*N65)+(D65*N65)+(E65*24*O65)+(F65*O65)+(G65*48*P65)+(H65*P65)+(I65*96*Q65)+(J65*Q65)+(K65*25*R65)+(L65*R65) -> 3640 | N65: 140 | O65: 140 | P65: 140
A66: 13 | B66: TANGO RED WINE | C66: ='TOTAL STOCK'!C66-'CLOSING STOCK'!C66 -> 0 | D66: ='TOTAL STOCK'!D66-'CLOSING STOCK'!D66 -> 0 | E66: ='TOTAL STOCK'!E66-'CLOSING STOCK'!E66 -> 0 | F66: ='TOTAL STOCK'!F66-'CLOSING STOCK'!F66 -> 0 | G66: ='TOTAL STOCK'!G66-'CLOSING STOCK'!G66 -> 0 | H66: ='TOTAL STOCK'!H66-'CLOSING STOCK'!H66 -> 0 | I66: ='TOTAL STOCK'!I66-'CLOSING STOCK'!I66 -> 0 | J66: ='TOTAL STOCK'!J66-'CLOSING STOCK'!J66 -> 0 | ... L66: ='TOTAL STOCK'!L66-'CLOSING STOCK'!L66 -> 0 | M66: =(C66*12*N66)+(D66*N66)+(E66*24*O66)+(F66*O66)+(G66*48*P66)+(H66*P66)+(I66*96*Q66)+(J66*Q66)+(K66*25*R66)+(L66*R66) -> 0 | N66: 180 | O66: 100 | P66: 50
A67: 14 | B67: BUZZ BALL | C67: ='TOTAL STOCK'!C67-'CLOSING STOCK'!C67 -> 0 | D67: ='TOTAL STOCK'!D67-'CLOSING STOCK'!D67 -> 0 | E67: ='TOTAL STOCK'!E67-'CLOSING STOCK'!E67 -> 0 | F67: ='TOTAL STOCK'!F67-'CLOSING STOCK'!F67 -> 0 | G67: ='TOTAL STOCK'!G67-'CLOSING STOCK'!G67 -> 1 | H67: ='TOTAL STOCK'!H67-'CLOSING STOCK'!H67 -> 0 | I67: ='TOTAL STOCK'!I67-'CLOSING STOCK'!I67 -> 0 | J67: ='TOTAL STOCK'!J67-'CLOSING STOCK'!J67 -> 0 | ... L67: ='TOTAL STOCK'!L67-'CLOSING STOCK'!L67 -> 0 | M67: =(C67*12*N67)+(D67*N67)+(E67*24*O67)+(F67*O67)+(G67*48*P67)+(H67*P67)+(I67*96*Q67)+(J67*Q67)+(K67*25*R67)+(L67*R67) -> 5760 | N67: 480 | O67: 240 | P67: 120
A68: 15 | C68: ='TOTAL STOCK'!C68-'CLOSING STOCK'!C68 -> 0 | D68: ='TOTAL STOCK'!D68-'CLOSING STOCK'!D68 -> 0 | E68: ='TOTAL STOCK'!E68-'CLOSING STOCK'!E68 -> 0 | F68: ='TOTAL STOCK'!F68-'CLOSING STOCK'!F68 -> 0 | G68: ='TOTAL STOCK'!G68-'CLOSING STOCK'!G68 -> 0 | H68: ='TOTAL STOCK'!H68-'CLOSING STOCK'!H68 -> 0 | I68: ='TOTAL STOCK'!I68-'CLOSING STOCK'!I68 -> 0 | J68: ='TOTAL STOCK'!J68-'CLOSING STOCK'!J68 -> 0 | ... L68: ='TOTAL STOCK'!L68-'CLOSING STOCK'!L68 -> 0 | M68: =(C68*12*N68)+(D68*N68)+(E68*24*O68)+(F68*O68)+(G68*48*P68)+(H68*P68)+(I68*96*Q68)+(J68*Q68)+(K68*25*R68)+(L68*R68) -> 0
A69: 16 | C69: ='TOTAL STOCK'!C69-'CLOSING STOCK'!C69 -> 0 | D69: ='TOTAL STOCK'!D69-'CLOSING STOCK'!D69 -> 0 | E69: ='TOTAL STOCK'!E69-'CLOSING STOCK'!E69 -> 0 | F69: ='TOTAL STOCK'!F69-'CLOSING STOCK'!F69 -> 0 | G69: ='TOTAL STOCK'!G69-'CLOSING STOCK'!G69 -> 0 | H69: ='TOTAL STOCK'!H69-'CLOSING STOCK'!H69 -> 0 | I69: ='TOTAL STOCK'!I69-'CLOSING STOCK'!I69 -> 0 | J69: ='TOTAL STOCK'!J69-'CLOSING STOCK'!J69 -> 0 | ... L69: ='TOTAL STOCK'!L69-'CLOSING STOCK'!L69 -> 0 | M69: =(C69*12*N69)+(D69*N69)+(E69*24*O69)+(F69*O69)+(G69*48*P69)+(H69*P69)+(I69*96*Q69)+(J69*Q69)+(K69*25*R69)+(L69*R69) -> 0
A70: 17 | C70: ='TOTAL STOCK'!C70-'CLOSING STOCK'!C70 -> 0 | D70: ='TOTAL STOCK'!D70-'CLOSING STOCK'!D70 -> 0 | E70: ='TOTAL STOCK'!E70-'CLOSING STOCK'!E70 -> 0 | F70: ='TOTAL STOCK'!F70-'CLOSING STOCK'!F70 -> 0 | G70: ='TOTAL STOCK'!G70-'CLOSING STOCK'!G70 -> 0 | H70: ='TOTAL STOCK'!H70-'CLOSING STOCK'!H70 -> 0 | I70: ='TOTAL STOCK'!I70-'CLOSING STOCK'!I70 -> 0 | J70: ='TOTAL STOCK'!J70-'CLOSING STOCK'!J70 -> 0 | ... L70: ='TOTAL STOCK'!L70-'CLOSING STOCK'!L70 -> 0 | M70: =(C70*12*N70)+(D70*N70)+(E70*24*O70)+(F70*O70)+(G70*48*P70)+(H70*P70)+(I70*96*Q70)+(J70*Q70)+(K70*25*R70)+(L70*R70) -> 0
A71: 18 | C71: ='TOTAL STOCK'!C71-'CLOSING STOCK'!C71 -> 0 | D71: ='TOTAL STOCK'!D71-'CLOSING STOCK'!D71 -> 0 | E71: ='TOTAL STOCK'!E71-'CLOSING STOCK'!E71 -> 0 | F71: ='TOTAL STOCK'!F71-'CLOSING STOCK'!F71 -> 0 | G71: ='TOTAL STOCK'!G71-'CLOSING STOCK'!G71 -> 0 | H71: ='TOTAL STOCK'!H71-'CLOSING STOCK'!H71 -> 0 | I71: ='TOTAL STOCK'!I71-'CLOSING STOCK'!I71 -> 0 | J71: ='TOTAL STOCK'!J71-'CLOSING STOCK'!J71 -> 0 | ... L71: ='TOTAL STOCK'!L71-'CLOSING STOCK'!L71 -> 0 | M71: =(C71*12*N71)+(D71*N71)+(E71*24*O71)+(F71*O71)+(G71*48*P71)+(H71*P71)+(I71*96*Q71)+(J71*Q71)+(K71*25*R71)+(L71*R71) -> 0
A72: BEERS | C72: SALES | N72: RATES
C73: 650 ML | E73: 500 ML TIN(CAN) | G73: 330 ML (PINT) | I73: 330 ML TIN(CAN) | N73: 650 ML | O73: 500 CAN | P73: 330 PINT | Q73: 330 CAN
A74: SL. | B74: PRODUCT NAME | C74: CASES*12 | D74: BTLS | E74: CASES*24 | F74: BTLS | G74: CASES*24 | H74: BTLS | I74: CASES*24 | J74: BTLS | N74: RATE | O74: RATE | P74: RATE | Q74: RATE
A75: 1 | B75: K.F PREMIUM | C75: ='TOTAL STOCK'!C75-'CLOSING STOCK'!C75 -> 1 | D75: ='TOTAL STOCK'!D75-'CLOSING STOCK'!D75 -> 15 | E75: ='TOTAL STOCK'!E75-'CLOSING STOCK'!E75 -> 0 | F75: ='TOTAL STOCK'!F75-'CLOSING STOCK'!F75 -> 0 | G75: ='TOTAL STOCK'!G75-'CLOSING STOCK'!G75 -> 0 | H75: ='TOTAL STOCK'!H75-'CLOSING STOCK'!H75 -> 0 | I75: ='TOTAL STOCK'!I75-'CLOSING STOCK'!I75 -> 0 | J75: ='TOTAL STOCK'!J75-'CLOSING STOCK'!J75 -> 0 | M75: =(C75*12*N75)+(D75*N75)+(E75*24*O75)+(F75*O75)+(G75*24*P75)+(H75*P75)+(I75*24*Q75)+(J75*Q75)+(K75*24*R75)+(L75*R75) -> 5940 | N75: 220 | O75: 160 | P75: 120 | Q75: 130
A76: 2 | B76: K.F STRONG | C76: ='TOTAL STOCK'!C76-'CLOSING STOCK'!C76 -> 39 | D76: ='TOTAL STOCK'!D76-'CLOSING STOCK'!D76 -> -10 | E76: ='TOTAL STOCK'!E76-'CLOSING STOCK'!E76 -> 2 | F76: ='TOTAL STOCK'!F76-'CLOSING STOCK'!F76 -> -33 | G76: ='TOTAL STOCK'!G76-'CLOSING STOCK'!G76 -> 3 | H76: ='TOTAL STOCK'!H76-'CLOSING STOCK'!H76 -> -9 | I76: ='TOTAL STOCK'!I76-'CLOSING STOCK'!I76 -> 1 | J76: ='TOTAL STOCK'!J76-'CLOSING STOCK'!J76 -> -13 | M76: =(C76*12*N76)+(D76*N76)+(E76*24*O76)+(F76*O76)+(G76*24*P76)+(H76*P76)+(I76*24*Q76)+(J76*Q76)+(K76*24*R76)+(L76*R76) -> 114440 | N76: 225 | O76: 160 | P76: 120 | Q76: 130
A77: 3 | B77: U.B EXPORT | C77: ='TOTAL STOCK'!C77-'CLOSING STOCK'!C77 -> 1 | D77: ='TOTAL STOCK'!D77-'CLOSING STOCK'!D77 -> 1 | E77: ='TOTAL STOCK'!E77-'CLOSING STOCK'!E77 -> 0 | F77: ='TOTAL STOCK'!F77-'CLOSING STOCK'!F77 -> 0 | G77: ='TOTAL STOCK'!G77-'CLOSING STOCK'!G77 -> 0 | H77: ='TOTAL STOCK'!H77-'CLOSING STOCK'!H77 -> 0 | I77: ='TOTAL STOCK'!I77-'CLOSING STOCK'!I77 -> 0 | J77: ='TOTAL STOCK'!J77-'CLOSING STOCK'!J77 -> 0 | M77: =(C77*12*N77)+(D77*N77)+(E77*24*O77)+(F77*O77)+(G77*24*P77)+(H77*P77)+(I77*24*Q77)+(J77*Q77)+(K77*24*R77)+(L77*R77) -> 2340 | N77: 180 | O77: 130 | P77: 100 | Q77: 90
A78: 4 | B78: KNOCK OUT | C78: ='TOTAL STOCK'!C78-'CLOSING STOCK'!C78 -> 5 | D78: ='TOTAL STOCK'!D78-'CLOSING STOCK'!D78 -> -10 | E78: ='TOTAL STOCK'!E78-'CLOSING STOCK'!E78 -> 0 | F78: ='TOTAL STOCK'!F78-'CLOSING STOCK'!F78 -> 0 | G78: ='TOTAL STOCK'!G78-'CLOSING STOCK'!G78 -> 1 | H78: ='TOTAL STOCK'!H78-'CLOSING STOCK'!H78 -> 7 | I78: ='TOTAL STOCK'!I78-'CLOSING STOCK'!I78 -> 0 | J78: ='TOTAL STOCK'!J78-'CLOSING STOCK'!J78 -> 0 | M78: =(C78*12*N78)+(D78*N78)+(E78*24*O78)+(F78*O78)+(G78*24*P78)+(H78*P78)+(I78*24*Q78)+(J78*Q78)+(K78*24*R78)+(L78*R78) -> 13910 | N78: 210 | O78: 160 | P78: 110 | Q78: 130
A79: 5 | B79: K.F STROM | C79: ='TOTAL STOCK'!C79-'CLOSING STOCK'!C79 -> 0 | D79: ='TOTAL STOCK'!D79-'CLOSING STOCK'!D79 -> 0 | E79: ='TOTAL STOCK'!E79-'CLOSING STOCK'!E79 -> 0 | F79: ='TOTAL STOCK'!F79-'CLOSING STOCK'!F79 -> 0 | G79: ='TOTAL STOCK'!G79-'CLOSING STOCK'!G79 -> 0 | H79: ='TOTAL STOCK'!H79-'CLOSING STOCK'!H79 -> 0 | I79: ='TOTAL STOCK'!I79-'CLOSING STOCK'!I79 -> 0 | J79: ='TOTAL STOCK'!J79-'CLOSING STOCK'!J79 -> 0 | M79: =(C79*12*N79)+(D79*N79)+(E79*24*O79)+(F79*O79)+(G79*24*P79)+(H79*P79)+(I79*24*Q79)+(J79*Q79)+(K79*24*R79)+(L79*R79) -> 0 | N79: 225 | O79: 160 | P79: 120 | Q79: 130
A80: 6 | B80: BUDWISER MAGNUM | C80: ='TOTAL STOCK'!C80-'CLOSING STOCK'!C80 -> 19 | D80: ='TOTAL STOCK'!D80-'CLOSING STOCK'!D80 -> -3 | E80: ='TOTAL STOCK'!E80-'CLOSING STOCK'!E80 -> 0 | F80: ='TOTAL STOCK'!F80-'CLOSING STOCK'!F80 -> 23 | G80: ='TOTAL STOCK'!G80-'CLOSING STOCK'!G80 -> 0 | H80: ='TOTAL STOCK'!H80-'CLOSING STOCK'!H80 -> 0 | I80: ='TOTAL STOCK'!I80-'CLOSING STOCK'!I80 -> 0 | J80: ='TOTAL STOCK'!J80-'CLOSING STOCK'!J80 -> 0 | M80: =(C80*12*N80)+(D80*N80)+(E80*24*O80)+(F80*O80)+(G80*24*P80)+(H80*P80)+(I80*24*Q80)+(J80*Q80)+(K80*24*R80)+(L80*R80) -> 66475 | N80: 275 | O80: 200 | P80: 135 | Q80: 140
A81: 7 | B81: BUDWISER PREM | C81: ='TOTAL STOCK'!C81-'CLOSING STOCK'!C81 -> 3 | D81: ='TOTAL STOCK'!D81-'CLOSING STOCK'!D81 -> -3 | E81: ='TOTAL STOCK'!E81-'CLOSING STOCK'!E81 -> 0 | F81: ='TOTAL STOCK'!F81-'CLOSING STOCK'!F81 -> 6 | G81: ='TOTAL STOCK'!G81-'CLOSING STOCK'!G81 -> 0 | H81: ='TOTAL STOCK'!H81-'CLOSING STOCK'!H81 -> 0 | I81: ='TOTAL STOCK'!I81-'CLOSING STOCK'!I81 -> 0 | J81: ='TOTAL STOCK'!J81-'CLOSING STOCK'!J81 -> 0 | M81: =(C81*12*N81)+(D81*N81)+(E81*24*O81)+(F81*O81)+(G81*24*P81)+(H81*P81)+(I81*24*Q81)+(J81*Q81)+(K81*24*R81)+(L81*R81) -> 9780 | N81: 260 | O81: 200 | P81: 135 | Q81: 140
A82: 8 | B82: K.F ULTRA/ WITT BEER | C82: ='TOTAL STOCK'!C82-'CLOSING STOCK'!C82 -> 0 | D82: ='TOTAL STOCK'!D82-'CLOSING STOCK'!D82 -> 22 | E82: ='TOTAL STOCK'!E82-'CLOSING STOCK'!E82 -> 0 | F82: ='TOTAL STOCK'!F82-'CLOSING STOCK'!F82 -> 0 | G82: ='TOTAL STOCK'!G82-'CLOSING STOCK'!G82 -> 0 | H82: ='TOTAL STOCK'!H82-'CLOSING STOCK'!H82 -> 0 | I82: ='TOTAL STOCK'!I82-'CLOSING STOCK'!I82 -> 0 | J82: ='TOTAL STOCK'!J82-'CLOSING STOCK'!J82 -> 0 | M82: =(C82*12*N82)+(D82*N82)+(E82*24*O82)+(F82*O82)+(G82*24*P82)+(H82*P82)+(I82*24*Q82)+(J82*Q82)+(K82*24*R82)+(L82*R82) -> 5720 | N82: 260 | O82: 200 | P82: 135 | Q82: 140
A83: 9 | B83: TOBURG STRONG BEER | C83: ='TOTAL STOCK'!C83-'CLOSING STOCK'!C83 -> 24 | D83: ='TOTAL STOCK'!D83-'CLOSING STOCK'!D83 -> 18 | E83: ='TOTAL STOCK'!E83-'CLOSING STOCK'!E83 -> 1 | F83: ='TOTAL STOCK'!F83-'CLOSING STOCK'!F83 -> -13 | G83: ='TOTAL STOCK'!G83-'CLOSING STOCK'!G83 -> 2 | H83: ='TOTAL STOCK'!H83-'CLOSING STOCK'!H83 -> -19 | I83: ='TOTAL STOCK'!I83-'CLOSING STOCK'!I83 -> 0 | J83: ='TOTAL STOCK'!J83-'CLOSING STOCK'!J83 -> 0 | M83: =(C83*12*N83)+(D83*N83)+(E83*24*O83)+(F83*O83)+(G83*24*P83)+(H83*P83)+(I83*24*Q83)+(J83*Q83)+(K83*24*R83)+(L83*R83) -> 74380 | N83: 225 | O83: 160 | P83: 130 | Q83: 130
A84: 10 | B84: POWERCOOL | C84: ='TOTAL STOCK'!C84-'CLOSING STOCK'!C84 -> 4 | D84: ='TOTAL STOCK'!D84-'CLOSING STOCK'!D84 -> 15 | E84: ='TOTAL STOCK'!E84-'CLOSING STOCK'!E84 -> 0 | F84: ='TOTAL STOCK'!F84-'CLOSING STOCK'!F84 -> 11 | G84: ='TOTAL STOCK'!G84-'CLOSING STOCK'!G84 -> 0 | H84: ='TOTAL STOCK'!H84-'CLOSING STOCK'!H84 -> 7 | I84: ='TOTAL STOCK'!I84-'CLOSING STOCK'!I84 -> 0 | J84: ='TOTAL STOCK'!J84-'CLOSING STOCK'!J84 -> 0 | M84: =(C84*12*N84)+(D84*N84)+(E84*24*O84)+(F84*O84)+(G84*24*P84)+(H84*P84)+(I84*24*Q84)+(J84*Q84)+(K84*24*R84)+(L84*R84) -> 12730 | N84: 170 | O84: 120 | P84: 100 | Q84: 100
A85: 11 | B85: BACARDI + | C85: ='TOTAL STOCK'!C85-'CLOSING STOCK'!C85 -> 0 | D85: ='TOTAL STOCK'!D85-'CLOSING STOCK'!D85 -> 0 | E85: ='TOTAL STOCK'!E85-'CLOSING STOCK'!E85 -> 0 | F85: ='TOTAL STOCK'!F85-'CLOSING STOCK'!F85 -> 0 | G85: ='TOTAL STOCK'!G85-'CLOSING STOCK'!G85 -> 3 | H85: ='TOTAL STOCK'!H85-'CLOSING STOCK'!H85 -> -28 | I85: ='TOTAL STOCK'!I85-'CLOSING STOCK'!I85 -> 0 | J85: ='TOTAL STOCK'!J85-'CLOSING STOCK'!J85 -> 0 | M85: =(C85*12*N85)+(D85*N85)+(E85*12*O85)+(F85*O85)+(G85*24*P85)+(H85*P85)+(I85*24*Q85)+(J85*Q85)+(K85*24*R85)+(L85*R85) -> 5720 | N85: 205 | O85: 205 | P85: 130 | Q85: 130
A86: 12 | B86: BACARDI BREEZER | C86: ='TOTAL STOCK'!C86-'CLOSING STOCK'!C86 -> 0 | D86: ='TOTAL STOCK'!D86-'CLOSING STOCK'!D86 -> 0 | E86: ='TOTAL STOCK'!E86-'CLOSING STOCK'!E86 -> 0 | F86: ='TOTAL STOCK'!F86-'CLOSING STOCK'!F86 -> 0 | G86: ='TOTAL STOCK'!G86-'CLOSING STOCK'!G86 -> 0 | H86: ='TOTAL STOCK'!H86-'CLOSING STOCK'!H86 -> 26 | I86: ='TOTAL STOCK'!I86-'CLOSING STOCK'!I86 -> 0 | J86: ='TOTAL STOCK'!J86-'CLOSING STOCK'!J86 -> 0 | M86: =(C86*12*N86)+(D86*N86)+(E86*24*O86)+(F86*O86)+(G86*24*P86)+(H86*P86)+(I86*24*Q86)+(J86*Q86)+(K86*24*R86)+(L86*R86) -> 4160 | N86: 160 | O86: 160 | P86: 160 | Q86: 160
A87: 13 | B87: RC / BULLET BEER | C87: ='TOTAL STOCK'!C87-'CLOSING STOCK'!C87 -> 6 | D87: ='TOTAL STOCK'!D87-'CLOSING STOCK'!D87 -> 17 | E87: ='TOTAL STOCK'!E87-'CLOSING STOCK'!E87 -> 0 | F87: ='TOTAL STOCK'!F87-'CLOSING STOCK'!F87 -> 20 | G87: ='TOTAL STOCK'!G87-'CLOSING STOCK'!G87 -> 0 | H87: ='TOTAL STOCK'!H87-'CLOSING STOCK'!H87 -> 0 | I87: ='TOTAL STOCK'!I87-'CLOSING STOCK'!I87 -> 0 | J87: ='TOTAL STOCK'!J87-'CLOSING STOCK'!J87 -> 0 | M87: =(C87*12*N87)+(D87*N87)+(E87*24*O87)+(F87*O87)+(G87*24*P87)+(H87*P87)+(I87*24*Q87)+(J87*Q87)+(K87*24*R87)+(L87*R87) -> 14860 | N87: 140 | O87: 120 | P87: 90 | Q87: 90
A88: 14 | B88: HUNTER | C88: ='TOTAL STOCK'!C88-'CLOSING STOCK'!C88 -> 0 | D88: ='TOTAL STOCK'!D88-'CLOSING STOCK'!D88 -> 0 | E88: ='TOTAL STOCK'!E88-'CLOSING STOCK'!E88 -> 0 | F88: ='TOTAL STOCK'!F88-'CLOSING STOCK'!F88 -> 0 | G88: ='TOTAL STOCK'!G88-'CLOSING STOCK'!G88 -> 0 | H88: ='TOTAL STOCK'!H88-'CLOSING STOCK'!H88 -> 0 | I88: ='TOTAL STOCK'!I88-'CLOSING STOCK'!I88 -> 0 | J88: ='TOTAL STOCK'!J88-'CLOSING STOCK'!J88 -> 0 | M88: =(C88*12*N88)+(D88*N88)+(E88*24*O88)+(F88*O88)+(G88*24*P88)+(H88*P88)+(I88*24*Q88)+(J88*Q88)+(K88*24*R88)+(L88*R88) -> 0 | N88: 220 | O88: 160 | P88: 120 | Q88: 130
A89: 15 | B89: CARLSBERG ELE STRONG | C89: ='TOTAL STOCK'!C89-'CLOSING STOCK'!C89 -> 10 | D89: ='TOTAL STOCK'!D89-'CLOSING STOCK'!D89 -> -14 | E89: ='TOTAL STOCK'!E89-'CLOSING STOCK'!E89 -> 1 | F89: ='TOTAL STOCK'!F89-'CLOSING STOCK'!F89 -> -24 | G89: ='TOTAL STOCK'!G89-'CLOSING STOCK'!G89 -> 0 | H89: ='TOTAL STOCK'!H89-'CLOSING STOCK'!H89 -> 0 | I89: ='TOTAL STOCK'!I89-'CLOSING STOCK'!I89 -> 0 | J89: ='TOTAL STOCK'!J89-'CLOSING STOCK'!J89 -> 0 | M89: =(C89*12*N89)+(D89*N89)+(E89*24*O89)+(F89*O89)+(G89*24*P89)+(H89*P89)+(I89*24*Q89)+(J89*Q89)+(K89*24*R89)+(L89*R89) -> 29680 | N89: 280 | O89: 210 | P89: 140 | Q89: 140
A90: 16 | B90: SUNNY STRONG | C90: ='TOTAL STOCK'!C90-'CLOSING STOCK'!C90 -> 5 | D90: ='TOTAL STOCK'!D90-'CLOSING STOCK'!D90 -> 0 | E90: ='TOTAL STOCK'!E90-'CLOSING STOCK'!E90 -> 0 | F90: ='TOTAL STOCK'!F90-'CLOSING STOCK'!F90 -> 0 | G90: ='TOTAL STOCK'!G90-'CLOSING STOCK'!G90 -> 0 | H90: ='TOTAL STOCK'!H90-'CLOSING STOCK'!H90 -> 0 | I90: ='TOTAL STOCK'!I90-'CLOSING STOCK'!I90 -> 0 | J90: ='TOTAL STOCK'!J90-'CLOSING STOCK'!J90 -> 0 | M90: =(C90*12*N90)+(D90*N90)+(E90*24*O90)+(F90*O90)+(G90*24*P90)+(H90*P90)+(I90*24*Q90)+(J90*Q90)+(K90*24*R90)+(L90*R90) -> 7800 | N90: 130 | O90: 120 | P90: 120 | Q90: 120
A91: 17 | B91: FOSTERS BEER | C91: ='TOTAL STOCK'!C91-'CLOSING STOCK'!C91 -> 0 | D91: ='TOTAL STOCK'!D91-'CLOSING STOCK'!D91 -> 0 | E91: ='TOTAL STOCK'!E91-'CLOSING STOCK'!E91 -> 0 | F91: ='TOTAL STOCK'!F91-'CLOSING STOCK'!F91 -> 0 | G91: ='TOTAL STOCK'!G91-'CLOSING STOCK'!G91 -> 0 | H91: ='TOTAL STOCK'!H91-'CLOSING STOCK'!H91 -> 0 | I91: ='TOTAL STOCK'!I91-'CLOSING STOCK'!I91 -> 0 | J91: ='TOTAL STOCK'!J91-'CLOSING STOCK'!J91 -> 0 | M91: =(C91*12*N91)+(D91*N91)+(E91*24*O91)+(F91*O91)+(G91*24*P91)+(H91*P91)+(I91*24*Q91)+(J91*Q91)+(K91*24*R91)+(L91*R91) -> 0 | N91: 200 | O91: 150 | P91: 90 | Q91: 90
A92: 18 | B92: HEINEKEN BEER | C92: ='TOTAL STOCK'!C92-'CLOSING STOCK'!C92 -> 0 | D92: ='TOTAL STOCK'!D92-'CLOSING STOCK'!D92 -> 0 | E92: ='TOTAL STOCK'!E92-'CLOSING STOCK'!E92 -> 0 | F92: ='TOTAL STOCK'!F92-'CLOSING STOCK'!F92 -> 0 | G92: ='TOTAL STOCK'!G92-'CLOSING STOCK'!G92 -> 0 | H92: ='TOTAL STOCK'!H92-'CLOSING STOCK'!H92 -> 0 | I92: ='TOTAL STOCK'!I92-'CLOSING STOCK'!I92 -> 0 | J92: ='TOTAL STOCK'!J92-'CLOSING STOCK'!J92 -> 0 | M92: =(C92*12*N92)+(D92*N92)+(E92*24*O92)+(F92*O92)+(G92*24*P92)+(H92*P92)+(I92*24*Q92)+(J92*Q92)+(K92*24*R92)+(L92*R92) -> 0 | N92: 300 | O92: 220 | P92: 200 | Q92: 200
A93: 19 | B93: TUBORG CLASSIC | C93: ='TOTAL STOCK'!C93-'CLOSING STOCK'!C93 -> 0 | D93: ='TOTAL STOCK'!D93-'CLOSING STOCK'!D93 -> 9 | E93: ='TOTAL STOCK'!E93-'CLOSING STOCK'!E93 -> 0 | F93: ='TOTAL STOCK'!F93-'CLOSING STOCK'!F93 -> 0 | G93: ='TOTAL STOCK'!G93-'CLOSING STOCK'!G93 -> 0 | H93: ='TOTAL STOCK'!H93-'CLOSING STOCK'!H93 -> 0 | I93: ='TOTAL STOCK'!I93-'CLOSING STOCK'!I93 -> 0 | J93: ='TOTAL STOCK'!J93-'CLOSING STOCK'!J93 -> 0 | M93: =(C93*12*N93)+(D93*N93)+(E93*24*O93)+(F93*O93)+(G93*24*P93)+(H93*P93)+(I93*24*Q93)+(J93*Q93)+(K93*24*R93)+(L93*R93) -> 2520 | N93: 280 | O93: 215 | P93: 160 | Q93: 160
A94: 20 | C94: ='TOTAL STOCK'!C94-'CLOSING STOCK'!C94 -> 0 | D94: ='TOTAL STOCK'!D94-'CLOSING STOCK'!D94 -> 0 | E94: ='TOTAL STOCK'!E94-'CLOSING STOCK'!E94 -> 0 | F94: ='TOTAL STOCK'!F94-'CLOSING STOCK'!F94 -> 0 | G94: ='TOTAL STOCK'!G94-'CLOSING STOCK'!G94 -> 0 | H94: ='TOTAL STOCK'!H94-'CLOSING STOCK'!H94 -> 0 | I94: ='TOTAL STOCK'!I94-'CLOSING STOCK'!I94 -> 0 | J94: ='TOTAL STOCK'!J94-'CLOSING STOCK'!J94 -> 0 | M94: =(C94*12*N94)+(D94*N94)+(E94*24*O94)+(F94*O94)+(G94*24*P94)+(H94*P94)+(I94*24*Q94)+(J94*Q94)+(K94*24*R94)+(L94*R94) -> 0
A95: BEVERAGES | C95: SALES | N95: RATES
C96: 2 LTRS | E96: 1 LTRS | G96: 500 ML-600 ML | I96: 250 ML | N96: 2 LTRS | O96: 1 LTRS | P96: 0.5-0.6L | Q96: 0.3-.25L
A97: SL. | B97: PRODUCT NAME | C97: CASES*9 | D97: BTLS | E97: CASES*12 | F97: BTLS | G97: CASES*24 | H97: BTLS | I97: CASES*30 | J97: BTLS | N97: RATE | O97: RATE | P97: RATE | Q97: RATE
A98: 1 | B98: COOL DRINKS | C98: ='TOTAL STOCK'!C98-'CLOSING STOCK'!C98 -> 0 | D98: ='TOTAL STOCK'!D98-'CLOSING STOCK'!D98 -> 0 | E98: ='TOTAL STOCK'!E98-'CLOSING STOCK'!E98 -> 0 | F98: ='TOTAL STOCK'!F98-'CLOSING STOCK'!F98 -> 0 | G98: ='TOTAL STOCK'!G98-'CLOSING STOCK'!G98 -> 4 | H98: ='TOTAL STOCK'!H98-'CLOSING STOCK'!H98 -> 48 | I98: ='TOTAL STOCK'!I98-'CLOSING STOCK'!I98 -> 7 | J98: ='TOTAL STOCK'!J98-'CLOSING STOCK'!J98 -> -5 | M98: =(C98*9*N98)+(D98*N98)+(E98*12*O98)+(F98*O98)+(G98*24*P98)+(H98*P98)+(I98*30*Q98)+(J98*Q98)+(K98*25*R98)+(L98*R98) -> 9860 | N98: 80 | O98: 45 | P98: 40 | Q98: 20
A99: 2 | B99: SODA*12/REDBULL*24 | C99: ='TOTAL STOCK'!C99-'CLOSING STOCK'!C99 -> 0 | D99: ='TOTAL STOCK'!D99-'CLOSING STOCK'!D99 -> 0 | E99: ='TOTAL STOCK'!E99-'CLOSING STOCK'!E99 -> 0 | F99: ='TOTAL STOCK'!F99-'CLOSING STOCK'!F99 -> 0 | G99: ='TOTAL STOCK'!G99-'CLOSING STOCK'!G99 -> 7 | H99: ='TOTAL STOCK'!H99-'CLOSING STOCK'!H99 -> 5 | I99: ='TOTAL STOCK'!I99-'CLOSING STOCK'!I99 -> 1 | J99: ='TOTAL STOCK'!J99-'CLOSING STOCK'!J99 -> -5 | M99: =(C99*9*N99)+(D99*N99)+(E99*12*O99)+(F99*O99)+(G99*12*P99)+(H99*P99)+(I99*24*Q99)+(J99*Q99)+(K99*25*R99)+(L99*R99) -> 4060 | P99: 20 | Q99: 120
A100: 3 | B100: MIN WATER | C100: ='TOTAL STOCK'!C100-'CLOSING STOCK'!C100 -> 9 | D100: ='TOTAL STOCK'!D100-'CLOSING STOCK'!D100 -> 0 | E100: ='TOTAL STOCK'!E100-'CLOSING STOCK'!E100 -> 68 | F100: ='TOTAL STOCK'!F100-'CLOSING STOCK'!F100 -> -1 | G100: ='TOTAL STOCK'!G100-'CLOSING STOCK'!G100 -> 25 | H100: ='TOTAL STOCK'!H100-'CLOSING STOCK'!H100 -> 71 | I100: ='TOTAL STOCK'!I100-'CLOSING STOCK'!I100 -> 0 | J100: ='TOTAL STOCK'!J100-'CLOSING STOCK'!J100 -> 0 | M100: =(C100*9*N100)+(D100*N100)+(E100*12*O100)+(F100*O100)+(G100*24*P100)+(H100*P100)+(I100*30*Q100)+(J100*Q100)+(K100*25*R100)+(L100*R100) -> 25845 | N100: 35 | O100: 20 | P100: 10
...

Sheet EXPENDITURE
A1: DATE | B1: PARTICULARS | C1: AMOUNT
C2: 147440
B10: TOTAL | C10: =SUM(C2:C9) -> 147440
